Workbook
Name DATOS: Datos!$B$2:$S$17

Sheet PS1 (17)
A1: BOLETA DE PAGO | W1: EMPLEADO | X1: # AG ESSALUD | Y1: CODIGO EMPRESA
A2: EMPRESA | B2: CLARKE, MODET & CO. PERU S.A.C. | E2: R.U.C. | F2: 20256396000 | G2: MES | H2: =Detallado!R2 -> 05 | I2: AÑO | J2: =Detallado!S2 -> 2026 | K2: F. INGRESO | L2: =VLOOKUP(A6,'BD Total'!$A$2:$EZ$17,11,FALSE) -> 45740 | O2: # | P2: 1 | W2: 1007874085 | X2: 260130RRCOI9 | Y2: 07874085
E3: PERIODO | F3: =VLOOKUP($A$6,Detallado!$C:$U,16,FALSE) -> 05 | G3: DEL | H3: =VLOOKUP($A$6,Detallado!$C:$U,18,FALSE) -> 01/05/2026 | I3: AL | J3: =VLOOKUP($A$6,Detallado!$C:$U,19,FALSE) -> 46173 | K3: F. RETIRO | W3: 1040703418 | X3: 595200FCCCA8 | Y3: 40703418
W4: 1044771836 | X4: 621441RFSRR2 | Y4: 44771836
A5: CÓDIGO | B5: NOMBRES Y APELLIDOS | E5: CARGO | I5: AREA | W5: 1045191394 | X5: 322431AABAT4 | Y5: 45191394
A6: 76607245 | B6: =VLOOKUP(A6,Dev!$C$1:$D$88,2,FALSE) -> STEFFANY FELICIA CAICEDO ROSADO | E6: =VLOOKUP(A6,'BD Total'!$A$2:$EZ$18,77,FALSE) -> BECARIA | I6: =VLOOKUP(A6,'BD Total'!$A$2:$EZ$18,81,FALSE) -> FACILITES | W6: 1046129072 | X6: 628890LLCAD9 | Y6: 46129072
A7: D.N.I. | B7: CUSPP AFP | C7: # AG ESSALUD | E7: SALARIO | G7: MONEDA | I7: CODIGO EMPRESA | K7: A.F.P. | W7: 1046722547 | X7: 632311FKROJ0 | Y7: 46722547
A8: =VLOOKUP(A6,'BD Total'!$A$2:$EZ$18,2,FALSE) -> 76607245 | B8: =VLOOKUP(A6,'BD Total'!$A$2:$EZ$18,85,FALSE) -> FACILITIES | C8: =VLOOKUP(A6,$W$1:$Y$20,2,FALSE) -> N/A | E8: =VLOOKUP(A6,'BD Total'!$A$2:$EZ$18,22,FALSE) -> 1130 | G8: SOL | I8: =VLOOKUP(A6,$W$1:$Y$20,3,FALSE) -> 76607245 | K8: =VLOOKUP(A6,'BD Total'!$A$2:$EZ$18,101,FALSE) | W8: 1047924040 | X8: 641640MNERI3 | Y8: 47924040
W9: 1070165336 | X9: 640621VFCNT9 | Y9: 70165336
A10: REMUNERACIONES | E10: DESCUENTOS TRABAJADOR | I10: APORTACIONES EMPLEADOR | W10: 1070680748 | X10: 0 | Y10: 70680748
A11: CONCEPTO | C11: HORAS | D11: VALOR | E11: CONCEPTO | G11: HORAS | H11: VALOR | I11: CONCEPTO | K11: HORAS | L11: VALOR | W11: 1072251509 | X11: 631390CHTMR2 | Y11: 72251509
A12: A006 SUBVENCION ECONOMICA | C12: =SUMIF(Dev!$B:$B,CONCATENATE($A$6,A12),Dev!$L:$L) -> 216 | D12: =SUMIF(Dev!$B:$B,CONCATENATE($A$6,A12),Dev!M:M) -> 1017 | I12: APORTE A ESSALUD | K12: 0 | L12: =VLOOKUP(A6,ESSALUD!$B$1:$G$19,6,FALSE) -> 0 | W12: 1077485287 | X12: 655610ZCBIT4 | Y12: 77485287
A13: G006 VACACIONES | C13: =SUMIF(Dev!$B:$B,CONCATENATE($A$6,A13),Dev!$L:$L) -> 24 | D13: =SUMIF(Dev!$B:$B,CONCATENATE($A$6,A13),Dev!M:M) -> 113 | I13: CREDITO EPS | K13: 0 | L13: =VLOOKUP(A6,ESSALUD!$B$1:$H$19,7,FALSE) -> 0 | W13: 2001252358 | X13: 627991JMXQX0 | Y13: 001252358
W14: 42115329 | X14: FACILITIES | Y14: 42115329
W15: 42683912 | X15: 309631GHMAI4 | Y15: 42683912
W16: 72836862 | X16: 663680JMDIO1 | Y16: 72836862
W17: 76607245 | X17: N/A | Y17: 76607245
W18: 74026184 | X18: N/A | Y18: 74026184
I25: TOTAL APORTE EMPLEADOR | L25: =SUM(L12:L24) -> 0
A26: REMUNERACION TOTAL | D26: =SUM(D12:D24) -> 1130 | E26: DESCUENTOS TOTALES | H26: =SUM(H12:H24) -> 0 | I26: REMUNERACION NETA | L26: =+D26-H26 -> 1130
F36: REPRESENTANTE LEGAL | J36: RECIBI CONFORME TRABAJADOR

Sheet PS1 (16)
A1: BOLETA DE PAGO | W1: EMPLEADO | X1: # AG ESSALUD | Y1: CODIGO EMPRESA
A2: EMPRESA | B2: CLARKE, MODET & CO. PERU S.A.C. | E2: R.U.C. | F2: 20256396000 | G2: MES | H2: =Detallado!R2 -> 05 | I2: AÑO | J2: =Detallado!S2 -> 2026 | K2: F. INGRESO | L2: =VLOOKUP(A6,'BD Total'!$A$2:$EZ$17,11,FALSE) -> #N/A | O2: # | P2: 1 | W2: 1007874085 | X2: 260130RRCOI9 | Y2: 07874085
E3: PERIODO | F3: =VLOOKUP($A$6,Detallado!$C:$U,16,FALSE) -> 05 | G3: DEL | H3: =VLOOKUP($A$6,Detallado!$C:$U,18,FALSE) -> 01/05/2026 | I3: AL | J3: =VLOOKUP($A$6,Detallado!$C:$U,19,FALSE) -> 46173 | K3: F. RETIRO | W3: 1040703418 | X3: 595200FCCCA8 | Y3: 40703418
W4: 1044771836 | X4: 621441RFSRR2 | Y4: 44771836
A5: CÓDIGO | B5: NOMBRES Y APELLIDOS | E5: CARGO | I5: AREA | W5: 1045191394 | X5: 322431AABAT4 | Y5: 45191394
A6: 74026184 | B6: =VLOOKUP(A6,Dev!$C$1:$D$88,2,FALSE) -> JACKELINE TAMARA FAJARDO APOLAYA | E6: =VLOOKUP(A6,'BD Total'!$A$2:$EZ$18,77,FALSE) -> BECARIA | I6: =VLOOKUP(A6,'BD Total'!$A$2:$EZ$18,81,FALSE) -> FACILITES | W6: 1046129072 | X6: 628890LLCAD9 | Y6: 46129072
A7: D.N.I. | B7: CUSPP AFP | C7: # AG ESSALUD | E7: SALARIO | G7: MONEDA | I7: CODIGO EMPRESA | K7: A.F.P. | W7: 1046722547 | X7: 632311FKROJ0 | Y7: 46722547
A8: =VLOOKUP(A6,'BD Total'!$A$2:$EZ$18,2,FALSE) -> 74026184 | B8: =VLOOKUP(A6,'BD Total'!$A$2:$EZ$18,85,FALSE) -> FACILITIES | C8: =VLOOKUP(A6,$W$1:$Y$20,2,FALSE) -> N/A | E8: =VLOOKUP(A6,'BD Total'!$A$2:$EZ$18,22,FALSE) -> 1130 | G8: SOL | I8: =VLOOKUP(A6,$W$1:$Y$20,3,FALSE) -> 74026184 | K8: =VLOOKUP(A6,'BD Total'!$A$2:$EZ$18,101,FALSE) | W8: 1047924040 | X8: 641640MNERI3 | Y8: 47924040
W9: 1070165336 | X9: 640621VFCNT9 | Y9: 70165336
A10: REMUNERACIONES | E10: DESCUENTOS TRABAJADOR | I10: APORTACIONES EMPLEADOR | W10: 1070680748 | X10: 0 | Y10: 70680748
A11: CONCEPTO | C11: HORAS | D11: VALOR | E11: CONCEPTO | G11: HORAS | H11: VALOR | I11: CONCEPTO | K11: HORAS | L11: VALOR | W11: 1072251509 | X11: 631390CHTMR2 | Y11: 72251509
A12: A006 SUBVENCION ECONOMICA | C12: =SUMIF(Dev!$B:$B,CONCATENATE($A$6,A12),Dev!$L:$L) -> 160 | D12: =SUMIF(Dev!$B:$B,CONCATENATE($A$6,A12),Dev!M:M) -> 753.33 | I12: APORTE A ESSALUD | K12: 0 | L12: =VLOOKUP(A6,ESSALUD!$B$1:$G$19,6,FALSE) -> 0 | W12: 1077485287 | X12: 655610ZCBIT4 | Y12: 77485287
I13: CREDITO EPS | K13: 0 | L13: =VLOOKUP(A6,ESSALUD!$B$1:$H$19,7,FALSE) -> 0 | W13: 2001252358 | X13: 627991JMXQX0 | Y13: 001252358
W14: 42115329 | X14: FACILITIES | Y14: 42115329
W15: 42683912 | X15: 309631GHMAI4 | Y15: 42683912
W16: 72836862 | X16: 663680JMDIO1 | Y16: 72836862
W17: 76607245 | X17: N/A | Y17: 76607245
W18: 74026184 | X18: N/A | Y18: 74026184
I25: TOTAL APORTE EMPLEADOR | L25: =SUM(L12:L24) -> 0
A26: REMUNERACION TOTAL | D26: =SUM(D12:D24) -> 753.33 | E26: DESCUENTOS TOTALES | H26: =SUM(H12:H24) -> 0 | I26: REMUNERACION NETA | L26: =+D26-H26 -> 753.33
F36: REPRESENTANTE LEGAL | J36: RECIBI CONFORME TRABAJADOR

Sheet PS1 (15)
A1: BOLETA DE PAGO | W1: EMPLEADO | X1: # AG ESSALUD | Y1: CODIGO EMPRESA
A2: EMPRESA | B2: CLARKE, MODET & CO. PERU S.A.C. | E2: R.U.C. | F2: 20256396000 | G2: MES | H2: =Detallado!R2 -> 05 | I2: AÑO | J2: =Detallado!S2 -> 2026 | K2: F. INGRESO | L2: =VLOOKUP(A6,'BD Total'!$A$2:$EZ$17,11,FALSE) -> 45208 | O2: # | P2: 1 | W2: 1007874085 | X2: 260130RRCOI9 | Y2: 07874085
E3: PERIODO | F3: =VLOOKUP($A$6,Detallado!$C:$U,16,FALSE) -> 05 | G3: DEL | H3: =VLOOKUP($A$6,Detallado!$C:$U,18,FALSE) -> 01/05/2026 | I3: AL | J3: =VLOOKUP($A$6,Detallado!$C:$U,19,FALSE) -> 46173 | K3: F. RETIRO | W3: 1040703418 | X3: 595200FCCCA8 | Y3: 40703418
W4: 1044771836 | X4: 621441RFSRR2 | Y4: 44771836
A5: CÓDIGO | B5: NOMBRES Y APELLIDOS | E5: CARGO | I5: AREA | W5: 1045191394 | X5: 322431AABAT4 | Y5: 45191394
A6: 72836862 | B6: =VLOOKUP(A6,Dev!$C$1:$D$88,2,FALSE) -> JACKELINE NANCY MEJIA DOLORES | E6: =VLOOKUP(A6,'BD Total'!$A$2:$EZ$18,77,FALSE) -> IP PROCUREMENT SPECIALIST | I6: =VLOOKUP(A6,'BD Total'!$A$2:$EZ$18,81,FALSE) -> TRADEMARKS | W6: 1046129072 | X6: 628890LLCAD9 | Y6: 46129072
A7: D.N.I. | B7: CUSPP AFP | C7: # AG ESSALUD | E7: SALARIO | G7: MONEDA | I7: CODIGO EMPRESA | K7: A.F.P. | W7: 1046722547 | X7: 632311FKROJ0 | Y7: 46722547
A8: =VLOOKUP(A6,'BD Total'!$A$2:$EZ$18,2,FALSE) -> 72836862 | B8: =VLOOKUP(A6,'BD Total'!$A$2:$EZ$18,85,FALSE) -> 663680JMDIO1 | C8: =VLOOKUP(A6,$W$1:$Y$20,2,FALSE) -> 663680JMDIO1 | E8: =VLOOKUP(A6,'BD Total'!$A$2:$EZ$18,22,FALSE) -> 2652 | G8: SOL | I8: =VLOOKUP(A6,$W$1:$Y$20,3,FALSE) -> 72836862 | K8: =VLOOKUP(A6,'BD Total'!$A$2:$EZ$18,101,FALSE) -> INTEGRA | W8: 1047924040 | X8: 641640MNERI3 | Y8: 47924040
W9: 1070165336 | X9: 640621VFCNT9 | Y9: 70165336
A10: REMUNERACIONES | E10: DESCUENTOS TRABAJADOR | I10: APORTACIONES EMPLEADOR | W10: 1070680748 | X10: 0 | Y10: 70680748
A11: CONCEPTO | C11: HORAS | D11: VALOR | E11: CONCEPTO | G11: HORAS | H11: VALOR | I11: CONCEPTO | K11: HORAS | L11: VALOR | W11: 1072251509 | X11: 631390CHTMR2 | Y11: 72251509
A12: A000 SUELDO BASICO | C12: =SUMIF(Dev!$B:$B,CONCATENATE($A$6,A12),Dev!$L:$L) -> 168 | D12: =SUMIF(Dev!$B:$B,CONCATENATE($A$6,A12),Dev!M:M) -> 1856.4 | E12: I100 APORTE OBLIGATORIO AFP | G12: =SUMIF(Dev!$B:$B,CONCATENATE($A$6,E12),Dev!$L:$L) -> 0 | H12: =SUMIF(Dev!$B:$B,CONCATENATE($A$6,E12),Dev!N:N) -> 265.2 | I12: APORTE A ESSALUD | K12: 0 | L12: =VLOOKUP(A6,ESSALUD!$B$1:$G$19,6,FALSE) -> 179.01 | W12: 1077485287 | X12: 655610ZCBIT4 | Y12: 77485287
A13: D013 AUXILIO DE MOVILIDAD | C13: =SUMIF(Dev!$B:$B,CONCATENATE($A$6,A13),Dev!$L:$L) -> 0 | D13: =SUMIF(Dev!$B:$B,CONCATENATE($A$6,A13),Dev!M:M) -> 32 | E13: I200 SOBREVIVENCIA AFP | G13: =SUMIF(Dev!$B:$B,CONCATENATE($A$6,E13),Dev!$L:$L) -> 0 | H13: =SUMIF(Dev!$B:$B,CONCATENATE($A$6,E13),Dev!N:N) -> 36.33 | I13: CREDITO EPS | K13: 0 | L13: =VLOOKUP(A6,ESSALUD!$B$1:$H$19,7,FALSE) -> 59.67 | W13: 2001252358 | X13: 627991JMXQX0 | Y13: 001252358
A14: G006 VACACIONES | C14: =SUMIF(Dev!$B:$B,CONCATENATE($A$6,A14),Dev!$L:$L) -> 72 | D14: =SUMIF(Dev!$B:$B,CONCATENATE($A$6,A14),Dev!M:M) -> 795.6 | W14: 42115329 | X14: FACILITIES | Y14: 42115329
W15: 42683912 | X15: 309631GHMAI4 | Y15: 42683912
W16: 72836862 | X16: 663680JMDIO1 | Y16: 72836862
W17: 76607245 | X17: N/A | Y17: 76607245
W18: 74026184 | X18: N/A | Y18: 74026184
I25: TOTAL APORTE EMPLEADOR | L25: =SUM(L12:L24) -> 238.68
A26: REMUNERACION TOTAL | D26: =SUM(D12:D24) -> 2684 | E26: DESCUENTOS TOTALES | H26: =SUM(H12:H24) -> 301.53 | I26: REMUNERACION NETA | L26: =+D26-H26 -> 2382.47
F36: REPRESENTANTE LEGAL | J36: RECIBI CONFORME TRABAJADOR

Sheet PS1 (14)
A1: BOLETA DE PAGO | W1: EMPLEADO | X1: # AG ESSALUD | Y1: CODIGO EMPRESA
A2: EMPRESA | B2: CLARKE, MODET & CO. PERU S.A.C. | E2: R.U.C. | F2: 20256396000 | G2: MES | H2: =Detallado!R2 -> 05 | I2: AÑO | J2: =Detallado!S2 -> 2026 | K2: F. INGRESO | L2: =VLOOKUP(A6,'BD Total'!$A$2:$EZ$17,11,FALSE) -> 45637 | O2: # | P2: 1 | W2: 1007874085 | X2: 260130RRCOI9 | Y2: 07874085
E3: PERIODO | F3: =VLOOKUP($A$6,Detallado!$C:$U,16,FALSE) -> 05 | G3: DEL | H3: =VLOOKUP($A$6,Detallado!$C:$U,18,FALSE) -> 01/05/2026 | I3: AL | J3: =VLOOKUP($A$6,Detallado!$C:$U,19,FALSE) -> 46173 | K3: F. RETIRO | W3: 1040703418 | X3: 595200FCCCA8 | Y3: 40703418
W4: 1044771836 | X4: 621441RFSRR2 | Y4: 44771836
A5: CÓDIGO | B5: NOMBRES Y APELLIDOS | E5: CARGO | I5: AREA | W5: 1045191394 | X5: 322431AABAT4 | Y5: 45191394
A6: 42683912 | B6: =VLOOKUP(A6,Dev!$C$1:$D$78,2,FALSE) -> GUILLERMO HENRY HIRAOKA MARINA | E6: =VLOOKUP(A6,'BD Total'!$A$2:$EZ$18,77,FALSE) -> IP SPECIALIST | I6: =VLOOKUP(A6,'BD Total'!$A$2:$EZ$18,81,FALSE) -> TRADEMARKS | W6: 1046129072 | X6: 628890LLCAD9 | Y6: 46129072
A7: D.N.I. | B7: CUSPP AFP | C7: # AG ESSALUD | E7: SALARIO | G7: MONEDA | I7: CODIGO EMPRESA | K7: A.F.P. | W7: 1046722547 | X7: 632311FKROJ0 | Y7: 46722547
A8: =VLOOKUP(A6,'BD Total'!$A$2:$EZ$18,2,FALSE) -> 42683912 | B8: =VLOOKUP(A6,'BD Total'!$A$2:$EZ$18,85,FALSE) -> 309631GHMAI4 | C8: =VLOOKUP(A6,$W$1:$Y$20,2,FALSE) -> 309631GHMAI4 | E8: =VLOOKUP(A6,'BD Total'!$A$2:$EZ$18,22,FALSE) -> 5768 | G8: SOL | I8: =VLOOKUP(A6,$W$1:$Y$20,3,FALSE) -> 42683912 | K8: =VLOOKUP(A6,'BD Total'!$A$2:$EZ$18,101,FALSE) -> HABITAT | W8: 1047924040 | X8: 641640MNERI3 | Y8: 47924040
W9: 1070165336 | X9: 640621VFCNT9 | Y9: 70165336
A10: REMUNERACIONES | E10: DESCUENTOS TRABAJADOR | I10: APORTACIONES EMPLEADOR | W10: 1070680748 | X10: 0 | Y10: 70680748
A11: CONCEPTO | C11: HORAS | D11: VALOR | E11: CONCEPTO | G11: HORAS | H11: VALOR | I11: CONCEPTO | K11: HORAS | L11: VALOR | W11: 1072251509 | X11: 631390CHTMR2 | Y11: 72251509
A12: A000 SUELDO BASICO | C12: =SUMIF(Dev!$B:$B,CONCATENATE($A$6,A12),Dev!$L:$L) -> 240 | D12: =SUMIF(Dev!$B:$B,CONCATENATE($A$6,A12),Dev!M:M) -> 5768 | E12: I100 APORTE OBLIGATORIO AFP | G12: =SUMIF(Dev!$B:$B,CONCATENATE($A$6,E12),Dev!$L:$L) -> 0 | H12: =SUMIF(Dev!$B:$B,CONCATENATE($A$6,E12),Dev!N:N) -> 576.8 | I12: APORTE A ESSALUD | K12: 0 | L12: =VLOOKUP(A6,ESSALUD!$B$1:$G$19,6,FALSE) -> 389.34 | W12: 1077485287 | X12: 655610ZCBIT4 | Y12: 77485287
A13: D013 AUXILIO DE MOVILIDAD | C13: =SUMIF(Dev!$B:$B,CONCATENATE($A$6,A13),Dev!$L:$L) -> 0 | D13: =SUMIF(Dev!$B:$B,CONCATENATE($A$6,A13),Dev!M:M) -> 48 | E13: I200 SOBREVIVENCIA AFP | G13: =SUMIF(Dev!$B:$B,CONCATENATE($A$6,E13),Dev!$L:$L) -> 0 | H13: =SUMIF(Dev!$B:$B,CONCATENATE($A$6,E13),Dev!N:N) -> 79.02 | I13: CREDITO EPS | K13: 0 | L13: =VLOOKUP(A6,ESSALUD!$B$1:$H$19,7,FALSE) -> 129.78 | W13: 2001252358 | X13: 627991JMXQX0 | Y13: 001252358
E14: R000 RETENCION IMPUESTO A LA RENTA | G14: =SUMIF(Dev!$B:$B,CONCATENATE($A$6,E14),Dev!$L:$L) -> 0 | H14: =SUMIF(Dev!$B:$B,CONCATENATE($A$6,E14),Dev!N:N) -> 368.65 | W14: 42115329 | X14: FACILITIES | Y14: 42115329
W15: 42683912 | X15: 309631GHMAI4 | Y15: 42683912
W16: 72836862 | X16: 663680JMDIO1 | Y16: 72836862
W17: 76607245 | X17: N/A | Y17: 76607245
W18: 74026184 | X18: N/A | Y18: 74026184
I25: TOTAL APORTE EMPLEADOR | L25: =SUM(L12:L24) -> 519.12
A26: REMUNERACION TOTAL | D26: =SUM(D12:D24) -> 5816 | E26: DESCUENTOS TOTALES | H26: =SUM(H12:H24) -> 1024.47 | I26: REMUNERACION NETA | L26: =+D26-H26 -> 4791.53
F36: REPRESENTANTE LEGAL | J36: RECIBI CONFORME TRABAJADOR

Sheet PS1 (13)
A1: BOLETA DE PAGO | W1: EMPLEADO | X1: # AG ESSALUD | Y1: CODIGO EMPRESA
A2: EMPRESA | B2: CLARKE, MODET & CO. PERU S.A.C. | E2: R.U.C. | F2: 20256396000 | G2: MES | H2: =Detallado!R2 -> 05 | I2: AÑO | J2: =Detallado!S2 -> 2026 | K2: F. INGRESO | L2: =VLOOKUP(A6,'BD Total'!$A$2:$EZ$17,11,FALSE) -> 45740 | O2: # | P2: 1 | W2: 1007874085 | X2: 260130RRCOI9 | Y2: 07874085
E3: PERIODO | F3: =VLOOKUP($A$6,Detallado!$C:$U,16,FALSE) -> 05 | G3: DEL | H3: =VLOOKUP($A$6,Detallado!$C:$U,18,FALSE) -> 01/05/2026 | I3: AL | J3: =VLOOKUP($A$6,Detallado!$C:$U,19,FALSE) -> 46173 | K3: F. RETIRO | W3: 1040703418 | X3: 595200FCCCA8 | Y3: 40703418
W4: 1044771836 | X4: 621441RFSRR2 | Y4: 44771836
A5: CÓDIGO | B5: NOMBRES Y APELLIDOS | E5: CARGO | I5: AREA | W5: 1045191394 | X5: 322431AABAT4 | Y5: 45191394
A6: 42115329 | B6: =VLOOKUP(A6,Dev!$C$1:$D$78,2,FALSE) -> SARA MILAGROS SOTO LLOCLLA | E6: =VLOOKUP(A6,'BD Total'!$A$2:$EZ$18,77,FALSE) -> IP PROSECUTION SPECIALIST | I6: =VLOOKUP(A6,'BD Total'!$A$2:$EZ$18,81,FALSE) -> CENTRAL SERVICES | W6: 1046129072 | X6: 628890LLCAD9 | Y6: 46129072
A7: D.N.I. | B7: CUSPP AFP | C7: # AG ESSALUD | E7: SALARIO | G7: MONEDA | I7: CODIGO EMPRESA | K7: A.F.P. | W7: 1046722547 | X7: 632311FKROJ0 | Y7: 46722547
A8: =VLOOKUP(A6,'BD Total'!$A$2:$EZ$18,2,FALSE) -> 42115329 | B8: =VLOOKUP(A6,'BD Total'!$A$2:$EZ$18,85,FALSE) -> FACILITIES | C8: =VLOOKUP(A6,$W$1:$Y$20,2,FALSE) -> FACILITIES | E8: =VLOOKUP(A6,'BD Total'!$A$2:$EZ$18,22,FALSE) -> 3090 | G8: SOL | I8: =VLOOKUP(A6,$W$1:$Y$20,3,FALSE) -> 42115329 | K8: =VLOOKUP(A6,'BD Total'!$A$2:$EZ$18,101,FALSE) -> INTEGRA | W8: 1047924040 | X8: 641640MNERI3 | Y8: 47924040
W9: 1070165336 | X9: 640621VFCNT9 | Y9: 70165336
A10: REMUNERACIONES | E10: DESCUENTOS TRABAJADOR | I10: APORTACIONES EMPLEADOR | W10: 1070680748 | X10: 0 | Y10: 70680748
A11: CONCEPTO | C11: HORAS | D11: VALOR | E11: CONCEPTO | G11: HORAS | H11: VALOR | I11: CONCEPTO | K11: HORAS | L11: VALOR | W11: 1072251509 | X11: 631390CHTMR2 | Y11: 72251509
A12: A000 SUELDO BASICO | C12: =SUMIF(Dev!$B:$B,CONCATENATE($A$6,A12),Dev!$L:$L) -> 240 | D12: =SUMIF(Dev!$B:$B,CONCATENATE($A$6,A12),Dev!M:M) -> 3090 | E12: I100 APORTE OBLIGATORIO AFP | G12: =SUMIF(Dev!$B:$B,CONCATENATE($A$6,E12),Dev!$L:$L) -> 0 | H12: =SUMIF(Dev!$B:$B,CONCATENATE($A$6,E12),Dev!N:N) -> 309 | I12: APORTE A ESSALUD | K12: 0 | L12: =VLOOKUP(A6,ESSALUD!$B$1:$G$19,6,FALSE) -> 208.575 | W12: 1077485287 | X12: 655610ZCBIT4 | Y12: 77485287
A13: D013 AUXILIO DE MOVILIDAD | C13: =SUMIF(Dev!$B:$B,CONCATENATE($A$6,A13),Dev!$L:$L) -> 0 | D13: =SUMIF(Dev!$B:$B,CONCATENATE($A$6,A13),Dev!M:M) -> 36 | E13: I200 SOBREVIVENCIA AFP | G13: =SUMIF(Dev!$B:$B,CONCATENATE($A$6,E13),Dev!$L:$L) -> 0 | H13: =SUMIF(Dev!$B:$B,CONCATENATE($A$6,E13),Dev!N:N) -> 42.33 | I13: CREDITO EPS | K13: 0 | L13: =VLOOKUP(A6,ESSALUD!$B$1:$H$19,7,FALSE) -> 69.525 | W13: 2001252358 | X13: 627991JMXQX0 | Y13: 001252358
E14: I300 COMISION VARIABLE AFP | G14: =SUMIF(Dev!$B:$B,CONCATENATE($A$6,E14),Dev!$L:$L) -> 0 | H14: =SUMIF(Dev!$B:$B,CONCATENATE($A$6,E14),Dev!N:N) -> 47.9 | W14: 42115329 | X14: FACILITIES | Y14: 42115329
E15: R000 RETENCION IMPUESTO A LA RENTA | G15: =SUMIF(Dev!$B:$B,CONCATENATE($A$6,E15),Dev!$L:$L) -> 0 | H15: =SUMIF(Dev!$B:$B,CONCATENATE($A$6,E15),Dev!N:N) -> 36.25 | W15: 42683912 | X15: 309631GHMAI4 | Y15: 42683912
W16: 72836862 | X16: 663680JMDIO1 | Y16: 72836862
W17: 76607245 | X17: N/A | Y17: 76607245
W18: 74026184 | X18: N/A | Y18: 74026184
I25: TOTAL APORTE EMPLEADOR | L25: =SUM(L12:L24) -> 278.1
A26: REMUNERACION TOTAL | D26: =SUM(D12:D24) -> 3126 | E26: DESCUENTOS TOTALES | H26: =SUM(H12:H24) -> 435.48 | I26: REMUNERACION NETA | L26: =+D26-H26 -> 2690.52
F36: REPRESENTANTE LEGAL | J36: RECIBI CONFORME TRABAJADOR

Sheet PS1 (12)
A1: BOLETA DE PAGO | W1: EMPLEADO | X1: # AG ESSALUD | Y1: CODIGO EMPRESA
A2: EMPRESA | B2: CLARKE, MODET & CO. PERU S.A.C. | E2: R.U.C. | F2: 20256396000 | G2: MES | H2: =Detallado!R2 -> 05 | I2: AÑO | J2: =Detallado!S2 -> 2026 | K2: F. INGRESO | L2: =VLOOKUP(A6,'BD Total'!$A$2:$EZ$17,11,FALSE) -> 42438 | O2: # | P2: 1 | W2: 1007874085 | X2: 260130RRCOI9 | Y2: 07874085
E3: PERIODO | F3: =VLOOKUP($A$6,Detallado!$C:$U,16,FALSE) -> 05 | G3: DEL | H3: =VLOOKUP($A$6,Detallado!$C:$U,18,FALSE) -> 01/05/2026 | I3: AL | J3: =VLOOKUP($A$6,Detallado!$C:$U,19,FALSE) -> 46173 | K3: F. RETIRO | W3: 1040703418 | X3: 595200FCCCA8 | Y3: 40703418
W4: 1044771836 | X4: 621441RFSRR2 | Y4: 44771836
A5: CÓDIGO | B5: NOMBRES Y APELLIDOS | E5: CARGO | I5: AREA | W5: 1045191394 | X5: 322431AABAT4 | Y5: 45191394
A6: 2001252358 | B6: =VLOOKUP(A6,Dev!$C$1:$D$78,2,FALSE) -> JOSE NORBERT MARQUIS XXX | E6: =VLOOKUP(A6,'BD Total'!$A$2:$EZ$18,77,FALSE) -> IP SPECIALIST | I6: =VLOOKUP(A6,'BD Total'!$A$2:$EZ$18,81,FALSE) -> INVENTIONS | W6: 1046129072 | X6: 628890LLCAD9 | Y6: 46129072
A7: D.N.I. | B7: CUSPP AFP | C7: # AG ESSALUD | E7: SALARIO | G7: MONEDA | I7: CODIGO EMPRESA | K7: A.F.P. | W7: 1046722547 | X7: 632311FKROJ0 | Y7: 46722547
A8: =VLOOKUP(A6,'BD Total'!$A$2:$EZ$18,2,FALSE) -> 001252358 | B8: =VLOOKUP(A6,'BD Total'!$A$2:$EZ$18,85,FALSE) -> 627991JMXQX0 | C8: =VLOOKUP(A6,$W$1:$Y$20,2,FALSE) -> 627991JMXQX0 | E8: =VLOOKUP(A6,'BD Total'!$A$2:$EZ$18,22,FALSE) -> 6644 | G8: SOL | I8: =VLOOKUP(A6,$W$1:$Y$20,3,FALSE) -> 001252358 | K8: =VLOOKUP(A6,'BD Total'!$A$2:$EZ$18,101,FALSE) -> HABITAT | W8: 1047924040 | X8: 641640MNERI3 | Y8: 47924040
W9: 1070165336 | X9: 640621VFCNT9 | Y9: 70165336
A10: REMUNERACIONES | E10: DESCUENTOS TRABAJADOR | I10: APORTACIONES EMPLEADOR | W10: 1070680748 | X10: 0 | Y10: 70680748
A11: CONCEPTO | C11: HORAS | D11: VALOR | E11: CONCEPTO | G11: HORAS | H11: VALOR | I11: CONCEPTO | K11: HORAS | L11: VALOR | W11: 1072251509 | X11: 631390CHTMR2 | Y11: 72251509
A12: A000 SUELDO BASICO | C12: =SUMIF(Dev!$B:$B,CONCATENATE($A$6,A12),Dev!$L:$L) -> 240 | D12: =SUMIF(Dev!$B:$B,CONCATENATE($A$6,A12),Dev!M:M) -> 6644 | E12: I100 APORTE OBLIGATORIO AFP | G12: =SUMIF(Dev!$B:$B,CONCATENATE($A$6,E12),Dev!$L:$L) -> 0 | H12: =SUMIF(Dev!$B:$B,CONCATENATE($A$6,E12),Dev!N:N) -> 664.4 | I12: APORTE A ESSALUD | K12: 0 | L12: =VLOOKUP(A6,ESSALUD!$B$1:$G$19,6,FALSE) -> 448.47 | W12: 1077485287 | X12: 655610ZCBIT4 | Y12: 77485287
A13: D013 AUXILIO DE MOVILIDAD | C13: =SUMIF(Dev!$B:$B,CONCATENATE($A$6,A13),Dev!$L:$L) -> 0 | D13: =SUMIF(Dev!$B:$B,CONCATENATE($A$6,A13),Dev!M:M) -> 48 | E13: I200 SOBREVIVENCIA AFP | G13: =SUMIF(Dev!$B:$B,CONCATENATE($A$6,E13),Dev!$L:$L) -> 0 | H13: =SUMIF(Dev!$B:$B,CONCATENATE($A$6,E13),Dev!N:N) -> 91.02 | I13: CREDITO EPS | K13: 0 | L13: =VLOOKUP(A6,ESSALUD!$B$1:$H$19,7,FALSE) -> 149.49 | W13: 2001252358 | X13: 627991JMXQX0 | Y13: 001252358
E14: R000 RETENCION IMPUESTO A LA RENTA | G14: =SUMIF(Dev!$B:$B,CONCATENATE($A$6,#REF!),Dev!$L:$L) -> 0 | H14: =SUMIF(Dev!$B:$B,CONCATENATE($A$6,E14),Dev!N:N) -> 513.58 | W14: 42115329 | X14: FACILITIES | Y14: 42115329
W15: 42683912 | X15: 309631GHMAI4 | Y15: 42683912
W16: 72836862 | X16: 663680JMDIO1 | Y16: 72836862
W17: 76607245 | X17: N/A | Y17: 76607245
W18: 74026184 | X18: N/A | Y18: 74026184
I25: TOTAL APORTE EMPLEADOR | L25: =SUM(L12:L24) -> 597.96
A26: REMUNERACION TOTAL | D26: =SUM(D12:D24) -> 6692 | E26: DESCUENTOS TOTALES | H26: =SUM(H12:H24) -> 1269 | I26: REMUNERACION NETA | L26: =+D26-H26 -> 5423
F36: REPRESENTANTE LEGAL | J36: RECIBI CONFORME TRABAJADOR

Sheet PS1 (11)
A1: BOLETA DE PAGO | W1: EMPLEADO | X1: # AG ESSALUD | Y1: CODIGO EMPRESA
A2: EMPRESA | B2: CLARKE, MODET & CO. PERU S.A.C. | E2: R.U.C. | F2: 20256396000 | G2: MES | H2: =Detallado!R2 -> 05 | I2: AÑO | J2: =Detallado!S2 -> 2026 | K2: F. INGRESO | L2: =VLOOKUP(A6,'BD Total'!$A$2:$EZ$17,11,FALSE) -> 45323 | O2: # | P2: 1 | W2: 1007874085 | X2: 260130RRCOI9 | Y2: 07874085
E3: PERIODO | F3: =VLOOKUP($A$6,Detallado!$C:$U,16,FALSE) -> 05 | G3: DEL | H3: =VLOOKUP($A$6,Detallado!$C:$U,18,FALSE) -> 01/05/2026 | I3: AL | J3: =VLOOKUP($A$6,Detallado!$C:$U,19,FALSE) -> 46173 | K3: F. RETIRO | W3: 1040703418 | X3: 595200FCCCA8 | Y3: 40703418
W4: 1044771836 | X4: 621441RFSRR2 | Y4: 44771836
A5: CÓDIGO | B5: NOMBRES Y APELLIDOS | E5: CARGO | I5: AREA | W5: 1045191394 | X5: 322431AABAT4 | Y5: 45191394
A6: 1077485287 | B6: =VLOOKUP(A6,Dev!$C$1:$D$78,2,FALSE) -> ZULEMA BELINDA CADILLO BRITO | E6: =VLOOKUP(A6,'BD Total'!$A$2:$EZ$18,77,FALSE) -> IP PROSECUTION SPECIALIST | I6: =VLOOKUP(A6,'BD Total'!$A$2:$EZ$18,81,FALSE) -> CENTRAL SERVICES | W6: 1046129072 | X6: 628890LLCAD9 | Y6: 46129072
A7: D.N.I. | B7: CUSPP AFP | C7: # AG ESSALUD | E7: SALARIO | G7: MONEDA | I7: CODIGO EMPRESA | K7: A.F.P. | W7: 1046722547 | X7: 632311FKROJ0 | Y7: 46722547
A8: =VLOOKUP(A6,'BD Total'!$A$2:$EZ$18,2,FALSE) -> 77485287 | B8: =VLOOKUP(A6,'BD Total'!$A$2:$EZ$18,85,FALSE) -> 655610ZCBIT4 | C8: =VLOOKUP(A6,$W$1:$Y$20,2,FALSE) -> 655610ZCBIT4 | E8: =VLOOKUP(A6,'BD Total'!$A$2:$EZ$18,22,FALSE) -> 2142 | G8: SOL | I8: =VLOOKUP(A6,$W$1:$Y$20,3,FALSE) -> 77485287 | K8: =VLOOKUP(A6,'BD Total'!$A$2:$EZ$18,101,FALSE) -> PRIMA | W8: 1047924040 | X8: 641640MNERI3 | Y8: 47924040
W9: 1070165336 | X9: 640621VFCNT9 | Y9: 70165336
A10: REMUNERACIONES | E10: DESCUENTOS TRABAJADOR | I10: APORTACIONES EMPLEADOR | W10: 1070680748 | X10: 0 | Y10: 70680748
A11: CONCEPTO | C11: HORAS | D11: VALOR | E11: CONCEPTO | G11: HORAS | H11: VALOR | I11: CONCEPTO | K11: HORAS | L11: VALOR | W11: 1072251509 | X11: 631390CHTMR2 | Y11: 72251509
A12: A000 SUELDO BASICO | C12: =SUMIF(Dev!$B:$B,CONCATENATE($A$6,A12),Dev!$L:$L) -> 240 | D12: =SUMIF(Dev!$B:$B,CONCATENATE($A$6,A12),Dev!M:M) -> 2142 | E12: I100 APORTE OBLIGATORIO AFP | G12: =SUMIF(Dev!$B:$B,CONCATENATE($A$6,E12),Dev!$L:$L) -> 0 | H12: =SUMIF(Dev!$B:$B,CONCATENATE($A$6,E12),Dev!N:N) -> 214.2 | I12: APORTE A ESSALUD | K12: 0 | L12: =VLOOKUP(A6,ESSALUD!$B$1:$G$19,6,FALSE) -> 144.585 | W12: 1077485287 | X12: 655610ZCBIT4 | Y12: 77485287
A13: D013 AUXILIO DE MOVILIDAD | C13: =SUMIF(Dev!$B:$B,CONCATENATE($A$6,A13),Dev!$L:$L) -> 0 | D13: =SUMIF(Dev!$B:$B,CONCATENATE($A$6,A13),Dev!M:M) -> 48 | E13: I200 SOBREVIVENCIA AFP | G13: =SUMIF(Dev!$B:$B,CONCATENATE($A$6,E13),Dev!$L:$L) -> 0 | H13: =SUMIF(Dev!$B:$B,CONCATENATE($A$6,E13),Dev!N:N) -> 29.35 | I13: CREDITO EPS | K13: 0 | L13: =VLOOKUP(A6,ESSALUD!$B$1:$H$19,7,FALSE) -> 48.195 | W13: 2001252358 | X13: 627991JMXQX0 | Y13: 001252358
W14: 42115329 | X14: FACILITIES | Y14: 42115329
W15: 42683912 | X15: 309631GHMAI4 | Y15: 42683912
W16: 72836862 | X16: 663680JMDIO1 | Y16: 72836862
W17: 76607245 | X17: N/A | Y17: 76607245
W18: 74026184 | X18: N/A | Y18: 74026184
I25: TOTAL APORTE EMPLEADOR | L25: =SUM(L12:L24) -> 192.78
A26: REMUNERACION TOTAL | D26: =SUM(D12:D24) -> 2190 | E26: DESCUENTOS TOTALES | H26: =SUM(H12:H24) -> 243.55 | I26: REMUNERACION NETA | L26: =+D26-H26 -> 1946.45
F36: REPRESENTANTE LEGAL | J36: RECIBI CONFORME TRABAJADOR

Sheet PS1 (10)
A1: BOLETA DE PAGO | W1: EMPLEADO | X1: # AG ESSALUD | Y1: CODIGO EMPRESA
A2: EMPRESA | B2: CLARKE, MODET & CO. PERU S.A.C. | E2: R.U.C. | F2: 20256396000 | G2: MES | H2: =Detallado!R2 -> 05 | I2: AÑO | J2: =Detallado!S2 -> 2026 | K2: F. INGRESO | L2: =VLOOKUP(A6,'BD Total'!$A$2:$EZ$17,11,FALSE) -> 43241 | W2: 1007874085 | X2: 260130RRCOI9 | Y2: 07874085
E3: PERIODO | F3: =VLOOKUP($A$6,Detallado!$C:$U,16,FALSE) -> 05 | G3: DEL | H3: =VLOOKUP($A$6,Detallado!$C:$U,18,FALSE) -> 01/05/2026 | I3: AL | J3: =VLOOKUP($A$6,Detallado!$C:$U,19,FALSE) -> 46173 | K3: F. RETIRO | W3: 1040703418 | X3: 595200FCCCA8 | Y3: 40703418
W4: 1044771836 | X4: 621441RFSRR2 | Y4: 44771836
A5: CÓDIGO | B5: NOMBRES Y APELLIDOS | E5: CARGO | I5: AREA | W5: 1045191394 | X5: 322431AABAT4 | Y5: 45191394
A6: 1072251509 | B6: =VLOOKUP(A6,Dev!$C$1:$D$78,2,FALSE) -> CYNTHIA FIORELLA HUAMAN TORRES | E6: =VLOOKUP(A6,'BD Total'!$A$2:$EZ$18,77,FALSE) -> PATENT SPECIALIST | I6: =VLOOKUP(A6,'BD Total'!$A$2:$EZ$18,81,FALSE) -> INVENTIONS | W6: 1046129072 | X6: 628890LLCAD9 | Y6: 46129072
A7: D.N.I. | B7: CUSPP AFP | C7: # AG ESSALUD | E7: SALARIO | G7: MONEDA | I7: CODIGO EMPRESA | K7: A.F.P. | W7: 1046722547 | X7: 632311FKROJ0 | Y7: 46722547
A8: =VLOOKUP(A6,'BD Total'!$A$2:$EZ$18,2,FALSE) -> 72251509 | B8: =VLOOKUP(A6,'BD Total'!$A$2:$EZ$18,85,FALSE) -> 631390CHTMR2 | C8: =VLOOKUP(A6,$W$1:$Y$20,2,FALSE) -> 631390CHTMR2 | E8: =VLOOKUP(A6,'BD Total'!$A$2:$EZ$18,22,FALSE) -> 4631 | G8: SOL | I8: =VLOOKUP(A6,$W$1:$Y$20,3,FALSE) -> 72251509 | K8: =VLOOKUP(A6,'BD Total'!$A$2:$EZ$18,101,FALSE) -> HABITAT | W8: 1047924040 | X8: 641640MNERI3 | Y8: 47924040
W9: 1070165336 | X9: 640621VFCNT9 | Y9: 70165336
A10: REMUNERACIONES | E10: DESCUENTOS TRABAJADOR | I10: APORTACIONES EMPLEADOR | W10: 1070680748 | X10: 0 | Y10: 70680748
A11: CONCEPTO | C11: HORAS | D11: VALOR | E11: CONCEPTO | G11: HORAS | H11: VALOR | I11: CONCEPTO | K11: HORAS | L11: VALOR | W11: 1072251509 | X11: 631390CHTMR2 | Y11: 72251509
A12: A000 SUELDO BASICO | C12: =SUMIF(Dev!$B:$B,CONCATENATE($A$6,A12),Dev!$L:$L) -> 168 | D12: =SUMIF(Dev!$B:$B,CONCATENATE($A$6,A12),Dev!M:M) -> 3241.7 | E12: I100 APORTE OBLIGATORIO AFP | G12: =SUMIF(Dev!$B:$B,CONCATENATE($A$6,E12),Dev!$L:$L) -> 0 | H12: =SUMIF(Dev!$B:$B,CONCATENATE($A$6,E12),Dev!N:N) -> 474.4 | I12: APORTE A ESSALUD | K12: 0 | L12: =VLOOKUP(A6,ESSALUD!$B$1:$G$19,6,FALSE) -> 426.96 | W12: 1077485287 | X12: 655610ZCBIT4 | Y12: 77485287
A13: D013 AUXILIO DE MOVILIDAD | C13: =SUMIF(Dev!$B:$B,CONCATENATE($A$6,A13),Dev!$L:$L) -> 0 | D13: =SUMIF(Dev!$B:$B,CONCATENATE($A$6,A13),Dev!M:M) -> 32 | E13: I200 SOBREVIVENCIA AFP | G13: =SUMIF(Dev!$B:$B,CONCATENATE($A$6,E13),Dev!$L:$L) -> 0 | H13: =SUMIF(Dev!$B:$B,CONCATENATE($A$6,E13),Dev!N:N) -> 64.99 | W13: 2001252358 | X13: 627991JMXQX0 | Y13: 001252358
A14: G006 VACACIONES | C14: =SUMIF(Dev!$B:$B,CONCATENATE($A$6,A14),Dev!$L:$L) -> 72 | D14: =SUMIF(Dev!$B:$B,CONCATENATE($A$6,A14),Dev!M:M) -> 1389.3 | E14: R000 RETENCION IMPUESTO A LA RENTA | G14: =SUMIF(Dev!$B:$B,CONCATENATE($A$6,#REF!),Dev!$L:$L) -> 0 | H14: =SUMIF(Dev!$B:$B,CONCATENATE($A$6,E14),Dev!N:N) -> 197.7 | W14: 42115329 | X14: FACILITIES | Y14: 42115329
A15: A012 ASIGNACION FAMILIAR | C15: =SUMIF(Dev!$B:$B,CONCATENATE($A$6,A15),Dev!$L:$L) -> 0 | D15: =SUMIF(Dev!$B:$B,CONCATENATE($A$6,A15),Dev!M:M) -> 113 | W15: 42683912 | X15: 309631GHMAI4 | Y15: 42683912
W16: 72836862 | X16: 663680JMDIO1 | Y16: 72836862
W17: 76607245 | X17: N/A | Y17: 76607245
W18: 74026184 | X18: N/A | Y18: 74026184
I25: TOTAL APORTE EMPLEADOR | L25: =SUM(L12:L24) -> 426.96
A26: REMUNERACION TOTAL | D26: =SUM(D12:D24) -> 4776 | E26: DESCUENTOS TOTALES | H26: =SUM(H12:H24) -> 737.09 | I26: REMUNERACION NETA | L26: =+D26-H26 -> 4038.91
F36: REPRESENTANTE LEGAL | J36: RECIBI CONFORME TRABAJADOR

Sheet PS1 (9)
A1: BOLETA DE PAGO | W1: EMPLEADO | X1: # AG ESSALUD | Y1: CODIGO EMPRESA
A2: EMPRESA | B2: CLARKE, MODET & CO. PERU S.A.C. | E2: R.U.C. | F2: 20256396000 | G2: MES | H2: =Detallado!R2 -> 05 | I2: AÑO | J2: =Detallado!S2 -> 2026 | K2: F. INGRESO | L2: =VLOOKUP(A6,'BD Total'!$A$2:$EZ$17,11,FALSE) -> 44879 | O2: # | P2: 1 | W2: 1007874085 | X2: 260130RRCOI9 | Y2: 07874085
E3: PERIODO | F3: =VLOOKUP($A$6,Detallado!$C:$U,16,FALSE) -> 05 | G3: DEL | H3: =VLOOKUP($A$6,Detallado!$C:$U,18,FALSE) -> 01/05/2026 | I3: AL | J3: =VLOOKUP($A$6,Detallado!$C:$U,19,FALSE) -> 46173 | K3: F. RETIRO | W3: 1040703418 | X3: 595200FCCCA8 | Y3: 40703418
W4: 1044771836 | X4: 621441RFSRR2 | Y4: 44771836
A5: CÓDIGO | B5: NOMBRES Y APELLIDOS | E5: CARGO | I5: AREA | W5: 1045191394 | X5: 322431AABAT4 | Y5: 45191394
A6: 1070680748 | B6: =VLOOKUP(A6,Dev!$C$1:$D$78,2,FALSE) -> LIZ VALERIA SOLANO CARRILLO | E6: =VLOOKUP(A6,'BD Total'!$A$2:$EZ$18,77,FALSE) -> IP SPECIALIST | I6: =VLOOKUP(A6,'BD Total'!$A$2:$EZ$18,81,FALSE) -> TRADEMARKS | W6: 1046129072 | X6: 628890LLCAD9 | Y6: 46129072
A7: D.N.I. | B7: CUSPP AFP | C7: # AG ESSALUD | E7: SALARIO | G7: MONEDA | I7: CODIGO EMPRESA | K7: A.F.P. | W7: 1046722547 | X7: 632311FKROJ0 | Y7: 46722547
A8: =VLOOKUP(A6,'BD Total'!$A$2:$EZ$18,2,FALSE) -> 70680748 | B8: =VLOOKUP(A6,'BD Total'!$A$2:$EZ$18,85,FALSE) -> 0 | C8: =VLOOKUP(A6,$W$1:$Y$20,2,FALSE) -> 0 | E8: =VLOOKUP(A6,'BD Total'!$A$2:$EZ$18,22,FALSE) -> 6125 | G8: SOL | I8: =VLOOKUP(A6,$W$1:$Y$20,3,FALSE) -> 70680748 | K8: =VLOOKUP(A6,'BD Total'!$A$2:$EZ$18,101,FALSE) -> ONP | W8: 1047924040 | X8: 641640MNERI3 | Y8: 47924040
W9: 1070165336 | X9: 640621VFCNT9 | Y9: 70165336
A10: REMUNERACIONES | E10: DESCUENTOS TRABAJADOR | I10: APORTACIONES EMPLEADOR | W10: 1070680748 | X10: 0 | Y10: 70680748
A11: CONCEPTO | C11: HORAS | D11: VALOR | E11: CONCEPTO | G11: HORAS | H11: VALOR | I11: CONCEPTO | K11: HORAS | L11: VALOR | W11: 1072251509 | X11: 631390CHTMR2 | Y11: 72251509
A12: A000 SUELDO BASICO | C12: =SUMIF(Dev!$B:$B,CONCATENATE($A$6,A12),Dev!$L:$L) -> 152 | D12: =SUMIF(Dev!$B:$B,CONCATENATE($A$6,A12),Dev!M:M) -> 3879.17 | E12: I100 APORTE OBLIGATORIO AFP | G12: =SUMIF(Dev!$B:$B,CONCATENATE($A$6,E12),Dev!$L:$L) -> 0 | H12: =SUMIF(Dev!$B:$B,CONCATENATE($A$6,E12),Dev!N:N) -> 810.94 | I12: APORTE A ESSALUD | K12: 0 | L12: =VLOOKUP(A6,ESSALUD!$B$1:$G$19,6,FALSE) -> 421.065 | W12: 1077485287 | X12: 655610ZCBIT4 | Y12: 77485287
A13: A012 ASIGNACION FAMILIAR | C13: =SUMIF(Dev!$B:$B,CONCATENATE($A$6,A13),Dev!$L:$L) -> 0 | D13: =SUMIF(Dev!$B:$B,CONCATENATE($A$6,A13),Dev!M:M) -> 113 | E13: R000 RETENCION IMPUESTO A LA RENTA | G13: =SUMIF(Dev!$B:$B,CONCATENATE($A$6,#REF!),Dev!$L:$L) -> 0 | H13: =SUMIF(Dev!$B:$B,CONCATENATE($A$6,E13),Dev!N:N) -> 440.35 | I13: CREDITO EPS | K13: 0 | L13: =VLOOKUP(A6,ESSALUD!$B$1:$H$19,7,FALSE) -> 140.355 | W13: 2001252358 | X13: 627991JMXQX0 | Y13: 001252358
A14: G006 VACACIONES | C14: =SUMIF(Dev!$B:$B,CONCATENATE($A$6,A14),Dev!$L:$L) -> 88 | D14: =SUMIF(Dev!$B:$B,CONCATENATE($A$6,A14),Dev!M:M) -> 2245.83 | W14: 42115329 | X14: FACILITIES | Y14: 42115329
W15: 42683912 | X15: 309631GHMAI4 | Y15: 42683912
W16: 72836862 | X16: 663680JMDIO1 | Y16: 72836862
W17: 76607245 | X17: N/A | Y17: 76607245
W18: 74026184 | X18: N/A | Y18: 74026184
I25: TOTAL APORTE EMPLEADOR | L25: =SUM(L12:L24) -> 561.42
A26: REMUNERACION TOTAL | D26: =SUM(D12:D24) -> 6238 | E26: DESCUENTOS TOTALES | H26: =SUM(H12:H24) -> 1251.29 | I26: REMUNERACION NETA | L26: =+D26-H26 -> 4986.71
F36: REPRESENTANTE LEGAL | J36: RECIBI CONFORME TRABAJADOR

Sheet PS1 (8)
A1: BOLETA DE PAGO | W1: EMPLEADO | X1: # AG ESSALUD | Y1: CODIGO EMPRESA
A2: EMPRESA | B2: CLARKE, MODET & CO. PERU S.A.C. | E2: R.U.C. | F2: 20256396000 | G2: MES | H2: =Detallado!R2 -> 05 | I2: AÑO | J2: =Detallado!S2 -> 2026 | K2: F. INGRESO | L2: =VLOOKUP(A6,'BD Total'!$A$2:$EZ$17,11,FALSE) -> 44623 | O2: # | P2: 1 | W2: 1007874085 | X2: 260130RRCOI9 | Y2: 07874085
E3: PERIODO | F3: =VLOOKUP($A$6,Detallado!$C:$U,16,FALSE) -> 05 | G3: DEL | H3: =VLOOKUP($A$6,Detallado!$C:$U,18,FALSE) -> 01/05/2026 | I3: AL | J3: =VLOOKUP($A$6,Detallado!$C:$U,19,FALSE) -> 46173 | K3: F. RETIRO | W3: 1040703418 | X3: 595200FCCCA8 | Y3: 40703418
W4: 1044771836 | X4: 621441RFSRR2 | Y4: 44771836
A5: CÓDIGO | B5: NOMBRES Y APELLIDOS | E5: CARGO | I5: AREA | W5: 1045191394 | X5: 322431AABAT4 | Y5: 45191394
A6: 1070165336 | B6: =VLOOKUP(A6,Dev!$C$1:$D$78,2,FALSE) -> VICTOR DANIEL FERNANDEZ CASTILLO | E6: =VLOOKUP(A6,'BD Total'!$A$2:$EZ$18,77,FALSE) -> PATENT SPECIALIST | I6: =VLOOKUP(A6,'BD Total'!$A$2:$EZ$18,81,FALSE) -> INVENTIONS | W6: 1046129072 | X6: 628890LLCAD9 | Y6: 46129072
A7: D.N.I. | B7: CUSPP AFP | C7: # AG ESSALUD | E7: SALARIO | G7: MONEDA | I7: CODIGO EMPRESA | K7: A.F.P. | W7: 1046722547 | X7: 632311FKROJ0 | Y7: 46722547
A8: =VLOOKUP(A6,'BD Total'!$A$2:$EZ$18,2,FALSE) -> 70165336 | B8: =VLOOKUP(A6,'BD Total'!$A$2:$EZ$18,85,FALSE) -> 640621VFCNT9 | C8: =VLOOKUP(A6,$W$1:$Y$20,2,FALSE) -> 640621VFCNT9 | E8: =VLOOKUP(A6,'BD Total'!$A$2:$EZ$18,22,FALSE) -> 4099 | G8: SOL | I8: =VLOOKUP(A6,$W$1:$Y$20,3,FALSE) -> 70165336 | K8: =VLOOKUP(A6,'BD Total'!$A$2:$EZ$18,101,FALSE) -> HABITAT | W8: 1047924040 | X8: 641640MNERI3 | Y8: 47924040
W9: 1070165336 | X9: 640621VFCNT9 | Y9: 70165336
A10: REMUNERACIONES | E10: DESCUENTOS TRABAJADOR | I10: APORTACIONES EMPLEADOR | W10: 1070680748 | X10: 0 | Y10: 70680748
A11: CONCEPTO | C11: HORAS | D11: VALOR | E11: CONCEPTO | G11: HORAS | H11: VALOR | I11: CONCEPTO | K11: HORAS | L11: VALOR | W11: 1072251509 | X11: 631390CHTMR2 | Y11: 72251509
A12: A000 SUELDO BASICO | C12: =SUMIF(Dev!$B:$B,CONCATENATE($A$6,A12),Dev!$L:$L) -> 184 | D12: =SUMIF(Dev!$B:$B,CONCATENATE($A$6,A12),Dev!M:M) -> 3142.57 | E12: I100 APORTE OBLIGATORIO AFP | G12: =SUMIF(Dev!$B:$B,CONCATENATE($A$6,E12),Dev!$L:$L) -> 0 | H12: =SUMIF(Dev!$B:$B,CONCATENATE($A$6,E12),Dev!N:N) -> 409.9 | I12: APORTE A ESSALUD | K12: 0 | L12: =VLOOKUP(A6,ESSALUD!$B$1:$G$19,6,FALSE) -> 276.6825 | W12: 1077485287 | X12: 655610ZCBIT4 | Y12: 77485287
A13: D013 AUXILIO DE MOVILIDAD | C13: =SUMIF(Dev!$B:$B,CONCATENATE($A$6,A13),Dev!$L:$L) -> 0 | D13: =SUMIF(Dev!$B:$B,CONCATENATE($A$6,A13),Dev!M:M) -> 36 | E13: I200 SOBREVIVENCIA AFP | G13: =SUMIF(Dev!$B:$B,CONCATENATE($A$6,E13),Dev!$L:$L) -> 0 | H13: =SUMIF(Dev!$B:$B,CONCATENATE($A$6,E13),Dev!N:N) -> 56.16 | I13: CREDITO EPS | K13: 0 | L13: =VLOOKUP(A6,ESSALUD!$B$1:$H$19,7,FALSE) -> 92.2275 | W13: 2001252358 | X13: 627991JMXQX0 | Y13: 001252358
A14: G006 VACACIONES | C14: =SUMIF(Dev!$B:$B,CONCATENATE($A$6,A14),Dev!$L:$L) -> 56 | D14: =SUMIF(Dev!$B:$B,CONCATENATE($A$6,A14),Dev!M:M) -> 956.43 | E14: R000 RETENCION IMPUESTO A LA RENTA | G14: =SUMIF(Dev!$B:$B,CONCATENATE($A$6,#REF!),Dev!$L:$L) -> 0 | H14: =SUMIF(Dev!$B:$B,CONCATENATE($A$6,E14),Dev!N:N) -> 131.63 | W14: 42115329 | X14: FACILITIES | Y14: 42115329
W15: 42683912 | X15: 309631GHMAI4 | Y15: 42683912
W16: 72836862 | X16: 663680JMDIO1 | Y16: 72836862
W17: 76607245 | X17: N/A | Y17: 76607245
W18: 74026184 | X18: N/A | Y18: 74026184
I25: TOTAL APORTE EMPLEADOR | L25: =SUM(L12:L24) -> 368.91
A26: REMUNERACION TOTAL | D26: =SUM(D12:D24) -> 4135 | E26: DESCUENTOS TOTALES | H26: =SUM(H12:H24) -> 597.69 | I26: REMUNERACION NETA | L26: =+D26-H26 -> 3537.31
F36: REPRESENTANTE LEGAL | J36: RECIBI CONFORME TRABAJADOR

Sheet PS1 (7)
A1: BOLETA DE PAGO | W1: EMPLEADO | X1: # AG ESSALUD | Y1: CODIGO EMPRESA
A2: EMPRESA | B2: CLARKE, MODET & CO. PERU S.A.C. | E2: R.U.C. | F2: 20256396000 | G2: MES | H2: =Detallado!R2 -> 05 | I2: AÑO | J2: =Detallado!S2 -> 2026 | K2: F. INGRESO | L2: =VLOOKUP(A6,'BD Total'!$A$2:$EZ$17,11,FALSE) -> 42632 | O2: # | P2: 1 | W2: 1007874085 | X2: 260130RRCOI9 | Y2: 07874085
E3: PERIODO | F3: =VLOOKUP($A$6,Detallado!$C:$U,16,FALSE) -> 05 | G3: DEL | H3: =VLOOKUP($A$6,Detallado!$C:$U,18,FALSE) -> 01/05/2026 | I3: AL | J3: =VLOOKUP($A$6,Detallado!$C:$U,19,FALSE) -> 46173 | K3: F. RETIRO | W3: 1040703418 | X3: 595200FCCCA8 | Y3: 40703418
W4: 1044771836 | X4: 621441RFSRR2 | Y4: 44771836
A5: CÓDIGO | B5: NOMBRES Y APELLIDOS | E5: CARGO | I5: AREA | W5: 1045191394 | X5: 322431AABAT4 | Y5: 45191394
A6: 1047924040 | B6: =VLOOKUP(A6,Dev!$C$1:$D$78,2,FALSE) -> MARÍA DEL CARMEN NEYRA ELLIOT | E6: =VLOOKUP(A6,'BD Total'!$A$2:$EZ$18,77,FALSE) -> QUALITY PROCESS MANAGER | I6: =VLOOKUP(A6,'BD Total'!$A$2:$EZ$18,81,FALSE) -> OPERATIONS | W6: 1046129072 | X6: 628890LLCAD9 | Y6: 46129072
A7: D.N.I. | B7: CUSPP AFP | C7: # AG ESSALUD | E7: SALARIO | G7: MONEDA | I7: CODIGO EMPRESA | K7: A.F.P. | W7: 1046722547 | X7: 632311FKROJ0 | Y7: 46722547
A8: =VLOOKUP(A6,'BD Total'!$A$2:$EZ$18,2,FALSE) -> 47924040 | B8: =VLOOKUP(A6,'BD Total'!$A$2:$EZ$18,85,FALSE) -> 641640MNERI3 | C8: =VLOOKUP(A6,$W$1:$Y$20,2,FALSE) -> 641640MNERI3 | E8: =VLOOKUP(A6,'BD Total'!$A$2:$EZ$18,22,FALSE) -> 6552 | G8: SOL | I8: =VLOOKUP(A6,$W$1:$Y$20,3,FALSE) -> 47924040 | K8: =VLOOKUP(A6,'BD Total'!$A$2:$EZ$18,101,FALSE) -> HABITAT | W8: 1047924040 | X8: 641640MNERI3 | Y8: 47924040
W9: 1070165336 | X9: 640621VFCNT9 | Y9: 70165336
A10: REMUNERACIONES | E10: DESCUENTOS TRABAJADOR | I10: APORTACIONES EMPLEADOR | W10: 1070680748 | X10: 0 | Y10: 70680748
A11: CONCEPTO | C11: HORAS | D11: VALOR | E11: CONCEPTO | G11: HORAS | H11: VALOR | I11: CONCEPTO | K11: HORAS | L11: VALOR | W11: 1072251509 | X11: 631390CHTMR2 | Y11: 72251509
A12: A000 SUELDO BASICO | C12: =SUMIF(Dev!$B:$B,CONCATENATE($A$6,A12),Dev!$L:$L) -> 144 | D12: =SUMIF(Dev!$B:$B,CONCATENATE($A$6,A12),Dev!M:M) -> 3931.2 | E12: I100 APORTE OBLIGATORIO AFP | G12: =SUMIF(Dev!$B:$B,CONCATENATE($A$6,E12),Dev!$L:$L) -> 0 | H12: =SUMIF(Dev!$B:$B,CONCATENATE($A$6,E12),Dev!N:N) -> 655.2 | I12: APORTE A ESSALUD | K12: 0 | L12: =VLOOKUP(A6,ESSALUD!$B$1:$G$19,6,FALSE) -> 442.26 | W12: 1077485287 | X12: 655610ZCBIT4 | Y12: 77485287
A13: D013 AUXILIO DE MOVILIDAD | C13: =SUMIF(Dev!$B:$B,CONCATENATE($A$6,A13),Dev!$L:$L) -> 0 | D13: =SUMIF(Dev!$B:$B,CONCATENATE($A$6,A13),Dev!M:M) -> 36 | E13: I200 SOBREVIVENCIA AFP | G13: =SUMIF(Dev!$B:$B,CONCATENATE($A$6,E13),Dev!$L:$L) -> 0 | H13: =SUMIF(Dev!$B:$B,CONCATENATE($A$6,E13),Dev!N:N) -> 89.76 | I13: CREDITO EPS | K13: 0 | L13: =VLOOKUP(A6,ESSALUD!$B$1:$H$19,7,FALSE) -> 147.42 | W13: 2001252358 | X13: 627991JMXQX0 | Y13: 001252358
A14: G006 VACACIONES | C14: =SUMIF(Dev!$B:$B,CONCATENATE($A$6,A14),Dev!$L:$L) -> 96 | D14: =SUMIF(Dev!$B:$B,CONCATENATE($A$6,A14),Dev!M:M) -> 2620.8 | E14: R000 RETENCION IMPUESTO A LA RENTA | G14: =SUMIF(Dev!$B:$B,CONCATENATE($A$6,#REF!),Dev!$L:$L) -> 0 | H14: =SUMIF(Dev!$B:$B,CONCATENATE($A$6,E14),Dev!N:N) -> 501.01 | W14: 42115329 | X14: FACILITIES | Y14: 42115329
W15: 42683912 | X15: 309631GHMAI4 | Y15: 42683912
W16: 72836862 | X16: 663680JMDIO1 | Y16: 72836862
W17: 76607245 | X17: N/A | Y17: 76607245
W18: 74026184 | X18: N/A | Y18: 74026184
I25: TOTAL APORTE EMPLEADOR | L25: =SUM(L12:L24) -> 589.68
A26: REMUNERACION TOTAL | D26: =SUM(D12:D24) -> 6588 | E26: DESCUENTOS TOTALES | H26: =SUM(H12:H24) -> 1245.97 | I26: REMUNERACION NETA | L26: =+D26-H26 -> 5342.03
F36: REPRESENTANTE LEGAL | J36: RECIBI CONFORME TRABAJADOR

Sheet PS1 (6)
A1: BOLETA DE PAGO | W1: EMPLEADO | X1: # AG ESSALUD | Y1: CODIGO EMPRESA
A2: EMPRESA | B2: CLARKE, MODET & CO. PERU S.A.C. | E2: R.U.C. | F2: 20256396000 | G2: MES | H2: =Detallado!R2 -> 05 | I2: AÑO | J2: =Detallado!S2 -> 2026 | K2: F. INGRESO | L2: =VLOOKUP(A6,'BD Total'!$A$2:$EZ$17,11,FALSE) -> 44151 | O2: # | P2: 1 | W2: 1007874085 | X2: 260130RRCOI9 | Y2: 07874085
E3: PERIODO | F3: =VLOOKUP($A$6,Detallado!$C:$U,16,FALSE) -> 05 | G3: DEL | H3: =VLOOKUP($A$6,Detallado!$C:$U,18,FALSE) -> 01/05/2026 | I3: AL | J3: =VLOOKUP($A$6,Detallado!$C:$U,19,FALSE) -> 46173 | K3: F. RETIRO | W3: 1040703418 | X3: 595200FCCCA8 | Y3: 40703418
W4: 1044771836 | X4: 621441RFSRR2 | Y4: 44771836
A5: CÓDIGO | B5: NOMBRES Y APELLIDOS | E5: CARGO | I5: AREA | W5: 1045191394 | X5: 322431AABAT4 | Y5: 45191394
A6: 1046722547 | B6: =VLOOKUP(A6,Dev!$C$1:$D$78,2,FALSE) -> FELIX ALEJANDRO KOO RIOJA | E6: =VLOOKUP(A6,'BD Total'!$A$2:$EZ$18,77,FALSE) -> FINANCE & ACCOUNTING SPECIALIST | I6: =VLOOKUP(A6,'BD Total'!$A$2:$EZ$18,81,FALSE) -> FINANZAS | W6: 1046129072 | X6: 628890LLCAD9 | Y6: 46129072
A7: D.N.I. | B7: CUSPP AFP | C7: # AG ESSALUD | E7: SALARIO | G7: MONEDA | I7: CODIGO EMPRESA | K7: A.F.P. | W7: 1046722547 | X7: 632311FKROJ0 | Y7: 46722547
A8: =VLOOKUP(A6,'BD Total'!$A$2:$EZ$18,2,FALSE) -> 46722547 | B8: =VLOOKUP(A6,'BD Total'!$A$2:$EZ$18,85,FALSE) -> 632311FKROJ0 | C8: =VLOOKUP(A6,$W$1:$Y$20,2,FALSE) -> 632311FKROJ0 | E8: =VLOOKUP(A6,'BD Total'!$A$2:$EZ$18,22,FALSE) -> 5733 | G8: SOL | I8: =VLOOKUP(A6,$W$1:$Y$20,3,FALSE) -> 46722547 | K8: =VLOOKUP(A6,'BD Total'!$A$2:$EZ$18,101,FALSE) -> INTEGRA | W8: 1047924040 | X8: 641640MNERI3 | Y8: 47924040
W9: 1070165336 | X9: 640621VFCNT9 | Y9: 70165336
A10: REMUNERACIONES | E10: DESCUENTOS TRABAJADOR | I10: APORTACIONES EMPLEADOR | W10: 1070680748 | X10: 0 | Y10: 70680748
A11: CONCEPTO | C11: HORAS | D11: VALOR | E11: CONCEPTO | G11: HORAS | H11: VALOR | I11: CONCEPTO | K11: HORAS | L11: VALOR | W11: 1072251509 | X11: 631390CHTMR2 | Y11: 72251509
A12: A000 SUELDO BASICO | C12: =SUMIF(Dev!$B:$B,CONCATENATE($A$6,A12),Dev!$L:$L) -> 128 | D12: =SUMIF(Dev!$B:$B,CONCATENATE($A$6,A12),Dev!M:M) -> 3057.6 | E12: I100 APORTE OBLIGATORIO AFP | G12: =SUMIF(Dev!$B:$B,CONCATENATE($A$6,E12),Dev!$L:$L) -> 0 | H12: =SUMIF(Dev!$B:$B,CONCATENATE($A$6,E12),Dev!N:N) -> 573.3 | I12: APORTE A ESSALUD | K12: 0 | L12: =VLOOKUP(A6,ESSALUD!$B$1:$G$19,6,FALSE) -> 386.9775 | W12: 1077485287 | X12: 655610ZCBIT4 | Y12: 77485287
A13: G006 VACACIONES | C13: =SUMIF(Dev!$B:$B,CONCATENATE($A$6,A13),Dev!$L:$L) -> 112 | D13: =SUMIF(Dev!$B:$B,CONCATENATE($A$6,A13),Dev!M:M) -> 2675.4 | E13: I200 SOBREVIVENCIA AFP | G13: =SUMIF(Dev!$B:$B,CONCATENATE($A$6,E13),Dev!$L:$L) -> 0 | H13: =SUMIF(Dev!$B:$B,CONCATENATE($A$6,E13),Dev!N:N) -> 78.54 | I13: CREDITO EPS | K13: 0 | L13: =VLOOKUP(A6,ESSALUD!$B$1:$H$19,7,FALSE) -> 128.9925 | W13: 2001252358 | X13: 627991JMXQX0 | Y13: 001252358
E14: R000 RETENCION IMPUESTO A LA RENTA | G14: =SUMIF(Dev!$B:$B,CONCATENATE($A$6,#REF!),Dev!$L:$L) -> 0 | H14: =SUMIF(Dev!$B:$B,CONCATENATE($A$6,E14),Dev!N:N) -> 363.08 | W14: 42115329 | X14: FACILITIES | Y14: 42115329
W15: 42683912 | X15: 309631GHMAI4 | Y15: 42683912
W16: 72836862 | X16: 663680JMDIO1 | Y16: 72836862
W17: 76607245 | X17: N/A | Y17: 76607245
W18: 74026184 | X18: N/A | Y18: 74026184
I25: TOTAL APORTE EMPLEADOR | L25: =SUM(L12:L24) -> 515.97
A26: REMUNERACION TOTAL | D26: =SUM(D12:D24) -> 5733 | E26: DESCUENTOS TOTALES | H26: =SUM(H12:H24) -> 1014.92 | I26: REMUNERACION NETA | L26: =+D26-H26 -> 4718.08
F36: REPRESENTANTE LEGAL | J36: RECIBI CONFORME TRABAJADOR

Sheet PS1 (5)
A1: BOLETA DE PAGO | W1: EMPLEADO | X1: # AG ESSALUD | Y1: CODIGO EMPRESA
A2: EMPRESA | B2: CLARKE, MODET & CO. PERU S.A.C. | E2: R.U.C. | F2: 20256396000 | G2: MES | H2: =Detallado!R2 -> 05 | I2: AÑO | J2: =Detallado!S2 -> 2026 | K2: F. INGRESO | L2: =VLOOKUP(A6,'BD Total'!$A$2:$EZ$17,11,FALSE) -> 42765 | O2: # | P2: 1 | W2: 1007874085 | X2: 260130RRCOI9 | Y2: 07874085
E3: PERIODO | F3: =VLOOKUP($A$6,Detallado!$C:$U,16,FALSE) -> 05 | G3: DEL | H3: =VLOOKUP($A$6,Detallado!$C:$U,18,FALSE) -> 01/05/2026 | I3: AL | J3: =VLOOKUP($A$6,Detallado!$C:$U,19,FALSE) -> 46173 | K3: F. RETIRO | W3: 1040703418 | X3: 595200FCCCA8 | Y3: 40703418
W4: 1044771836 | X4: 621441RFSRR2 | Y4: 44771836
A5: CÓDIGO | B5: NOMBRES Y APELLIDOS | E5: CARGO | I5: AREA | W5: 1045191394 | X5: 322431AABAT4 | Y5: 45191394
A6: 1046129072 | B6: =VLOOKUP(A6,Dev!$C$1:$D$78,2,FALSE) -> LAURA CAROLINA LIRA CANDIA | E6: =VLOOKUP(A6,'BD Total'!$A$2:$EZ$18,77,FALSE) -> IP PROSECUTION SPECIALIST | I6: =VLOOKUP(A6,'BD Total'!$A$2:$EZ$18,81,FALSE) -> CENTRAL SERVICES | W6: 1046129072 | X6: 628890LLCAD9 | Y6: 46129072
A7: D.N.I. | B7: CUSPP AFP | C7: # AG ESSALUD | E7: SALARIO | G7: MONEDA | I7: CODIGO EMPRESA | K7: A.F.P. | W7: 1046722547 | X7: 632311FKROJ0 | Y7: 46722547
A8: =VLOOKUP(A6,'BD Total'!$A$2:$EZ$18,2,FALSE) -> 46129072 | B8: =VLOOKUP(A6,'BD Total'!$A$2:$EZ$18,85,FALSE) -> 628890LLCAD9 | C8: =VLOOKUP(A6,$W$1:$Y$20,2,FALSE) -> 628890LLCAD9 | E8: =VLOOKUP(A6,'BD Total'!$A$2:$EZ$18,22,FALSE) -> 3871 | G8: SOL | I8: =VLOOKUP(A6,$W$1:$Y$20,3,FALSE) -> 46129072 | K8: =VLOOKUP(A6,'BD Total'!$A$2:$EZ$18,101,FALSE) -> HABITAT | W8: 1047924040 | X8: 641640MNERI3 | Y8: 47924040
W9: 1070165336 | X9: 640621VFCNT9 | Y9: 70165336
A10: REMUNERACIONES | E10: DESCUENTOS TRABAJADOR | I10: APORTACIONES EMPLEADOR | W10: 1070680748 | X10: 0 | Y10: 70680748
A11: CONCEPTO | C11: HORAS | D11: VALOR | E11: CONCEPTO | G11: HORAS | H11: VALOR | I11: CONCEPTO | K11: HORAS | L11: VALOR | W11: 1072251509 | X11: 631390CHTMR2 | Y11: 72251509
A12: A000 SUELDO BASICO | C12: =SUMIF(Dev!$B:$B,CONCATENATE($A$6,A12),Dev!$L:$L) -> 184 | D12: =SUMIF(Dev!$B:$B,CONCATENATE($A$6,A12),Dev!M:M) -> 2967.77 | E12: I100 APORTE OBLIGATORIO AFP | G12: =SUMIF(Dev!$B:$B,CONCATENATE($A$6,E12),Dev!$L:$L) -> 0 | H12: =SUMIF(Dev!$B:$B,CONCATENATE($A$6,E12),Dev!N:N) -> 387.1 | I12: APORTE A ESSALUD | K12: 0 | L12: =VLOOKUP(A6,ESSALUD!$B$1:$G$19,6,FALSE) -> 261.2925 | W12: 1077485287 | X12: 655610ZCBIT4 | Y12: 77485287
A13: D013 AUXILIO DE MOVILIDAD | C13: =SUMIF(Dev!$B:$B,CONCATENATE($A$6,A13),Dev!$L:$L) -> 0 | D13: =SUMIF(Dev!$B:$B,CONCATENATE($A$6,A13),Dev!M:M) -> 36 | E13: I200 SOBREVIVENCIA AFP | G13: =SUMIF(Dev!$B:$B,CONCATENATE($A$6,E13),Dev!$L:$L) -> 0 | H13: =SUMIF(Dev!$B:$B,CONCATENATE($A$6,E13),Dev!N:N) -> 53.03 | I13: CREDITO EPS | K13: 0 | L13: =VLOOKUP(A6,ESSALUD!$B$1:$H$19,7,FALSE) -> 87.0975 | W13: 2001252358 | X13: 627991JMXQX0 | Y13: 001252358
A14: G006 VACACIONES | C14: =SUMIF(Dev!$B:$B,CONCATENATE($A$6,A14),Dev!$L:$L) -> 56 | D14: =SUMIF(Dev!$B:$B,CONCATENATE($A$6,A14),Dev!M:M) -> 903.23 | E14: R000 RETENCION IMPUESTO A LA RENTA | G14: =SUMIF(Dev!$B:$B,CONCATENATE($A$6,#REF!),Dev!$L:$L) -> 0 | H14: =SUMIF(Dev!$B:$B,CONCATENATE($A$6,E14),Dev!N:N) -> 109.98 | W14: 42115329 | X14: FACILITIES | Y14: 42115329
W15: 42683912 | X15: 309631GHMAI4 | Y15: 42683912
W16: 72836862 | X16: 663680JMDIO1 | Y16: 72836862
W17: 76607245 | X17: N/A | Y17: 76607245
W18: 74026184 | X18: N/A | Y18: 74026184
I25: TOTAL APORTE EMPLEADOR | L25: =SUM(L12:L24) -> 348.39
A26: REMUNERACION TOTAL | D26: =SUM(D12:D24) -> 3907 | E26: DESCUENTOS TOTALES | H26: =SUM(H12:H24) -> 550.11 | I26: REMUNERACION NETA | L26: =+D26-H26 -> 3356.89
F36: REPRESENTANTE LEGAL | J36: RECIBI CONFORME TRABAJADOR

Sheet PS1 (4)
A1: BOLETA DE PAGO | W1: EMPLEADO | X1: # AG ESSALUD | Y1: CODIGO EMPRESA
A2: EMPRESA | B2: CLARKE, MODET & CO. PERU S.A.C. | E2: R.U.C. | F2: 20256396000 | G2: MES | H2: =Detallado!R2 -> 05 | I2: AÑO | J2: =Detallado!S2 -> 2026 | K2: F. INGRESO | L2: =VLOOKUP(A6,'BD Total'!$A$2:$EZ$17,11,FALSE) -> 42989 | O2: # | P2: 1 | W2: 1007874085 | X2: 260130RRCOI9 | Y2: 07874085
E3: PERIODO | F3: =VLOOKUP($A$6,Detallado!$C:$U,16,FALSE) -> 05 | G3: DEL | H3: =VLOOKUP($A$6,Detallado!$C:$U,18,FALSE) -> 01/05/2026 | I3: AL | J3: =VLOOKUP($A$6,Detallado!$C:$U,19,FALSE) -> 46173 | K3: F. RETIRO | W3: 1040703418 | X3: 595200FCCCA8 | Y3: 40703418
W4: 1044771836 | X4: 621441RFSRR2 | Y4: 44771836
A5: CÓDIGO | B5: NOMBRES Y APELLIDOS | E5: CARGO | I5: AREA | W5: 1045191394 | X5: 322431AABAT4 | Y5: 45191394
A6: 1045191394 | B6: =VLOOKUP(A6,Dev!$C$1:$D$78,2,FALSE) -> ALVARO JAVIER ARIAS BAUTISTA | E6: =VLOOKUP(A6,'BD Total'!$A$2:$EZ$18,77,FALSE) -> COUNTRY MANAGING DIRECTOR | I6: =VLOOKUP(A6,'BD Total'!$A$2:$EZ$18,81,FALSE) -> CEO | W6: 1046129072 | X6: 628890LLCAD9 | Y6: 46129072
A7: D.N.I. | B7: CUSPP AFP | C7: # AG ESSALUD | E7: SALARIO | G7: MONEDA | I7: CODIGO EMPRESA | K7: A.F.P. | W7: 1046722547 | X7: 632311FKROJ0 | Y7: 46722547
A8: =VLOOKUP(A6,'BD Total'!$A$2:$EZ$18,2,FALSE) -> 45191394 | B8: =VLOOKUP(A6,'BD Total'!$A$2:$EZ$18,85,FALSE) -> 322431AABAT4 | C8: =VLOOKUP(A6,$W$1:$Y$20,2,FALSE) -> 322431AABAT4 | E8: =VLOOKUP(A6,'BD Total'!$A$2:$EZ$18,22,FALSE) -> 14615 | G8: SOL | I8: =VLOOKUP(A6,$W$1:$Y$20,3,FALSE) -> 45191394 | K8: =VLOOKUP(A6,'BD Total'!$A$2:$EZ$18,101,FALSE) -> PROFUTURO | W8: 1047924040 | X8: 641640MNERI3 | Y8: 47924040
W9: 1070165336 | X9: 640621VFCNT9 | Y9: 70165336
A10: REMUNERACIONES | E10: DESCUENTOS TRABAJADOR | I10: APORTACIONES EMPLEADOR | W10: 1070680748 | X10: 0 | Y10: 70680748
A11: CONCEPTO | C11: HORAS | D11: VALOR | E11: CONCEPTO | G11: HORAS | H11: VALOR | I11: CONCEPTO | K11: HORAS | L11: VALOR | W11: 1072251509 | X11: 631390CHTMR2 | Y11: 72251509
A12: A000 SUELDO BASICO | C12: =SUMIF(Dev!$B:$B,CONCATENATE($A$6,A12),Dev!$L:$L) -> 240 | D12: =SUMIF(Dev!$B:$B,CONCATENATE($A$6,A12),Dev!M:M) -> 14615 | E12: I100 APORTE OBLIGATORIO AFP | G12: =SUMIF(Dev!$B:$B,CONCATENATE($A$6,E12),Dev!$L:$L) -> 0 | H12: =SUMIF(Dev!$B:$B,CONCATENATE($A$6,E12),Dev!N:N) -> 1461.5 | I12: APORTE A ESSALUD | K12: 0 | L12: =VLOOKUP(A6,ESSALUD!$B$1:$G$19,6,FALSE) -> 986.5125 | W12: 1077485287 | X12: 655610ZCBIT4 | Y12: 77485287
E13: I200 SOBREVIVENCIA AFP | G13: =SUMIF(Dev!$B:$B,CONCATENATE($A$6,E13),Dev!$L:$L) -> 0 | H13: =SUMIF(Dev!$B:$B,CONCATENATE($A$6,E13),Dev!N:N) -> 172.61 | I13: CREDITO EPS | K13: 0 | L13: =VLOOKUP(A6,ESSALUD!$B$1:$H$19,7,FALSE) -> 328.8375 | W13: 2001252358 | X13: 627991JMXQX0 | Y13: 001252358
E14: R000 RETENCION IMPUESTO A LA RENTA | G14: =SUMIF(Dev!$B:$B,CONCATENATE($A$6,#REF!),Dev!$L:$L) -> 0 | H14: =SUMIF(Dev!$B:$B,CONCATENATE($A$6,E14),Dev!N:N) -> 1972.88 | W14: 42115329 | X14: FACILITIES | Y14: 42115329
W15: 42683912 | X15: 309631GHMAI4 | Y15: 42683912
W16: 72836862 | X16: 663680JMDIO1 | Y16: 72836862
W17: 76607245 | X17: N/A | Y17: 76607245
W18: 74026184 | X18: N/A | Y18: 74026184
I25: TOTAL APORTE EMPLEADOR | L25: =SUM(L12:L24) -> 1315.35
A26: REMUNERACION TOTAL | D26: =SUM(D12:D24) -> 14615 | E26: DESCUENTOS TOTALES | H26: =SUM(H12:H24) -> 3606.99 | I26: REMUNERACION NETA | L26: =+D26-H26 -> 11008.01
F36: REPRESENTANTE LEGAL | J36: RECIBI CONFORME TRABAJADOR

Sheet PS1 (3)
A1: BOLETA DE PAGO | W1: EMPLEADO | X1: # AG ESSALUD | Y1: CODIGO EMPRESA
A2: EMPRESA | B2: CLARKE, MODET & CO. PERU S.A.C. | E2: R.U.C. | F2: 20256396000 | G2: MES | H2: =Detallado!R2 -> 05 | I2: AÑO | J2: =Detallado!S2 -> 2026 | K2: F. INGRESO | L2: =VLOOKUP(A6,'BD Total'!$A$2:$EZ$17,11,FALSE) -> 42506 | O2: # | P2: 1 | W2: 1007874085 | X2: 260130RRCOI9 | Y2: 07874085
E3: PERIODO | F3: =VLOOKUP($A$6,Detallado!$C:$U,16,FALSE) -> 05 | G3: DEL | H3: =VLOOKUP($A$6,Detallado!$C:$U,18,FALSE) -> 01/05/2026 | I3: AL | J3: =VLOOKUP($A$6,Detallado!$C:$U,19,FALSE) -> 46173 | K3: F. RETIRO | W3: 1040703418 | X3: 595200FCCCA8 | Y3: 40703418
W4: 1044771836 | X4: 621441RFSRR2 | Y4: 44771836
A5: CÓDIGO | B5: NOMBRES Y APELLIDOS | E5: CARGO | I5: AREA | W5: 1045191394 | X5: 322431AABAT4 | Y5: 45191394
A6: 1044771836 | B6: =VLOOKUP(A6,Dev!$C$1:$D$78,2,FALSE) -> RONALD FLOREZ SUAREZ | E6: =VLOOKUP(A6,'BD Total'!$A$2:$EZ$18,77,FALSE) -> IP PROSECUTION SPECIALIST | I6: =VLOOKUP(A6,'BD Total'!$A$2:$EZ$18,81,FALSE) -> INVENTIONS | W6: 1046129072 | X6: 628890LLCAD9 | Y6: 46129072
A7: D.N.I. | B7: CUSPP AFP | C7: # AG ESSALUD | E7: SALARIO | G7: MONEDA | I7: CODIGO EMPRESA | K7: A.F.P. | W7: 1046722547 | X7: 632311FKROJ0 | Y7: 46722547
A8: =VLOOKUP(A6,'BD Total'!$A$2:$EZ$18,2,FALSE) -> 44771836 | B8: =VLOOKUP(A6,'BD Total'!$A$2:$EZ$18,85,FALSE) -> 621441RFSRR2 | C8: =VLOOKUP(A6,$W$1:$Y$20,2,FALSE) -> 621441RFSRR2 | E8: =VLOOKUP(A6,'BD Total'!$A$2:$EZ$18,22,FALSE) -> 8842 | G8: SOL | I8: =VLOOKUP(A6,$W$1:$Y$20,3,FALSE) -> 44771836 | K8: =VLOOKUP(A6,'BD Total'!$A$2:$EZ$18,101,FALSE) -> PROFUTURO | W8: 1047924040 | X8: 641640MNERI3 | Y8: 47924040
W9: 1070165336 | X9: 640621VFCNT9 | Y9: 70165336
A10: REMUNERACIONES | E10: DESCUENTOS TRABAJADOR | I10: APORTACIONES EMPLEADOR | W10: 1070680748 | X10: 0 | Y10: 70680748
A11: CONCEPTO | C11: HORAS | D11: VALOR | E11: CONCEPTO | G11: HORAS | H11: VALOR | I11: CONCEPTO | K11: HORAS | L11: VALOR | W11: 1072251509 | X11: 631390CHTMR2 | Y11: 72251509
A12: A000 SUELDO BASICO | C12: =SUMIF(Dev!$B:$B,CONCATENATE($A$6,A12),Dev!$L:$L) -> 184 | D12: =SUMIF(Dev!$B:$B,CONCATENATE($A$6,A12),Dev!M:M) -> 6778.87 | E12: I100 APORTE OBLIGATORIO AFP | G12: =SUMIF(Dev!$B:$B,CONCATENATE($A$6,E12),Dev!$L:$L) -> 0 | H12: =SUMIF(Dev!$B:$B,CONCATENATE($A$6,E12),Dev!N:N) -> 884.2 | I12: APORTE A ESSALUD | K12: 0 | L12: =VLOOKUP(A6,ESSALUD!$B$1:$G$19,6,FALSE) -> 596.835 | W12: 1077485287 | X12: 655610ZCBIT4 | Y12: 77485287
A13: G006 VACACIONES | C13: =SUMIF(Dev!$B:$B,CONCATENATE($A$6,A13),Dev!$L:$L) -> 56 | D13: =SUMIF(Dev!$B:$B,CONCATENATE($A$6,A13),Dev!M:M) -> 2063.13 | E13: I200 SOBREVIVENCIA AFP | G13: =SUMIF(Dev!$B:$B,CONCATENATE($A$6,E13),Dev!$L:$L) -> 0 | H13: =SUMIF(Dev!$B:$B,CONCATENATE($A$6,E13),Dev!N:N) -> 121.14 | I13: CREDITO EPS | K13: 0 | L13: =VLOOKUP(A6,ESSALUD!$B$1:$H$19,7,FALSE) -> 198.945 | W13: 2001252358 | X13: 627991JMXQX0 | Y13: 001252358
E14: I300 COMISION VARIABLE AFP | G14: =SUMIF(Dev!$B:$B,CONCATENATE($A$6,E14),Dev!$L:$L) -> 0 | H14: =SUMIF(Dev!$B:$B,CONCATENATE($A$6,E14),Dev!N:N) -> 149.43 | W14: 42115329 | X14: FACILITIES | Y14: 42115329
E15: R000 RETENCION IMPUESTO A LA RENTA | G15: =SUMIF(Dev!$B:$B,CONCATENATE($A$6,E15),Dev!$L:$L) -> 0 | H15: =SUMIF(Dev!$B:$B,CONCATENATE($A$6,E15),Dev!N:N) -> 871.57 | W15: 42683912 | X15: 309631GHMAI4 | Y15: 42683912
W16: 72836862 | X16: 663680JMDIO1 | Y16: 72836862
W17: 76607245 | X17: N/A | Y17: 76607245
W18: 74026184 | X18: N/A | Y18: 74026184
I25: TOTAL APORTE EMPLEADOR | L25: =SUM(L12:L24) -> 795.78
A26: REMUNERACION TOTAL | D26: =SUM(D12:D24) -> 8842 | E26: DESCUENTOS TOTALES | H26: =SUM(H12:H24) -> 2026.34 | I26: REMUNERACION NETA | L26: =+D26-H26 -> 6815.66
F36: REPRESENTANTE LEGAL | J36: RECIBI CONFORME TRABAJADOR

Sheet PS1 (2)
A1: BOLETA DE PAGO | W1: EMPLEADO | X1: # AG ESSALUD | Y1: CODIGO EMPRESA
A2: EMPRESA | B2: CLARKE, MODET & CO. PERU S.A.C. | E2: R.U.C. | F2: 20256396000 | G2: MES | H2: =Detallado!R2 -> 05 | I2: AÑO | J2: =Detallado!S2 -> 2026 | K2: F. INGRESO | L2: =VLOOKUP(A6,'BD Total'!$A$2:$EZ$17,11,FALSE) -> 42257 | O2: # | P2: 1 | W2: 1007874085 | X2: 260130RRCOI9 | Y2: 07874085
E3: PERIODO | F3: =VLOOKUP($A$6,Detallado!$C:$U,16,FALSE) -> 05 | G3: DEL | H3: =VLOOKUP($A$6,Detallado!$C:$U,18,FALSE) -> 01/05/2026 | I3: AL | J3: =VLOOKUP($A$6,Detallado!$C:$U,19,FALSE) -> 46173 | K3: F. RETIRO | W3: 1040703418 | X3: 595200FCCCA8 | Y3: 40703418
W4: 1044771836 | X4: 621441RFSRR2 | Y4: 44771836
A5: CÓDIGO | B5: NOMBRES Y APELLIDOS | E5: CARGO | I5: AREA | W5: 1045191394 | X5: 322431AABAT4 | Y5: 45191394
A6: 1040703418 | B6: =VLOOKUP(A6,Dev!$C$1:$D$78,2,FALSE) -> FIORELLA GIOVANNA CHICHIZOLA CANALE | E6: =VLOOKUP(A6,'BD Total'!$A$2:$EZ$18,77,FALSE) -> IP PROSECUTION SPECIALIST | I6: =VLOOKUP(A6,'BD Total'!$A$2:$EZ$18,81,FALSE) -> CENTRAL SERVICES | W6: 1046129072 | X6: 628890LLCAD9 | Y6: 46129072
A7: D.N.I. | B7: CUSPP AFP | C7: # AG ESSALUD | E7: SALARIO | G7: MONEDA | I7: CODIGO EMPRESA | K7: A.F.P. | W7: 1046722547 | X7: 632311FKROJ0 | Y7: 46722547
A8: =VLOOKUP(A6,'BD Total'!$A$2:$EZ$18,2,FALSE) -> 40703418 | B8: =VLOOKUP(A6,'BD Total'!$A$2:$EZ$18,85,FALSE) -> 595200FCCCA8 | C8: =VLOOKUP(A6,$W$1:$Y$20,2,FALSE) -> 595200FCCCA8 | E8: =VLOOKUP(A6,'BD Total'!$A$2:$EZ$18,22,FALSE) -> 3700 | G8: SOL | I8: =VLOOKUP(A6,$W$1:$Y$20,3,FALSE) -> 40703418 | K8: =VLOOKUP(A6,'BD Total'!$A$2:$EZ$18,101,FALSE) -> INTEGRA | W8: 1047924040 | X8: 641640MNERI3 | Y8: 47924040
W9: 1070165336 | X9: 640621VFCNT9 | Y9: 70165336
A10: REMUNERACIONES | E10: DESCUENTOS TRABAJADOR | I10: APORTACIONES EMPLEADOR | W10: 1070680748 | X10: 0 | Y10: 70680748
A11: CONCEPTO | C11: HORAS | D11: VALOR | E11: CONCEPTO | G11: HORAS | H11: VALOR | I11: CONCEPTO | K11: HORAS | L11: VALOR | W11: 1072251509 | X11: 631390CHTMR2 | Y11: 72251509
A12: A000 SUELDO BASICO | C12: =SUMIF(Dev!$B:$B,CONCATENATE($A$6,A12),Dev!$L:$L) -> 216 | D12: =SUMIF(Dev!$B:$B,CONCATENATE($A$6,A12),Dev!M:M) -> 3330 | E12: I100 APORTE OBLIGATORIO AFP | G12: =SUMIF(Dev!$B:$B,CONCATENATE($A$6,E12),Dev!$L:$L) -> 0 | H12: =SUMIF(Dev!$B:$B,CONCATENATE($A$6,E12),Dev!N:N) -> 370 | I12: APORTE A ESSALUD | K12: 0 | L12: =VLOOKUP(A6,ESSALUD!$B$1:$G$19,6,FALSE) -> 249.75 | W12: 1077485287 | X12: 655610ZCBIT4 | Y12: 77485287
A13: D013 AUXILIO DE MOVILIDAD | C13: =SUMIF(Dev!$B:$B,CONCATENATE($A$6,A13),Dev!$L:$L) -> 0 | D13: =SUMIF(Dev!$B:$B,CONCATENATE($A$6,A13),Dev!M:M) -> 24 | E13: I200 SOBREVIVENCIA AFP | G13: =SUMIF(Dev!$B:$B,CONCATENATE($A$6,E13),Dev!$L:$L) -> 0 | H13: =SUMIF(Dev!$B:$B,CONCATENATE($A$6,E13),Dev!N:N) -> 50.69 | I13: CREDITO EPS | K13: 0 | L13: =VLOOKUP(A6,ESSALUD!$B$1:$H$19,7,FALSE) -> 83.25 | W13: 2001252358 | X13: 627991JMXQX0 | Y13: 001252358
A14: B100 DESCANSO MEDICO | C14: =SUMIF(Dev!$B:$B,CONCATENATE($A$6,A14),Dev!$L:$L) -> 24 | D14: =SUMIF(Dev!$B:$B,CONCATENATE($A$6,A14),Dev!M:M) -> 370 | E14: I300 COMISION VARIABLE AFP | G14: =SUMIF(Dev!$B:$B,CONCATENATE($A$6,E14),Dev!$L:$L) -> 0 | H14: =SUMIF(Dev!$B:$B,CONCATENATE($A$6,E14),Dev!N:N) -> 57.35 | W14: 42115329 | X14: FACILITIES | Y14: 42115329
E15: R000 RETENCION IMPUESTO A LA RENTA | G15: =SUMIF(Dev!$B:$B,CONCATENATE($A$6,E15),Dev!$L:$L) -> 0 | H15: =SUMIF(Dev!$B:$B,CONCATENATE($A$6,E15),Dev!N:N) -> 93.85 | W15: 42683912 | X15: 309631GHMAI4 | Y15: 42683912
W16: 72836862 | X16: 663680JMDIO1 | Y16: 72836862
W17: 76607245 | X17: N/A | Y17: 76607245
W18: 74026184 | X18: N/A | Y18: 74026184
I25: TOTAL APORTE EMPLEADOR | L25: =SUM(L12:L24) -> 333
A26: REMUNERACION TOTAL | D26: =SUM(D12:D24) -> 3724 | E26: DESCUENTOS TOTALES | H26: =SUM(H12:H24) -> 571.89 | I26: REMUNERACION NETA | L26: =+D26-H26 -> 3152.11
F36: REPRESENTANTE LEGAL | J36: RECIBI CONFORME TRABAJADOR

Sheet PS1
A1: BOLETA DE PAGO | W1: EMPLEADO | X1: # AG ESSALUD | Y1: CODIGO EMPRESA
A2: EMPRESA | B2: CLARKE, MODET & CO. PERU S.A.C. | E2: R.U.C. | F2: 20256396000 | G2: MES | H2: =Detallado!R2 -> 05 | I2: AÑO | J2: =Detallado!S2 -> 2026 | K2: F. INGRESO | L2: =VLOOKUP(A6,'BD Total'!$A$2:$EZ$17,11,FALSE) -> 44348 | O2: # | P2: 1 | W2: 1007874085 | X2: 260130RRCOI9 | Y2: 07874085
E3: PERIODO | F3: =VLOOKUP($A$6,Detallado!$C:$U,16,FALSE) -> 05 | G3: DEL | H3: =VLOOKUP($A$6,Detallado!$C:$U,18,FALSE) -> 01/05/2026 | I3: AL | J3: =VLOOKUP($A$6,Detallado!$C:$U,19,FALSE) -> 46173 | K3: F. RETIRO | W3: 1040703418 | X3: 595200FCCCA8 | Y3: 40703418
W4: 1044771836 | X4: 621441RFSRR2 | Y4: 44771836
A5: CÓDIGO | B5: NOMBRES Y APELLIDOS | E5: CARGO | I5: AREA | W5: 1045191394 | X5: 322431AABAT4 | Y5: 45191394
A6: 1007874085 | B6: =VLOOKUP(A6,Dev!$C$1:$D$78,2,FALSE) -> ROCIO DE LOURDES RAMOS CORI | E6: =VLOOKUP(A6,'BD Total'!$A$2:$EZ$18,77,FALSE) -> IP PROSECUTION SPECIALIST | I6: =VLOOKUP(A6,'BD Total'!$A$2:$EZ$18,81,FALSE) -> CENTRAL SERVICES | W6: 1046129072 | X6: 628890LLCAD9 | Y6: 46129072
A7: D.N.I. | B7: CUSPP AFP | C7: # AG ESSALUD | E7: SALARIO | G7: MONEDA | I7: CODIGO EMPRESA | K7: A.F.P. | W7: 1046722547 | X7: 632311FKROJ0 | Y7: 46722547
A8: =VLOOKUP(A6,'BD Total'!$A$2:$EZ$18,2,FALSE) -> 07874085 | B8: =VLOOKUP(A6,'BD Total'!$A$2:$EZ$18,85,FALSE) -> 260130RRCOI9 | C8: =VLOOKUP(A6,$W$1:$Y$20,2,FALSE) -> 260130RRCOI9 | E8: =VLOOKUP(A6,'BD Total'!$A$2:$EZ$18,22,FALSE) -> 3899 | G8: SOL | I8: =VLOOKUP(A6,$W$1:$Y$20,3,FALSE) -> 07874085 | K8: =VLOOKUP(A6,'BD Total'!$A$2:$EZ$18,101,FALSE) -> INTEGRA | W8: 1047924040 | X8: 641640MNERI3 | Y8: 47924040
W9: 1070165336 | X9: 640621VFCNT9 | Y9: 70165336
A10: REMUNERACIONES | E10: DESCUENTOS TRABAJADOR | I10: APORTACIONES EMPLEADOR | W10: 1070680748 | X10: 0 | Y10: 70680748
A11: CONCEPTO | C11: HORAS | D11: VALOR | E11: CONCEPTO | G11: HORAS | H11: VALOR | I11: CONCEPTO | K11: HORAS | L11: VALOR | W11: 1072251509 | X11: 631390CHTMR2 | Y11: 72251509
A12: A000 SUELDO BASICO | C12: =SUMIF(Dev!$B:$B,CONCATENATE($A$6,A12),Dev!$L:$L) -> 240 | D12: =SUMIF(Dev!$B:$B,CONCATENATE($A$6,A12),Dev!M:M) -> 3899 | E12: R000 RETENCION IMPUESTO A LA RENTA | G12: =SUMIF(Dev!$B:$B,CONCATENATE($A$6,E12),Dev!$L:$L) -> 0 | H12: =SUMIF(Dev!$B:$B,CONCATENATE($A$6,E12),Dev!N:N) -> 121.57 | I12: APORTE A ESSALUD | K12: 0 | L12: =VLOOKUP(A6,ESSALUD!$B$1:$G$19,6,FALSE) -> 270.81 | W12: 1077485287 | X12: 655610ZCBIT4 | Y12: 77485287
A13: D013 AUXILIO DE MOVILIDAD | C13: =SUMIF(Dev!$B:$B,CONCATENATE($A$6,A13),Dev!$L:$L) -> 0 | D13: =SUMIF(Dev!$B:$B,CONCATENATE($A$6,A13),Dev!M:M) -> 36 | E13: S006 DESCUENTO EPS | G13: =SUMIF(Dev!$B:$B,CONCATENATE($A$6,E13),Dev!$L:$L) -> 0 | H13: =SUMIF(Dev!$B:$B,CONCATENATE($A$6,E13),Dev!N:N) -> 202.42 | I13: CREDITO EPS | K13: 0 | L13: =VLOOKUP(A6,ESSALUD!$B$1:$H$19,7,FALSE) -> 90.27 | W13: 2001252358 | X13: 627991JMXQX0 | Y13: 001252358
A14: A012 ASIGNACION FAMILIAR | C14: =SUMIF(Dev!$B:$B,CONCATENATE($A$6,A14),Dev!$L:$L) -> 0 | D14: =SUMIF(Dev!$B:$B,CONCATENATE($A$6,A14),Dev!M:M) -> 113 | W14: 42115329 | X14: FACILITIES | Y14: 42115329
W15: 42683912 | X15: 309631GHMAI4 | Y15: 42683912
W16: 72836862 | X16: 663680JMDIO1 | Y16: 72836862
W17: 76607245 | X17: N/A | Y17: 76607245
W18: 74026184 | X18: N/A | Y18: 74026184
I25: TOTAL APORTE EMPLEADOR | L25: =SUM(L12:L24) -> 361.08
A26: REMUNERACION TOTAL | D26: =SUM(D12:D24) -> 4048 | E26: DESCUENTOS TOTALES | H26: =SUM(H12:H24) -> 323.99 | I26: REMUNERACION NETA | L26: =+D26-H26 -> 3724.01
F36: REPRESENTANTE LEGAL | J36: RECIBI CONFORME TRABAJADOR

Sheet Dev
A1: Estructura | B1: LLAVE | C1: EMPLEADO | D1: NOMBRE COMPLETO | E1: DOCTO IDENT | F1: F ANTIGUEDAD | G1: SALARIO | H1: PERIODO/MES | I1: CONCEPTO | J1: DESCRIPCION CONCEPTO | K1: UNION | L1: HORAS | M1: VALOR DEVENGADO | N1: VALOR DEDUCCION | O1: NETO | Q1: DIA | R1: (Todas)
A2: 1 | B2: =+CONCATENATE($C2,$K2) -> 1007874085A000 SUELDO BASICO | C2: 1007874085 | D2: ROCIO DE LOURDES RAMOS CORI | E2: 07874085 | F2: 44348 | G2: 3899 | H2: 20260501 | I2: A000 | J2: SUELDO BASICO | K2: A000 SUELDO BASICO | L2: 240 | M2: 3899 | N2: 0 | O2: 3899 | Q2: VALOR DEDUCCION | R2: (Todas)
A3: 1 | B3: =+CONCATENATE($C3,$K3) -> 1007874085A012 ASIGNACION FAMILIAR | C3: 1007874085 | D3: ROCIO DE LOURDES RAMOS CORI | E3: 07874085 | F3: 44348 | G3: 3899 | H3: 20260501 | I3: A012 | J3: ASIGNACION FAMILIAR | K3: A012 ASIGNACION FAMILIAR | L3: 0 | M3: 113 | N3: 0 | O3: 113
A4: 1 | B4: =+CONCATENATE($C4,$K4) -> 1007874085D013 AUXILIO DE MOVILIDAD | C4: 1007874085 | D4: ROCIO DE LOURDES RAMOS CORI | E4: 07874085 | F4: 44348 | G4: 3899 | H4: 20260501 | I4: D013 | J4: AUXILIO DE MOVILIDAD | K4: D013 AUXILIO DE MOVILIDAD | L4: 0 | M4: 36 | N4: 0 | O4: 36 | Q4: CONCEPTO | R4: DESCRIPCION CONCEPTO | S4: Suma de VALOR DEVENGADO | T4: Suma de VALOR DEDUCCION | V4: =CONCATENATE(Q4," ",R4) -> CONCEPTO DESCRIPCION CONCEPTO
A5: 1 | B5: =+CONCATENATE($C5,$K5) -> 1007874085R000 RETENCION IMPUESTO A LA RENTA | C5: 1007874085 | D5: ROCIO DE LOURDES RAMOS CORI | E5: 07874085 | F5: 44348 | G5: 3899 | H5: 20260501 | I5: R000 | J5: RETENCION IMPUESTO A LA RENTA | K5: R000 RETENCION IMPUESTO A LA RENTA | L5: 0 | M5: 0 | N5: 121.57 | O5: -121.57 | Q5: A000 | R5: SUELDO BASICO | S5: 68343.28 | T5: 0 | V5: =CONCATENATE(Q5," ",R5) -> A000 SUELDO BASICO
A6: 1 | B6: =+CONCATENATE($C6,$K6) -> 1007874085S006 DESCUENTO EPS | C6: 1007874085 | D6: ROCIO DE LOURDES RAMOS CORI | E6: 07874085 | F6: 44348 | G6: 3899 | H6: 20260501 | I6: S006 | J6: DESCUENTO EPS | K6: S006 DESCUENTO EPS | L6: 0 | M6: 0 | N6: 202.42 | O6: -202.42 | Q6: A006 | R6: SUBVENCION ECONOMICA | S6: 1770.33 | T6: 0 | V6: =CONCATENATE(Q6," ",R6) -> A006 SUBVENCION ECONOMICA
A7: 2 | B7: =+CONCATENATE($C7,$K7) -> 1040703418A000 SUELDO BASICO | C7: 1040703418 | D7: FIORELLA GIOVANNA CHICHIZOLA CANALE | E7: 40703418 | F7: 42257 | G7: 3700 | H7: 20260501 | I7: A000 | J7: SUELDO BASICO | K7: A000 SUELDO BASICO | L7: 216 | M7: 3330 | N7: 0 | O7: 3330 | Q7: A012 | R7: ASIGNACION FAMILIAR | S7: 339 | T7: 0 | V7: =CONCATENATE(Q7," ",R7) -> A012 ASIGNACION FAMILIAR
A8: 2 | B8: =+CONCATENATE($C8,$K8) -> 1040703418B100 DESCANSO MEDICO | C8: 1040703418 | D8: FIORELLA GIOVANNA CHICHIZOLA CANALE | E8: 40703418 | F8: 42257 | G8: 3700 | H8: 20260501 | I8: B100 | J8: DESCANSO MEDICO | K8: B100 DESCANSO MEDICO | L8: 24 | M8: 370 | N8: 0 | O8: 370 | Q8: B100 | R8: DESCANSO MEDICO | S8: 370 | T8: 0 | V8: =CONCATENATE(Q8," ",R8) -> B100 DESCANSO MEDICO
A9: 2 | B9: =+CONCATENATE($C9,$K9) -> 1040703418D013 AUXILIO DE MOVILIDAD | C9: 1040703418 | D9: FIORELLA GIOVANNA CHICHIZOLA CANALE | E9: 40703418 | F9: 42257 | G9: 3700 | H9: 20260501 | I9: D013 | J9: AUXILIO DE MOVILIDAD | K9: D013 AUXILIO DE MOVILIDAD | L9: 0 | M9: 24 | N9: 0 | O9: 24 | Q9: D013 | R9: AUXILIO DE MOVILIDAD | S9: 412 | T9: 0 | V9: =CONCATENATE(Q9," ",R9) -> D013 AUXILIO DE MOVILIDAD
A10: 2 | B10: =+CONCATENATE($C10,$K10) -> 1040703418I100 APORTE OBLIGATORIO AFP | C10: 1040703418 | D10: FIORELLA GIOVANNA CHICHIZOLA CANALE | E10: 40703418 | F10: 42257 | G10: 3700 | H10: 20260501 | I10: I100 | J10: APORTE OBLIGATORIO AFP | K10: I100 APORTE OBLIGATORIO AFP | L10: 0 | M10: 0 | N10: 370 | O10: -370 | Q10: G006 | R10: VACACIONES | S10: 13762.72 | T10: 0 | V10: =CONCATENATE(Q10," ",R10) -> G006 VACACIONES
A11: 2 | B11: =+CONCATENATE($C11,$K11) -> 1040703418I200 SOBREVIVENCIA AFP | C11: 1040703418 | D11: FIORELLA GIOVANNA CHICHIZOLA CANALE | E11: 40703418 | F11: 42257 | G11: 3700 | H11: 20260501 | I11: I200 | J11: SOBREVIVENCIA AFP | K11: I200 SOBREVIVENCIA AFP | L11: 0 | M11: 0 | N11: 50.69 | O11: -50.69 | Q11: I100 | R11: APORTE OBLIGATORIO AFP | S11: 0 | T11: 8056.14 | V11: =CONCATENATE(Q11," ",R11) -> I100 APORTE OBLIGATORIO AFP
A12: 2 | B12: =+CONCATENATE($C12,$K12) -> 1040703418I300 COMISION VARIABLE AFP | C12: 1040703418 | D12: FIORELLA GIOVANNA CHICHIZOLA CANALE | E12: 40703418 | F12: 42257 | G12: 3700 | H12: 20260501 | I12: I300 | J12: COMISION VARIABLE AFP | K12: I300 COMISION VARIABLE AFP | L12: 0 | M12: 0 | N12: 57.35 | O12: -57.35 | Q12: I200 | R12: SOBREVIVENCIA AFP | S12: 0 | T12: 964.97 | V12: =CONCATENATE(Q12," ",R12) -> I200 SOBREVIVENCIA AFP
A13: 2 | B13: =+CONCATENATE($C13,$K13) -> 1040703418R000 RETENCION IMPUESTO A LA RENTA | C13: 1040703418 | D13: FIORELLA GIOVANNA CHICHIZOLA CANALE | E13: 40703418 | F13: 42257 | G13: 3700 | H13: 20260501 | I13: R000 | J13: RETENCION IMPUESTO A LA RENTA | K13: R000 RETENCION IMPUESTO A LA RENTA | L13: 0 | M13: 0 | N13: 93.85 | O13: -93.85 | Q13: I300 | R13: COMISION VARIABLE AFP | S13: 0 | T13: 254.68 | V13: =CONCATENATE(Q13," ",R13) -> I300 COMISION VARIABLE AFP
A14: 3 | B14: =+CONCATENATE($C14,$K14) -> 1044771836A000 SUELDO BASICO | C14: 1044771836 | D14: RONALD FLOREZ SUAREZ | E14: 44771836 | F14: 42506 | G14: 8842 | H14: 20260501 | I14: A000 | J14: SUELDO BASICO | K14: A000 SUELDO BASICO | L14: 184 | M14: 6778.87 | N14: 0 | O14: 6778.87 | Q14: R000 | R14: RETENCION IMPUESTO A LA RENTA | S14: 0 | T14: 5722.1 | V14: =CONCATENATE(Q14," ",R14) -> R000 RETENCION IMPUESTO A LA RENTA
A15: 3 | B15: =+CONCATENATE($C15,$K15) -> 1044771836G006 VACACIONES | C15: 1044771836 | D15: RONALD FLOREZ SUAREZ | E15: 44771836 | F15: 42506 | G15: 8842 | H15: 20260501 | I15: G006 | J15: VACACIONES | K15: G006 VACACIONES | L15: 56 | M15: 2063.13 | N15: 0 | O15: 2063.13 | Q15: S006 | R15: DESCUENTO EPS | S15: 0 | T15: 202.42 | V15: =CONCATENATE(Q15," ",R15) -> S006 DESCUENTO EPS
A16: 3 | B16: =+CONCATENATE($C16,$K16) -> 1044771836I100 APORTE OBLIGATORIO AFP | C16: 1044771836 | D16: RONALD FLOREZ SUAREZ | E16: 44771836 | F16: 42506 | G16: 8842 | H16: 20260501 | I16: I100 | J16: APORTE OBLIGATORIO AFP | K16: I100 APORTE OBLIGATORIO AFP | L16: 0 | M16: 0 | N16: 884.2 | O16: -884.2 | Q16: (en blanco) | R16: (en blanco) | V16: =CONCATENATE(Q16," ",R16) -> (en blanco) (en blanco)
A17: 3 | B17: =+CONCATENATE($C17,$K17) -> 1044771836I200 SOBREVIVENCIA AFP | C17: 1044771836 | D17: RONALD FLOREZ SUAREZ | E17: 44771836 | F17: 42506 | G17: 8842 | H17: 20260501 | I17: I200 | J17: SOBREVIVENCIA AFP | K17: I200 SOBREVIVENCIA AFP | L17: 0 | M17: 0 | N17: 121.14 | O17: -121.14 | V17: =CONCATENATE(Q17," ",R17)
A18: 3 | B18: =+CONCATENATE($C18,$K18) -> 1044771836I300 COMISION VARIABLE AFP | C18: 1044771836 | D18: RONALD FLOREZ SUAREZ | E18: 44771836 | F18: 42506 | G18: 8842 | H18: 20260501 | I18: I300 | J18: COMISION VARIABLE AFP | K18: I300 COMISION VARIABLE AFP | L18: 0 | M18: 0 | N18: 149.43 | O18: -149.43 | V18: =CONCATENATE(Q18," ",R18)
A19: 3 | B19: =+CONCATENATE($C19,$K19) -> 1044771836R000 RETENCION IMPUESTO A LA RENTA | C19: 1044771836 | D19: RONALD FLOREZ SUAREZ | E19: 44771836 | F19: 42506 | G19: 8842 | H19: 20260501 | I19: R000 | J19: RETENCION IMPUESTO A LA RENTA | K19: R000 RETENCION IMPUESTO A LA RENTA | L19: 0 | M19: 0 | N19: 871.57 | O19: -871.57 | V19: =CONCATENATE(Q19," ",R19)
A20: 4 | B20: =+CONCATENATE($C20,$K20) -> 1045191394A000 SUELDO BASICO | C20: 1045191394 | D20: ALVARO JAVIER ARIAS BAUTISTA | E20: 45191394 | F20: 42989 | G20: 14615 | H20: 20260501 | I20: A000 | J20: SUELDO BASICO | K20: A000 SUELDO BASICO | L20: 240 | M20: 14615 | N20: 0 | O20: 14615
A21: 4 | B21: =+CONCATENATE($C21,$K21) -> 1045191394I100 APORTE OBLIGATORIO AFP | C21: 1045191394 | D21: ALVARO JAVIER ARIAS BAUTISTA | E21: 45191394 | F21: 42989 | G21: 14615 | H21: 20260501 | I21: I100 | J21: APORTE OBLIGATORIO AFP | K21: I100 APORTE OBLIGATORIO AFP | L21: 0 | M21: 0 | N21: 1461.5 | O21: -1461.5
A22: 4 | B22: =+CONCATENATE($C22,$K22) -> 1045191394I200 SOBREVIVENCIA AFP | C22: 1045191394 | D22: ALVARO JAVIER ARIAS BAUTISTA | E22: 45191394 | F22: 42989 | G22: 14615 | H22: 20260501 | I22: I200 | J22: SOBREVIVENCIA AFP | K22: I200 SOBREVIVENCIA AFP | L22: 0 | M22: 0 | N22: 172.61 | O22: -172.61
A23: 4 | B23: =+CONCATENATE($C23,$K23) -> 1045191394R000 RETENCION IMPUESTO A LA RENTA | C23: 1045191394 | D23: ALVARO JAVIER ARIAS BAUTISTA | E23: 45191394 | F23: 42989 | G23: 14615 | H23: 20260501 | I23: R000 | J23: RETENCION IMPUESTO A LA RENTA | K23: R000 RETENCION IMPUESTO A LA RENTA | L23: 0 | M23: 0 | N23: 1972.88 | O23: -1972.88
A24: 5 | B24: =+CONCATENATE($C24,$K24) -> 1046129072A000 SUELDO BASICO | C24: 1046129072 | D24: LAURA CAROLINA LIRA CANDIA | E24: 46129072 | F24: 42765 | G24: 3871 | H24: 20260501 | I24: A000 | J24: SUELDO BASICO | K24: A000 SUELDO BASICO | L24: 184 | M24: 2967.77 | N24: 0 | O24: 2967.77
A25: 5 | B25: =+CONCATENATE($C25,$K25) -> 1046129072D013 AUXILIO DE MOVILIDAD | C25: 1046129072 | D25: LAURA CAROLINA LIRA CANDIA | E25: 46129072 | F25: 42765 | G25: 3871 | H25: 20260501 | I25: D013 | J25: AUXILIO DE MOVILIDAD | K25: D013 AUXILIO DE MOVILIDAD | L25: 0 | M25: 36 | N25: 0 | O25: 36
A26: 5 | B26: =+CONCATENATE($C26,$K26) -> 1046129072G006 VACACIONES | C26: 1046129072 | D26: LAURA CAROLINA LIRA CANDIA | E26: 46129072 | F26: 42765 | G26: 3871 | H26: 20260501 | I26: G006 | J26: VACACIONES | K26: G006 VACACIONES | L26: 56 | M26: 903.23 | N26: 0 | O26: 903.23
A27: 5 | B27: =+CONCATENATE($C27,$K27) -> 1046129072I100 APORTE OBLIGATORIO AFP | C27: 1046129072 | D27: LAURA CAROLINA LIRA CANDIA | E27: 46129072 | F27: 42765 | G27: 3871 | H27: 20260501 | I27: I100 | J27: APORTE OBLIGATORIO AFP | K27: I100 APORTE OBLIGATORIO AFP | L27: 0 | M27: 0 | N27: 387.1 | O27: -387.1
A28: 5 | B28: =+CONCATENATE($C28,$K28) -> 1046129072I200 SOBREVIVENCIA AFP | C28: 1046129072 | D28: LAURA CAROLINA LIRA CANDIA | E28: 46129072 | F28: 42765 | G28: 3871 | H28: 20260501 | I28: I200 | J28: SOBREVIVENCIA AFP | K28: I200 SOBREVIVENCIA AFP | L28: 0 | M28: 0 | N28: 53.03 | O28: -53.03
A29: 5 | B29: =+CONCATENATE($C29,$K29) -> 1046129072R000 RETENCION IMPUESTO A LA RENTA | C29: 1046129072 | D29: LAURA CAROLINA LIRA CANDIA | E29: 46129072 | F29: 42765 | G29: 3871 | H29: 20260501 | I29: R000 | J29: RETENCION IMPUESTO A LA RENTA | K29: R000 RETENCION IMPUESTO A LA RENTA | L29: 0 | M29: 0 | N29: 109.98 | O29: -109.98
A30: 6 | B30: =+CONCATENATE($C30,$K30) -> 1046722547A000 SUELDO BASICO | C30: 1046722547 | D30: FELIX ALEJANDRO KOO RIOJA | E30: 46722547 | F30: 44151 | G30: 5733 | H30: 20260501 | I30: A000 | J30: SUELDO BASICO | K30: A000 SUELDO BASICO | L30: 128 | M30: 3057.6 | N30: 0 | O30: 3057.6
A31: 6 | B31: =+CONCATENATE($C31,$K31) -> 1046722547G006 VACACIONES | C31: 1046722547 | D31: FELIX ALEJANDRO KOO RIOJA | E31: 46722547 | F31: 44151 | G31: 5733 | H31: 20260501 | I31: G006 | J31: VACACIONES | K31: G006 VACACIONES | L31: 112 | M31: 2675.4 | N31: 0 | O31: 2675.4
... A86: 17 | B86: =+CONCATENATE($C86,$K86) -> 76607245G006 VACACIONES | C86: 76607245 | D86: STEFFANY FELICIA CAICEDO ROSADO | E86: 76607245 | F86: 45740 | G86: 1130 | H86: 20260501 | I86: G006 | J86: VACACIONES | K86: G006 VACACIONES | L86: 24 | M86: 113 | N86: 0 | O86: 113

Sheet Detallado
A1: Estructura | B1: LLAVE | C1: EMPLEADO | D1: NOMBRE COMPLETO | E1: DOCTO IDENT | F1: F ANTIGUEDAD | G1: SALARIO | H1: PERIODO/MES | I1: CONCEPTO | J1: DESCRIPCION CONCEPTO | K1: UNION | L1: HORAS | M1: VALOR DEVENGADO | N1: VALOR DEDUCCION | O1: NETO | Q1: DIA | R1: MES | S1: AÑO | T1: FECHA INICIAL | U1: FECHA CORTE | Z1: 46173 | AA1: =TEXT(Z1,"MMMM") -> Mayo | AB1: =UPPER(AA1) -> MAYO
A2: 1 | B2: =+CONCATENATE($C2,$K2) -> 1007874085A000 SUELDO BASICO | C2: 1007874085 | D2: ROCIO DE LOURDES RAMOS CORI | E2: 07874085 | F2: 44348 | G2: 3899 | H2: 20260501 | I2: A000 | J2: SUELDO BASICO | K2: A000 SUELDO BASICO | L2: 240 | M2: 3899 | N2: 0 | O2: 3899 | Q2: =MID(H2,7,"2") -> 01 | R2: =MID(H2,5,2) -> 05 | S2: =MID(H2,1,4) -> 2026 | T2: =CONCATENATE(Q2,"/",R2,"/",S2) -> 01/05/2026 | U2: =$Z$1 -> 46173
A3: 1 | B3: =+CONCATENATE($C3,$K3) -> 1007874085A012 ASIGNACION FAMILIAR | C3: 1007874085 | D3: ROCIO DE LOURDES RAMOS CORI | E3: 07874085 | F3: 44348 | G3: 3899 | H3: 20260501 | I3: A012 | J3: ASIGNACION FAMILIAR | K3: A012 ASIGNACION FAMILIAR | L3: 0 | M3: 113 | N3: 0 | O3: 113 | Q3: =MID(H3,7,"2") -> 01 | R3: =MID(H3,5,2) -> 05 | S3: =MID(H3,1,4) -> 2026 | T3: =CONCATENATE(Q3,"/",R3,"/",S3) -> 01/05/2026 | U3: =$Z$1 -> 46173
A4: 1 | B4: =+CONCATENATE($C4,$K4) -> 1007874085D013 AUXILIO DE MOVILIDAD | C4: 1007874085 | D4: ROCIO DE LOURDES RAMOS CORI | E4: 07874085 | F4: 44348 | G4: 3899 | H4: 20260501 | I4: D013 | J4: AUXILIO DE MOVILIDAD | K4: D013 AUXILIO DE MOVILIDAD | L4: 0 | M4: 36 | N4: 0 | O4: 36 | Q4: =MID(H4,7,"2") -> 01 | R4: =MID(H4,5,2) -> 05 | S4: =MID(H4,1,4) -> 2026 | T4: =CONCATENATE(Q4,"/",R4,"/",S4) -> 01/05/2026 | U4: =$Z$1 -> 46173
A5: 1 | B5: =+CONCATENATE($C5,$K5) -> 1007874085R000 RETENCION IMPUESTO A LA RENTA | C5: 1007874085 | D5: ROCIO DE LOURDES RAMOS CORI | E5: 07874085 | F5: 44348 | G5: 3899 | H5: 20260501 | I5: R000 | J5: RETENCION IMPUESTO A LA RENTA | K5: R000 RETENCION IMPUESTO A LA RENTA | L5: 0 | M5: 0 | N5: 121.57 | O5: -121.57 | Q5: =MID(H5,7,"2") -> 01 | R5: =MID(H5,5,2) -> 05 | S5: =MID(H5,1,4) -> 2026 | T5: =CONCATENATE(Q5,"/",R5,"/",S5) -> 01/05/2026 | U5: =$Z$1 -> 46173
A6: 1 | B6: =+CONCATENATE($C6,$K6) -> 1007874085S006 DESCUENTO EPS | C6: 1007874085 | D6: ROCIO DE LOURDES RAMOS CORI | E6: 07874085 | F6: 44348 | G6: 3899 | H6: 20260501 | I6: S006 | J6: DESCUENTO EPS | K6: S006 DESCUENTO EPS | L6: 0 | M6: 0 | N6: 202.42 | O6: -202.42 | Q6: =MID(H6,7,"2") -> 01 | R6: =MID(H6,5,2) -> 05 | S6: =MID(H6,1,4) -> 2026 | T6: =CONCATENATE(Q6,"/",R6,"/",S6) -> 01/05/2026 | U6: =$Z$1 -> 46173
A7: 2 | B7: =+CONCATENATE($C7,$K7) -> 1040703418A000 SUELDO BASICO | C7: 1040703418 | D7: FIORELLA GIOVANNA CHICHIZOLA CANALE | E7: 40703418 | F7: 42257 | G7: 3700 | H7: 20260501 | I7: A000 | J7: SUELDO BASICO | K7: A000 SUELDO BASICO | L7: 216 | M7: 3330 | N7: 0 | O7: 3330 | Q7: =MID(H7,7,"2") -> 01 | R7: =MID(H7,5,2) -> 05 | S7: =MID(H7,1,4) -> 2026 | T7: =CONCATENATE(Q7,"/",R7,"/",S7) -> 01/05/2026 | U7: =$Z$1 -> 46173
A8: 2 | B8: =+CONCATENATE($C8,$K8) -> 1040703418B100 DESCANSO MEDICO | C8: 1040703418 | D8: FIORELLA GIOVANNA CHICHIZOLA CANALE | E8: 40703418 | F8: 42257 | G8: 3700 | H8: 20260501 | I8: B100 | J8: DESCANSO MEDICO | K8: B100 DESCANSO MEDICO | L8: 24 | M8: 370 | N8: 0 | O8: 370 | Q8: =MID(H8,7,"2") -> 01 | R8: =MID(H8,5,2) -> 05 | S8: =MID(H8,1,4) -> 2026 | T8: =CONCATENATE(Q8,"/",R8,"/",S8) -> 01/05/2026 | U8: =$Z$1 -> 46173
A9: 2 | B9: =+CONCATENATE($C9,$K9) -> 1040703418D013 AUXILIO DE MOVILIDAD | C9: 1040703418 | D9: FIORELLA GIOVANNA CHICHIZOLA CANALE | E9: 40703418 | F9: 42257 | G9: 3700 | H9: 20260501 | I9: D013 | J9: AUXILIO DE MOVILIDAD | K9: D013 AUXILIO DE MOVILIDAD | L9: 0 | M9: 24 | N9: 0 | O9: 24 | Q9: =MID(H9,7,"2") -> 01 | R9: =MID(H9,5,2) -> 05 | S9: =MID(H9,1,4) -> 2026 | T9: =CONCATENATE(Q9,"/",R9,"/",S9) -> 01/05/2026 | U9: =$Z$1 -> 46173
A10: 2 | B10: =+CONCATENATE($C10,$K10) -> 1040703418I100 APORTE OBLIGATORIO AFP | C10: 1040703418 | D10: FIORELLA GIOVANNA CHICHIZOLA CANALE | E10: 40703418 | F10: 42257 | G10: 3700 | H10: 20260501 | I10: I100 | J10: APORTE OBLIGATORIO AFP | K10: I100 APORTE OBLIGATORIO AFP | L10: 0 | M10: 0 | N10: 370 | O10: -370 | Q10: =MID(H10,7,"2") -> 01 | R10: =MID(H10,5,2) -> 05 | S10: =MID(H10,1,4) -> 2026 | T10: =CONCATENATE(Q10,"/",R10,"/",S10) -> 01/05/2026 | U10: =$Z$1 -> 46173
A11: 2 | B11: =+CONCATENATE($C11,$K11) -> 1040703418I200 SOBREVIVENCIA AFP | C11: 1040703418 | D11: FIORELLA GIOVANNA CHICHIZOLA CANALE | E11: 40703418 | F11: 42257 | G11: 3700 | H11: 20260501 | I11: I200 | J11: SOBREVIVENCIA AFP | K11: I200 SOBREVIVENCIA AFP | L11: 0 | M11: 0 | N11: 50.69 | O11: -50.69 | Q11: =MID(H11,7,"2") -> 01 | R11: =MID(H11,5,2) -> 05 | S11: =MID(H11,1,4) -> 2026 | T11: =CONCATENATE(Q11,"/",R11,"/",S11) -> 01/05/2026 | U11: =$Z$1 -> 46173
A12: 2 | B12: =+CONCATENATE($C12,$K12) -> 1040703418I300 COMISION VARIABLE AFP | C12: 1040703418 | D12: FIORELLA GIOVANNA CHICHIZOLA CANALE | E12: 40703418 | F12: 42257 | G12: 3700 | H12: 20260501 | I12: I300 | J12: COMISION VARIABLE AFP | K12: I300 COMISION VARIABLE AFP | L12: 0 | M12: 0 | N12: 57.35 | O12: -57.35 | Q12: =MID(H12,7,"2") -> 01 | R12: =MID(H12,5,2) -> 05 | S12: =MID(H12,1,4) -> 2026 | T12: =CONCATENATE(Q12,"/",R12,"/",S12) -> 01/05/2026 | U12: =$Z$1 -> 46173
A13: 2 | B13: =+CONCATENATE($C13,$K13) -> 1040703418R000 RETENCION IMPUESTO A LA RENTA | C13: 1040703418 | D13: FIORELLA GIOVANNA CHICHIZOLA CANALE | E13: 40703418 | F13: 42257 | G13: 3700 | H13: 20260501 | I13: R000 | J13: RETENCION IMPUESTO A LA RENTA | K13: R000 RETENCION IMPUESTO A LA RENTA | L13: 0 | M13: 0 | N13: 93.85 | O13: -93.85 | Q13: =MID(H13,7,"2") -> 01 | R13: =MID(H13,5,2) -> 05 | S13: =MID(H13,1,4) -> 2026 | T13: =CONCATENATE(Q13,"/",R13,"/",S13) -> 01/05/2026 | U13: =$Z$1 -> 46173
... A86: 17 | B86: =+CONCATENATE($C86,$K86) -> 76607245G006 VACACIONES | C86: 76607245 | D86: STEFFANY FELICIA CAICEDO ROSADO | E86: 76607245 | F86: 45740 | G86: 1130 | H86: 20260501 | I86: G006 | J86: VACACIONES | K86: G006 VACACIONES | L86: 24 | M86: 113 | N86: 0 | O86: 113 | Q86: =MID(H86,7,"2") -> 01 | R86: =MID(H86,5,2) -> 05 | S86: =MID(H86,1,4) -> 2026 | T86: =CONCATENATE(Q86,"/",R86,"/",S86) -> 01/05/2026 | U86: =$Z$1 -> 46173

Sheet Datos
A1: 1 | B1: 2 | C1: 3 | D1: 4 | E1: 5 | F1: 6 | G1: 7 | H1: 8 | I1: 9 | J1: 10 | K1: 11 | L1: 12 | M1: 13 | N1: 14 | O1: 15 | P1: 16 | Q1: 17 | R1: 18 | S1: 19
A2: # | B2: EMPLEADO | C2: NOMBRE COMPLETO | D2: DOCUMENTO IDENTIDAD | E2: OFICIO | F2: DESC. OFICIO | G2: AREA | H2: MARZO | I2: CUSSP | J2: ESSALUD | K2: AFP | L2: FECHA ANTIGUEDAD | M2: SALARIO | N2: APORTE A ESSALUD | O2: CREDITO EPS | P2: DEVENGADOS | Q2: DEDUCCIONES | R2: NETO A PAGAR | S2: #
A3: 1 | B3: 1007874085 | C3: ROCIO DE LOURDES RAMOS CORI | D3: 07874085 | E3: =+VLOOKUP($B3,'BD Total'!$A:$BX,76,0) -> IPS | F3: =+VLOOKUP($B3,'BD Total'!$A:$BY,77,0) -> IP PROSECUTION SPECIALIST | G3: =+VLOOKUP($B3,'BD Total'!$A:$CB,80,0) -> 002 | H3: =+VLOOKUP($B3,'BD Total'!$A:$CC,81,0) -> CENTRAL SERVICES | I3: =+VLOOKUP($B3,'BD Total'!$A:$FA,85,FALSE) -> 260130RRCOI9 | J3: 244.31625 | K3: =IFERROR(VLOOKUP($B3,'BD Total'!$A:$EW,101,0),0) -> INTEGRA | L3: =VLOOKUP($B3,'BD Total'!$A:$K,11,0) -> 44348 | M3: =+VLOOKUP($B3,'BD Total'!$A:$FA,22,FALSE) -> 3899 | N3: =+VLOOKUP($B3,ESSALUD!$B$2:$H$18,6,FALSE) -> 270.81 | O3: =+VLOOKUP($B3,ESSALUD!$B$2:$H$18,7,FALSE) -> 90.27 | P3: =+M3 -> 3899 | Q3: =+N3+O3 -> 361.08 | R3: =+P3-Q3 -> 3537.92 | S3: 1
A4: 2 | B4: 1040703418 | C4: FIORELLA GIOVANNA CHICHIZOLA CANALE | D4: 40703418 | E4: =+VLOOKUP($B4,'BD Total'!$A:$BX,76,0) -> IPS | F4: =+VLOOKUP($B4,'BD Total'!$A:$BY,77,0) -> IP PROSECUTION SPECIALIST | G4: =+VLOOKUP($B4,'BD Total'!$A:$CB,80,0) -> 002 | H4: =+VLOOKUP($B4,'BD Total'!$A:$CC,81,0) -> CENTRAL SERVICES | I4: =+VLOOKUP($B4,'BD Total'!$A:$FA,85,FALSE) -> 595200FCCCA8 | J4: 223.155 | K4: =IFERROR(VLOOKUP($B4,'BD Total'!$A:$EW,101,0),0) -> INTEGRA | L4: =VLOOKUP($B4,'BD Total'!$A:$K,11,0) -> 42257 | M4: =+VLOOKUP($B4,'BD Total'!$A:$FA,22,FALSE) -> 3700 | N4: =+VLOOKUP($B4,ESSALUD!$B$2:$H$18,6,FALSE) -> 249.75 | O4: =+VLOOKUP($B4,ESSALUD!$B$2:$H$18,7,FALSE) -> 83.25 | P4: =+M4 -> 3700 | Q4: =+N4+O4 -> 333 | R4: =+P4-Q4 -> 3367 | S4: 2
A5: 3 | B5: 1044771836 | C5: RONALD FLOREZ SUAREZ | D5: 44771836 | E5: =+VLOOKUP($B5,'BD Total'!$A:$BX,76,0) -> IPS | F5: =+VLOOKUP($B5,'BD Total'!$A:$BY,77,0) -> IP PROSECUTION SPECIALIST | G5: =+VLOOKUP($B5,'BD Total'!$A:$CB,80,0) -> 011 | H5: =+VLOOKUP($B5,'BD Total'!$A:$CC,81,0) -> INVENTIONS | I5: =+VLOOKUP($B5,'BD Total'!$A:$FA,85,FALSE) -> 621441RFSRR2 | J5: 227.4075 | K5: =IFERROR(VLOOKUP($B5,'BD Total'!$A:$EW,101,0),0) -> PROFUTURO | L5: =VLOOKUP($B5,'BD Total'!$A:$K,11,0) -> 42506 | M5: =+VLOOKUP($B5,'BD Total'!$A:$FA,22,FALSE) -> 8842 | N5: =+VLOOKUP($B5,ESSALUD!$B$2:$H$18,6,FALSE) -> 596.835 | O5: =+VLOOKUP($B5,ESSALUD!$B$2:$H$18,7,FALSE) -> 198.945 | P5: =+M5 -> 8842 | Q5: =+N5+O5 -> 795.78 | R5: =+P5-Q5 -> 8046.22 | S5: 3
A6: 4 | B6: 1045191394 | C6: ALVARO JAVIER ARIAS BAUTISTA | D6: 45191394 | E6: =+VLOOKUP($B6,'BD Total'!$A:$BX,76,0) -> CMD | F6: =+VLOOKUP($B6,'BD Total'!$A:$BY,77,0) -> COUNTRY MANAGING DIRECTOR | G6: =+VLOOKUP($B6,'BD Total'!$A:$CB,80,0) -> 007 | H6: =+VLOOKUP($B6,'BD Total'!$A:$CC,81,0) -> CEO | I6: =+VLOOKUP($B6,'BD Total'!$A:$FA,85,FALSE) -> 322431AABAT4 | J6: 877.5 | K6: =IFERROR(VLOOKUP($B6,'BD Total'!$A:$EW,101,0),0) -> PROFUTURO | L6: =VLOOKUP($B6,'BD Total'!$A:$K,11,0) -> 42989 | M6: =+VLOOKUP($B6,'BD Total'!$A:$FA,22,FALSE) -> 14615 | N6: =+VLOOKUP($B6,ESSALUD!$B$2:$H$18,6,FALSE) -> 986.5125 | O6: =+VLOOKUP($B6,ESSALUD!$B$2:$H$18,7,FALSE) -> 328.8375 | P6: =+M6 -> 14615 | Q6: =+N6+O6 -> 1315.35 | R6: =+P6-Q6 -> 13299.65 | S6: 4
A7: 5 | B7: 1046129072 | C7: LAURA CAROLINA LIRA CANDIA | D7: 46129072 | E7: =+VLOOKUP($B7,'BD Total'!$A:$BX,76,0) -> IPS | F7: =+VLOOKUP($B7,'BD Total'!$A:$BY,77,0) -> IP PROSECUTION SPECIALIST | G7: =+VLOOKUP($B7,'BD Total'!$A:$CB,80,0) -> 002 | H7: =+VLOOKUP($B7,'BD Total'!$A:$CC,81,0) -> CENTRAL SERVICES | I7: =+VLOOKUP($B7,'BD Total'!$A:$FA,85,FALSE) -> 628890LLCAD9 | J7: 232.2675 | K7: =IFERROR(VLOOKUP($B7,'BD Total'!$A:$EW,101,0),0) -> HABITAT | L7: =VLOOKUP($B7,'BD Total'!$A:$K,11,0) -> 42765 | M7: =+VLOOKUP($B7,'BD Total'!$A:$FA,22,FALSE) -> 3871 | N7: =+VLOOKUP($B7,ESSALUD!$B$2:$H$18,6,FALSE) -> 261.2925 | O7: =+VLOOKUP($B7,ESSALUD!$B$2:$H$18,7,FALSE) -> 87.0975 | P7: =+M7 -> 3871 | Q7: =+N7+O7 -> 348.39 | R7: =+P7-Q7 -> 3522.61 | S7: 5
A8: 6 | B8: 1046722547 | C8: FELIX ALEJANDRO KOO RIOJA | D8: 46722547 | E8: =+VLOOKUP($B8,'BD Total'!$A:$BX,76,0) -> FAS | F8: =+VLOOKUP($B8,'BD Total'!$A:$BY,77,0) -> FINANCE & ACCOUNTING SPECIALIST | G8: =+VLOOKUP($B8,'BD Total'!$A:$CB,80,0) -> 005 | H8: =+VLOOKUP($B8,'BD Total'!$A:$CC,81,0) -> FINANZAS | I8: =+VLOOKUP($B8,'BD Total'!$A:$FA,85,FALSE) -> 632311FKROJ0 | J8: 287.8875 | K8: =IFERROR(VLOOKUP($B8,'BD Total'!$A:$EW,101,0),0) -> INTEGRA | L8: =VLOOKUP($B8,'BD Total'!$A:$K,11,0) -> 44151 | M8: =+VLOOKUP($B8,'BD Total'!$A:$FA,22,FALSE) -> 5733 | N8: =+VLOOKUP($B8,ESSALUD!$B$2:$H$18,6,FALSE) -> 386.9775 | O8: =+VLOOKUP($B8,ESSALUD!$B$2:$H$18,7,FALSE) -> 128.9925 | P8: =+M8 -> 5733 | Q8: =+N8+O8 -> 515.97 | R8: =+P8-Q8 -> 5217.03 | S8: 6
A9: 7 | B9: 1047924040 | C9: MARÍA DEL CARMEN NEYRA ELLIOT | D9: 47924040 | E9: =+VLOOKUP($B9,'BD Total'!$A:$BX,76,0) -> QPM | F9: =+VLOOKUP($B9,'BD Total'!$A:$BY,77,0) -> QUALITY PROCESS MANAGER | G9: =+VLOOKUP($B9,'BD Total'!$A:$CB,80,0) -> 010 | H9: =+VLOOKUP($B9,'BD Total'!$A:$CC,81,0) -> OPERATIONS | I9: =+VLOOKUP($B9,'BD Total'!$A:$FA,85,FALSE) -> 641640MNERI3 | J9: 385.695 | K9: =IFERROR(VLOOKUP($B9,'BD Total'!$A:$EW,101,0),0) -> HABITAT | L9: =VLOOKUP($B9,'BD Total'!$A:$K,11,0) -> 42632 | M9: =+VLOOKUP($B9,'BD Total'!$A:$FA,22,FALSE) -> 6552 | N9: =+VLOOKUP($B9,ESSALUD!$B$2:$H$18,6,FALSE) -> 442.26 | O9: =+VLOOKUP($B9,ESSALUD!$B$2:$H$18,7,FALSE) -> 147.42 | P9: =+M9 -> 6552 | Q9: =+N9+O9 -> 589.68 | R9: =+P9-Q9 -> 5962.32 | S9: 7
A10: 8 | B10: 1070165336 | C10: VICTOR DANIEL FERNANDEZ CASTILLO | D10: 70165336 | E10: =+VLOOKUP($B10,'BD Total'!$A:$BX,76,0) -> PSP | F10: =+VLOOKUP($B10,'BD Total'!$A:$BY,77,0) -> PATENT SPECIALIST | G10: =+VLOOKUP($B10,'BD Total'!$A:$CB,80,0) -> 011 | H10: =+VLOOKUP($B10,'BD Total'!$A:$CC,81,0) -> INVENTIONS | I10: =+VLOOKUP($B10,'BD Total'!$A:$FA,85,FALSE) -> 640621VFCNT9 | J10: 251.9775 | K10: =IFERROR(VLOOKUP($B10,'BD Total'!$A:$EW,101,0),0) -> HABITAT | L10: =VLOOKUP($B10,'BD Total'!$A:$K,11,0) -> 44623 | M10: =+VLOOKUP($B10,'BD Total'!$A:$FA,22,FALSE) -> 4099 | N10: =+VLOOKUP($B10,ESSALUD!$B$2:$H$18,6,FALSE) -> 276.6825 | O10: =+VLOOKUP($B10,ESSALUD!$B$2:$H$18,7,FALSE) -> 92.2275 | P10: =+M10 -> 4099 | Q10: =+N10+O10 -> 368.91 | R10: =+P10-Q10 -> 3730.09 | S10: 8
A11: 9 | B11: 1070680748 | C11: LIZ VALERIA SOLANO CARRILLO | D11: 70680748 | E11: =+VLOOKUP($B11,'BD Total'!$A:$BX,76,0) -> P019 | F11: =+VLOOKUP($B11,'BD Total'!$A:$BY,77,0) -> IP SPECIALIST | G11: =+VLOOKUP($B11,'BD Total'!$A:$CB,80,0) -> 003 | H11: =+VLOOKUP($B11,'BD Total'!$A:$CC,81,0) -> TRADEMARKS | I11: =+VLOOKUP($B11,'BD Total'!$A:$FA,85,FALSE) -> 0 | J11: 371.25 | K11: =IFERROR(VLOOKUP($B11,'BD Total'!$A:$EW,101,0),0) -> ONP | L11: =VLOOKUP($B11,'BD Total'!$A:$K,11,0) -> 44879 | M11: =+VLOOKUP($B11,'BD Total'!$A:$FA,22,FALSE) -> 6125 | N11: =+VLOOKUP($B11,ESSALUD!$B$2:$H$18,6,FALSE) -> 421.065 | O11: =+VLOOKUP($B11,ESSALUD!$B$2:$H$18,7,FALSE) -> 140.355 | P11: =+M11 -> 6125 | Q11: =+N11+O11 -> 561.42 | R11: =+P11-Q11 -> 5563.58 | S11: 9
A12: 10 | B12: 1072251509 | C12: CYNTHIA FIORELLA HUAMAN TORRES | D12: 72251509 | E12: =+VLOOKUP($B12,'BD Total'!$A:$BX,76,0) -> PSP | F12: =+VLOOKUP($B12,'BD Total'!$A:$BY,77,0) -> PATENT SPECIALIST | G12: =+VLOOKUP($B12,'BD Total'!$A:$CB,80,0) -> 011 | H12: =+VLOOKUP($B12,'BD Total'!$A:$CC,81,0) -> INVENTIONS | I12: =+VLOOKUP($B12,'BD Total'!$A:$FA,85,FALSE) -> 631390CHTMR2 | J12: 378.045 | K12: =IFERROR(VLOOKUP($B12,'BD Total'!$A:$EW,101,0),0) -> HABITAT | L12: =VLOOKUP($B12,'BD Total'!$A:$K,11,0) -> 43241 | M12: =+VLOOKUP($B12,'BD Total'!$A:$FA,22,FALSE) -> 4631 | N12: =+VLOOKUP($B12,ESSALUD!$B$2:$H$18,6,FALSE) -> 426.96 | O12: =+VLOOKUP($B12,ESSALUD!$B$2:$H$18,7,FALSE) -> 0 | P12: =+M12 -> 4631 | Q12: =+N12+O12 -> 426.96 | R12: =+P12-Q12 -> 4204.04 | S12: 10
A13: 11 | B13: 1077485287 | C13: ZULEMA BELINDA CADILLO BRITO | D13: 77485287 | E13: =+VLOOKUP($B13,'BD Total'!$A:$BX,76,0) -> IPS | F13: =+VLOOKUP($B13,'BD Total'!$A:$BY,77,0) -> IP PROSECUTION SPECIALIST | G13: =+VLOOKUP($B13,'BD Total'!$A:$CB,80,0) -> 002 | H13: =+VLOOKUP($B13,'BD Total'!$A:$CC,81,0) -> CENTRAL SERVICES | I13: =+VLOOKUP($B13,'BD Total'!$A:$FA,85,FALSE) -> 655610ZCBIT4 | J13: 364.87125 | K13: =IFERROR(VLOOKUP($B13,'BD Total'!$A:$EW,101,0),0) -> PRIMA | L13: =VLOOKUP($B13,'BD Total'!$A:$K,11,0) -> 45323 | M13: =+VLOOKUP($B13,'BD Total'!$A:$FA,22,FALSE) -> 2142 | N13: =+VLOOKUP($B13,ESSALUD!$B$2:$H$18,6,FALSE) -> 144.585 | O13: =+VLOOKUP($B13,ESSALUD!$B$2:$H$18,7,FALSE) -> 48.195 | P13: =+M13 -> 2142 | Q13: =+N13+O13 -> 192.78 | R13: =+P13-Q13 -> 1949.22 | S13: 11
A14: 12 | B14: 2001252358 | C14: JOSE NORBERT MARQUIS XXX | D14: 001252358 | E14: =+VLOOKUP($B14,'BD Total'!$A:$BX,76,0) -> P019 | F14: =+VLOOKUP($B14,'BD Total'!$A:$BY,77,0) -> IP SPECIALIST | G14: =+VLOOKUP($B14,'BD Total'!$A:$CB,80,0) -> 011 | H14: =+VLOOKUP($B14,'BD Total'!$A:$CC,81,0) -> INVENTIONS | I14: =+VLOOKUP($B14,'BD Total'!$A:$FA,85,FALSE) -> 627991JMXQX0 | J14: 0 | K14: =IFERROR(VLOOKUP($B14,'BD Total'!$A:$EW,101,0),0) -> HABITAT | L14: =VLOOKUP($B14,'BD Total'!$A:$K,11,0) -> 42438 | M14: =+VLOOKUP($B14,'BD Total'!$A:$FA,22,FALSE) -> 6644 | N14: =+VLOOKUP($B14,ESSALUD!$B$2:$H$18,6,FALSE) -> 448.47 | O14: =+VLOOKUP($B14,ESSALUD!$B$2:$H$18,7,FALSE) -> 149.49 | P14: =+M14 -> 6644 | Q14: =+N14+O14 -> 597.96 | R14: =+P14-Q14 -> 6046.04 | S14: 12
... A16: 14 | B16: 42683912 | C16: GUILLERMO HENRY HIRAOKA MARINA | D16: 72836862 | E16: =+VLOOKUP($B16,'BD Total'!$A:$BX,76,0) -> P019 | F16: =+VLOOKUP($B16,'BD Total'!$A:$BY,77,0) -> IP SPECIALIST | G16: =+VLOOKUP($B16,'BD Total'!$A:$CB,80,0) -> 003 | H16: =+VLOOKUP($B16,'BD Total'!$A:$CC,81,0) -> TRADEMARKS | I16: =+VLOOKUP($B16,'BD Total'!$A:$FA,85,FALSE) -> 309631GHMAI4 | J16: 168.75 | K16: =IFERROR(VLOOKUP($B16,'BD Total'!$A:$EW,101,0),0) -> HABITAT | L16: =VLOOKUP($B16,'BD Total'!$A:$K,11,0) -> 45637 | M16: =+VLOOKUP($B16,'BD Total'!$A:$FA,22,FALSE) -> 5768 | N16: =+VLOOKUP($B16,ESSALUD!$B$2:$H$18,6,FALSE) -> 389.34 | O16: =+VLOOKUP($B16,ESSALUD!$B$2:$H$18,7,FALSE) -> 129.78 | P16: =+M16 -> 5768 | Q16: =+N16+O16 -> 519.12 | R16: =+P16-Q16 -> 5248.88 | S16: 14
A17: 15 | B17: 72836862 | C17: JACKELINE NANCY MEJIA DOLORES | D17: 75203640 | E17: =+VLOOKUP($B17,'BD Total'!$A:$BX,76,0) -> IPP | F17: =+VLOOKUP($B17,'BD Total'!$A:$BY,77,0) -> IP PROCUREMENT SPECIALIST | G17: =+VLOOKUP($B17,'BD Total'!$A:$CB,80,0) -> 003 | H17: =+VLOOKUP($B17,'BD Total'!$A:$CC,81,0) -> TRADEMARKS | I17: =+VLOOKUP($B17,'BD Total'!$A:$FA,85,FALSE) -> 663680JMDIO1 | K17: =IFERROR(VLOOKUP($B17,'BD Total'!$A:$EW,101,0),0) -> INTEGRA | L17: =VLOOKUP($B17,'BD Total'!$A:$K,11,0) -> 45208 | M17: =+VLOOKUP($B17,'BD Total'!$A:$FA,22,FALSE) -> 2652 | N17: =+VLOOKUP($B17,ESSALUD!$B$2:$H$18,6,FALSE) -> 179.01 | O17: =+VLOOKUP($B17,ESSALUD!$B$2:$H$18,7,FALSE) -> 59.67 | P17: =+M17 -> 2652 | Q17: =+N17+O17 -> 238.68 | R17: =+P17-Q17 -> 2413.32 | S17: 15
A18: 16 | B18: 76607245 | C18: STEFFANY FELICIA CAICEDO ROSADO | K18: =IFERROR(VLOOKUP($B18,'BD Total'!$A:$EW,101,0),0) | L18: =VLOOKUP($B18,'BD Total'!$A:$K,11,0) -> 45740 | M18: =+VLOOKUP($B18,'BD Total'!$A:$FA,22,FALSE) -> 1130 | N18: =+VLOOKUP($B18,ESSALUD!$B$2:$H$18,6,FALSE) -> 0 | O18: =+VLOOKUP($B18,ESSALUD!$B$2:$H$18,7,FALSE) -> 0 | P18: =+M18 -> 1130 | Q18: =+N18+O18 -> 0 | R18: =+P18-Q18 -> 1130 | S18: 16
A19: 17 | B19: 74026184 | C19: JACKELINE TAMARA FAJARDO APOLAYA | K19: =IFERROR(VLOOKUP($B19,'BD Total'!$A:$EW,101,0),0) | L19: =VLOOKUP($B19,'BD Total'!$A:$K,11,0) -> 46153 | M19: =+VLOOKUP($B19,'BD Total'!$A:$FA,22,FALSE) -> 1130 | N19: =+VLOOKUP($B19,ESSALUD!$B$2:$H$18,6,FALSE) -> 0 | O19: =+VLOOKUP($B19,ESSALUD!$B$2:$H$18,7,FALSE) -> 0 | P19: =+M19 -> 1130 | Q19: =+N19+O19 -> 0 | R19: =+P19-Q19 -> 1130 | S19: 17
N20: =SUM(N3:N19) -> 5689.125 | O20: =SUM(O3:O19) -> 1754.055

Sheet ESSALUD
A1: Id | B1: CUC | C1: TipoDocumento | D1: NumeroDocumento | E1: Trabajador | F1: CREDITO EPS | G1: APORTE A ESSALUD | H1: CREDITO EPS | I1: TOTAL APORTES EMPLEADOR
A2: 1 | B2: 1007874085 | C2: DNI | D2: 07874085 | E2: ROCIO DE LOURDES RAMOS CORI | F2: SI | G2: 270.81 | H2: 90.27 | I2: =+G2+H2 -> 361.08
A3: 2 | B3: 1040703418 | C3: DNI | D3: 40703418 | E3: FIORELLA GIOVANNA CHICHIZOLA CANALE | F3: SI | G3: 249.75 | H3: 83.25 | I3: =+G3+H3 -> 333
A4: 3 | B4: 1044771836 | C4: DNI | D4: 44771836 | E4: RONALD FLOREZ SUAREZ | F4: SI | G4: 596.835 | H4: 198.945 | I4: =+G4+H4 -> 795.78
A5: 4 | B5: 1045191394 | C5: DNI | D5: 45191394 | E5: ALVARO JAVIER ARIAS BAUTISTA | F5: SI | G5: 986.5125 | H5: 328.8375 | I5: =+G5+H5 -> 1315.35
A6: 5 | B6: 1046129072 | C6: DNI | D6: 46129072 | E6: LAURA CAROLINA LIRA CANDIA | F6: SI | G6: 261.2925 | H6: 87.0975 | I6: =+G6+H6 -> 348.39
A7: 6 | B7: 1046722547 | C7: DNI | D7: 46722547 | E7: FELIX ALEJANDRO KOO RIOJA | F7: SI | G7: 386.9775 | H7: 128.9925 | I7: =+G7+H7 -> 515.97
A8: 7 | B8: 1047924040 | C8: DNI | D8: 47924040 | E8: MARÍA DEL CARMEN NEYRA ELLIOT | F8: SI | G8: 442.26 | H8: 147.42 | I8: =+G8+H8 -> 589.68
A9: 8 | B9: 1070165336 | C9: DNI | D9: 70165336 | E9: VICTOR DANIEL FERNANDEZ CASTILLO | F9: SI | G9: 276.6825 | H9: 92.2275 | I9: =+G9+H9 -> 368.91
A10: 9 | B10: 1070680748 | C10: DNI | D10: 70680748 | E10: LIZ VALERIA SOLANO CARRILLO | F10: SI | G10: 421.065 | H10: 140.355 | I10: =+G10+H10 -> 561.42
A11: 10 | B11: 1072251509 | C11: DNI | D11: 72251509 | E11: CYNTHIA FIORELLA HUAMAN TORRES | F11: NO | G11: 426.96 | H11: 0 | I11: =+G11+H11 -> 426.96
A12: 11 | B12: 1077485287 | C12: DNI | D12: 77485287 | E12: ZULEMA BELINDA CADILLO BRITO | F12: SI | G12: 144.585 | H12: 48.195 | I12: =+G12+H12 -> 192.78
A13: 12 | B13: 2001252358 | C13: CARNET EXTRANJERÍA | D13: 001252358 | E13: JOSE NORBERT MARQUIS XXX | F13: SI | G13: 448.47 | H13: 149.49 | I13: =+G13+H13 -> 597.96
... A18: 17 | B18: 74026184 | C18: DNI | D18: 74026184 | E18: JACKELINE TAMARA FAJARDO APOLAYA | F18: SI | G18: 0 | H18: 0 | I18: =+G18+H18 -> 0
G19: =SUM(G2:G18) -> 5689.125 | H19: =SUM(H2:H18) -> 1754.055 | I19: =SUM(I2:I18) -> 7443.18

Sheet BD Total
A1: EMPLEADO | B1: DOCTO IDENT | C1: CLASE DOCTO | D1: NOM CLASE DOCTO | E1: APELLIDO | F1: NOMBRE | G1: TP CONTR | H1: CONTRATO | I1: F VCMT CONTR | J1: F INGRESO | K1: F ANTIGUEDAD | L1: TIPO COTIZANTE | M1: REL LABORAL | N1: NOM REL LABORAL | O1: CLASE EMP | P1: NOM CLASE EMP | Q1: TURNO | R1: NOM TURNO | S1: HORARIO | T1: NOM HORARIO | U1: F ULT SALAR | V1: SALARIO | W1: JORNADA | X1: NOM JORNADA | Y1: PROCEDIMTO | Z1: PORC RFTE | AA1: VAR TRA 01 | AB1: VAR TRA 02 | AC1: VAR TRA 03 | AD1: VAR TRA 04 | AE1: VAR TRA 05 | AF1: VAR TRA 06 | AG1: VAR TRA 07 | AH1: VAR TRA 08 | AI1: VAR TRA 09 | AJ1: VAR TRA 10 | AK1: EMPLEADO JEFE | AL1: DOCTO IDENT JEFE | AM1: NOMBRE JEFE | AN1: APELLIDO JEFE | AO1: SEXO | AP1: ESTADOCIVIL | AQ1: F NACE | AR1: GRUPO RH | AS1: NRO HIJOS | AT1: CIUDAD N | AU1: CIUDAD NACE | AV1: DIRECCION | AW1: TELEFONO | AX1: CELULAR | AY1: TELE OFC | AZ1: EXTENSION | BA1: E MAIL | BB1: E MAIL2 | BC1: CLASE VAC | BD1: DESCRIPCIONCLASEVAC | BE1: BANCO | BF1: NOM BANCO | BG1: SUCURSAL BCO | BH1: NOM SUCURSAL BCO | BI1: CTA BCO | BJ1: TIPO CTA | BK1: NOM TIPO CTA | BL1: F RETIRO | BM1: REL SINDICAL | BN1: NOM REL SINDICAL | BO1: DIVISION | BP1: NOM DIVISION | BQ1: TIPO NOM | BR1: CLASE NOM | BS1: NOMINA | BT1: SUBDIVISION | BU1: NOM SUBDIVISION | BV1: NIVEL | BW1: NOM NIVEL | BX1: OFICIO | BY1: NOM OFICIO | BZ1: CCOSTO | CA1: NOM CCOSTO | CB1: AREA | CC1: NOM AREA | CD1: DPTO | CE1: NOM DPTO | CF1: GRUPO | CG1: NOM GRUPO | CH1: SECCION | CI1: NOM SECCION | CJ1: PROYECTO | CK1: NOM PROYECTO | CL1: PRODUCTO | CM1: NOM PRODUCTO | CN1: SUC CIA | CO1: NOM SUC CIA | CP1: SUCURSAL | CQ1: NOM SUCURSAL | CR1: COD ARP | CS1: ARP | CT1: COD EPS | CU1: EPS | CV1: COD AFP | CW1: AFP | CX1: FONDO | CY1: FCESANTIAS | CZ1: USUARIO | DA1: CDG CCF | DB1: DSC CCF | DC1: UBICACION | DD1: NOM UBICACION | DE1: SUBGRUPO | DF1: NOM SUBGRUPO | DG1: ANEXO | DH1: ESTADO | DI1: FCH MDF | DJ1: DEPENDING1 | DK1: DEPENDING2 | DL1: MOT RETIRO | DM1: MOTIVO | DN1: F ULT CONTRATO EMPZ | DO1: CIUDAD RESID | DP1: NOM CIUDAD RESID | DQ1: IND P LIQ | DR1: FORMAPAGO | DS1: NOM FORMAPAGO | DT1: CATEGORIA | DU1: CIUDAD TRABAJA | DV1: NOM CIUDAD TRABAJA | DW1: CIUDAD EXP | DX1: COD CIUD EXP DOCUMENTO | DY1: DPTO EXP | DZ1: SALARIO MENSUAl | EA1: SALARIO HORA | EB1: CNSEMPB | EC1: DES TIPO SAL | ED1: TIPO SAL | EE1: SALARIOFLEX | EF1: SALARIOREAL | EG1: TOTDIASPEND VAC | EH1: IDPROFESION | EI1: PROFESION | EJ1: NIVEL EDU | EK1: NOM NIVEL EDU | EL1: DIR OFC | EM1: P CARGO | EN1: FACTORRIESGOARL | EO1: TIPOCUENTA | EP1: PROPIEDADCUENTA | EQ1: NOMBREEMPRESA | ER1: CODBANCOEMPRESA | ES1: NOM BANCOEMPRESA | ET1: CUENTABANCOEMPRESA | EU1: TIPOCUENTAEMPRESA | EV1: ACTIVIDAD | EW1: PAIS NACIMIENTO | EX1: BARRIO | EY1: NOM BARRIO | EZ1: CDGCIA | FA1: N HRS P
A2: 1007874085 | B2: 07874085 | C2: D | D2: LIBRETA ELECTORAL O DNI | E2: RAMOS CORI | F2: ROCIO DE LOURDES | G2: PI | H2: PLAZO INDETERMINADO | J2: 44348 | K2: 44348 | L2: DP2 | M2: L5 | N2: SUELDO FIJO | O2: EMP | P2: EMPLEADO | Q2: TD | R2: TURNO DIURNO | S2: HD | T2: HORARIO DIURNO | U2: 46023 | V2: 3899 | W2: C | X2: Completa | Y2: 1 | Z2: 0 | AA2: 0 | AB2: 0 | AC2: 0 | AD2: 0 | AE2: 0 | AF2: 0 | AG2: 0 | AH2: 0 | AI2: 0 | AJ2: 0 | AO2: F | AP2: Casado(a) | AQ2: 26015 | AR2: SND | AS2: 0 | AT2: PO001 | AU2: LIMA | AV2: OTROS - 0 | AW2: 1111111 | BC2: 01 | BD2: LUNES-VIERNES | BE2: 11 | BF2: BBVA PERU | BG2: 11 | BH2: BBVA PERU | BI2: 01136800020054566686 | BJ2: A | BK2: Ahorro | BM2: NO | BN2: SIN RELACION SINDICAL | BO2: CM&CO | BP2: CLARKE, MODET & CO. PERU S.A.C. | BQ2: ME | BR2: 01 | BS2: CLARKE, MODET Y CO. PERÚ SAC | BT2: PONP | BU2: PENSION ONP | BV2: UNCO | BW2: UNIVERSIDAD COMPLETA | BX2: IPS | BY2: IP PROSECUTION SPECIALIST | BZ2: 029 | CA2: CENTRAL SERVICES | CB2: 002 | CC2: CENTRAL SERVICES | CD2: CM&CO | CE2: CLARKE, MODET & CO. PERU S.A.C. | CF2: 1007874085 | CG2: 260130RRCOI9 | CH2: LINEA | CI2: LINEA | CJ2: 1007874085 | CK2: 7103230ROCIR001 | CP2: 100 | CQ2: SAN ISIDRO | CR2: ST | CS2: SCTR | CT2: ES | CU2: ESSALUD | CV2: IN | CW2: INTEGRA | CX2: ND | CY2: NO DEFINIDO | CZ2: NATHALIE | DA2: PE | DB2: PERUANO | DC2: 100 | DD2: SAN ISIDRO | DE2: OPE | DF2: OPERATIONS | DH2: Activo | DI2: 46100 | DO2: PO001 | DP2: LIMA | DQ2: 1 | DR2: TN | DS2: TRANSFERENCIA | DU2: PO001 | DV2: LIMA | DW2: LIMA | DX2: PO001 | DY2: LIMA | DZ2: 3899 | EA2: 16.245833 | EC2: Normal | ED2: N | EE2: 0 | EF2: 3899 | EG2: 14 | EH2: 0 | EM2: 0 | EN2: 0.522% | EO2: Ahorros | EP2: Propia | EQ2: CLARKE, MODET Y CO. PERÚ SAC | ER2: 01 | ES2: BANCO CENTRAL RESERVA DEL PERÚ | ET2: 0123456789 | EU2: S | EW2: PERU | FA2: 0 | FL2: 0 | FN2: 44348 | FO2: 20210601
A3: 1040703418 | B3: 40703418 | C3: D | D3: LIBRETA ELECTORAL O DNI | E3: CHICHIZOLA CANALE | F3: FIORELLA GIOVANNA | G3: PI | H3: PLAZO INDETERMINADO | J3: 42257 | K3: 42257 | L3: DP1 | M3: L5 | N3: SUELDO FIJO | O3: EMP | P3: EMPLEADO | Q3: TD | R3: TURNO DIURNO | S3: HD | T3: HORARIO DIURNO | U3: 46023 | V3: 3700 | W3: C | X3: Completa | Y3: 1 | Z3: 0 | AA3: 0 | AB3: 0 | AC3: 0 | AD3: 0 | AE3: 0 | AF3: 0 | AG3: 0 | AH3: 0 | AI3: 0 | AJ3: 0 | AO3: F | AP3: Soltero(a) | AQ3: 29522 | AR3: SND | AS3: 0 | AT3: PO001 | AU3: LIMA | AV3: ZONA INDUSTRIAL CALLE LOS LIBERTADORES 758 | AW3: 6000000 | AX3: 941377416 | BC3: 01 | BD3: LUNES-VIERNES | BE3: 11 | BF3: BBVA PERU | BG3: 11 | BH3: BBVA PERU | BI3: 01115600020044890077 | BJ3: A | BK3: Ahorro | BM3: NO | BN3: SIN RELACION SINDICAL | BO3: CM&CO | BP3: CLARKE, MODET & CO. PERU S.A.C. | BQ3: ME | BR3: 01 | BS3: CLARKE, MODET Y CO. PERÚ SAC | BT3: CFIN | BU3: COMISION FLUJO INTEGRA | BV3: ISCO | BW3: INSTITUTO SUPERIOR,ETC COMPLETA | BX3: IPS | BY3: IP PROSECUTION SPECIALIST | BZ3: 029 | CA3: CENTRAL SERVICES | CB3: 002 | CC3: CENTRAL SERVICES | CD3: CM&CO | CE3: CLARKE, MODET & CO. PERU S.A.C. | CF3: 1040703418 | CG3: 595200FCCCA8 | CH3: LINEA | CI3: LINEA | CJ3: 1040703418 | CK3: 8010280CCCAF009 | CP3: 100 | CQ3: SAN ISIDRO | CR3: ST | CS3: SCTR | CT3: ES | CU3: ESSALUD | CV3: IN | CW3: INTEGRA | CX3: ND | CY3: NO DEFINIDO | CZ3: NATHALIE | DA3: PE | DB3: PERUANO | DC3: 100 | DD3: SAN ISIDRO | DE3: OPE | DF3: OPERATIONS | DH3: Activo | DI3: 46100 | DO3: PO001 | DP3: LIMA | DQ3: 1 | DR3: TN | DS3: TRANSFERENCIA | DU3: PO001 | DV3: LIMA | DW3: LIMA | DX3: PO001 | DY3: LIMA | DZ3: 3700 | EA3: 15.416667 | EC3: Normal | ED3: N | EE3: 0 | EF3: 3700 | EG3: 14 | EH3: 0 | EM3: 0 | EN3: 0.522% | EO3: Ahorros | EP3: Propia | EQ3: CLARKE, MODET Y CO. PERÚ SAC | ER3: 01 | ES3: BANCO CENTRAL RESERVA DEL PERÚ | ET3: 0123456789 | EU3: S | EW3: PERU | FA3: 0 | FL3: 0 | FN3: 42257 | FO3: 20150910
A4: 1044771836 | B4: 44771836 | C4: D | D4: LIBRETA ELECTORAL O DNI | E4: FLOREZ SUAREZ | F4: RONALD | G4: PI | H4: PLAZO INDETERMINADO | J4: 42506 | K4: 42506 | L4: DP1 | M4: L5 | N4: SUELDO FIJO | O4: EMP | P4: EMPLEADO | Q4: TD | R4: TURNO DIURNO | S4: HD | T4: HORARIO DIURNO | U4: 46023 | V4: 8842 | W4: C | X4: Completa | Y4: 1 | Z4: 0 | AA4: 0 | AB4: 0 | AC4: 0 | AD4: 0 | AE4: 0 | AF4: 0 | AG4: 0 | AH4: 0 | AI4: 0 | AJ4: 0 | AO4: M | AP4: Soltero(a) | AQ4: 32146 | AR4: SND | AS4: 0 | AT4: PO001 | AU4: LIMA | AV4: ZONA INDUSTRIAL JIRÓN MANUEL PEREZ DE TUDELA 2847 | AW4: 6000000 | AX4: 982770079 | BC4: 01 | BD4: LUNES-VIERNES | BE4: 11 | BF4: BBVA PERU | BG4: 11 | BH4: BBVA PERU | BI4: 01105700022436134471 | BJ4: A | BK4: Ahorro | BM4: NO | BN4: SIN RELACION SINDICAL | BO4: CM&CO | BP4: CLARKE, MODET & CO. PERU S.A.C. | BQ4: ME | BR4: 01 | BS4: CLARKE, MODET Y CO. PERÚ SAC | BT4: CFPRO | BU4: COMISION FLUJO PROFUTURO | BV4: ISCO | BW4: INSTITUTO SUPERIOR,ETC COMPLETA | BX4: IPS | BY4: IP PROSECUTION SPECIALIST | BZ4: 028 | CA4: OPERATIONS INVENTIONS | CB4: 011 | CC4: INVENTIONS | CD4: CM&CO | CE4: CLARKE, MODET & CO. PERU S.A.C. | CF4: 1044771836 | CG4: 621441RFSRR2 | CH4: LINEA | CI4: LINEA | CJ4: 1044771836 | CK4: 8801041FRSRR003 | CP4: 100 | CQ4: SAN ISIDRO | CR4: ST | CS4: SCTR | CT4: ES | CU4: ESSALUD | CV4: PT | CW4: PROFUTURO | CX4: ND | CY4: NO DEFINIDO | CZ4: NATHALIE | DA4: PE | DB4: PERUANO | DC4: 100 | DD4: SAN ISIDRO | DE4: OPE | DF4: OPERATIONS | DH4: Activo | DI4: 46100 | DO4: PO001 | DP4: LIMA | DQ4: 1 | DR4: TN | DS4: TRANSFERENCIA | DU4: PO001 | DV4: LIMA | DW4: LIMA | DX4: PO001 | DY4: LIMA | DZ4: 8842 | EA4: 33.966667 | EC4: Normal | ED4: N | EE4: 0 | EF4: 8842 | EG4: 35 | EH4: 0 | EM4: 0 | EN4: 0.522% | EO4: Ahorros | EP4: Propia | EQ4: CLARKE, MODET Y CO. PERÚ SAC | ER4: 01 | ES4: BANCO CENTRAL RESERVA DEL PERÚ | ET4: 0123456789 | EU4: S | EW4: PERU | FA4: 0 | FL4: 0 | FN4: 42506 | FO4: 20160516
A5: 1045191394 | B5: 45191394 | C5: D | D5: LIBRETA ELECTORAL O DNI | E5: ARIAS BAUTISTA | F5: ALVARO JAVIER | G5: PI | H5: PLAZO INDETERMINADO | J5: 42989 | K5: 42989 | L5: DP1 | M5: L5 | N5: SUELDO FIJO | O5: EMP | P5: EMPLEADO | Q5: TD | R5: TURNO DIURNO | S5: HD | T5: HORARIO DIURNO | U5: 46023 | V5: 14615 | W5: C | X5: Completa | Y5: 1 | Z5: 0 | AA5: 0 | AB5: 0 | AC5: 0 | AD5: 0 | AE5: 0 | AF5: 0 | AG5: 0 | AH5: 0 | AI5: 0 | AJ5: 0 | AO5: M | AP5: Soltero(a) | AQ5: 32245 | AR5: SND | AS5: 0 | AT5: PO001 | AU5: LIMA | AV5: URBANIZACIÓN JIRÓN MARTE 757 | AW5: 6000000 | BC5: 01 | BD5: LUNES-VIERNES | BE5: 11 | BF5: BBVA PERU | BG5: 11 | BH5: BBVA PERU | BI5: 01136600020033922424 | BJ5: A | BK5: Ahorro | BM5: NO | BN5: SIN RELACION SINDICAL | BO5: CM&CO | BP5: CLARKE, MODET & CO. PERU S.A.C. | BQ5: ME | BR5: 01 | BS5: CLARKE, MODET Y CO. PERÚ SAC | BT5: CMMX | BU5: COMISION MIXTA | BV5: ESCO | BW5: EDUCACIÓN SECUNDARIA COMPLETA | BX5: CMD | BY5: COUNTRY MANAGING DIRECTOR | BZ5: 012 | CA5: CEO | CB5: 007 | CC5: CEO | CD5: CM&CO | CE5: CLARKE, MODET & CO. PERU S.A.C. | CF5: 1045191394 | CG5: 322431AABAT4 | CH5: LINEA | CI5: LINEA | CJ5: 1045191394 | CK5: 8804121AABTA003 | CP5: 100 | CQ5: SAN ISIDRO | CR5: ST | CS5: SCTR | CT5: ES | CU5: ESSALUD | CV5: PT | CW5: PROFUTURO | CX5: ND | CY5: NO DEFINIDO | CZ5: NATHALIE | DA5: PE | DB5: PERUANO | DC5: 100 | DD5: SAN ISIDRO | DE5: OPI | DF5: OPERATIONS INVENTIONS | DH5: Activo | DI5: 46100 | DO5: PO001 | DP5: LIMA | DQ5: 1 | DR5: TN | DS5: TRANSFERENCIA | DU5: PO001 | DV5: LIMA | DW5: LIMA | DX5: PO001 | DY5: LIMA | DZ5: 14615 | EA5: 60.895833 | EC5: Normal | ED5: N | EE5: 0 | EF5: 14615 | EG5: 45 | EH5: 0 | EM5: 0 | EN5: 0.522% | EO5: Ahorros | EP5: Propia | EQ5: CLARKE, MODET Y CO. PERÚ SAC | ER5: 01 | ES5: BANCO CENTRAL RESERVA DEL PERÚ | ET5: 0123456789 | EU5: S | EW5: PERU | FA5: 0 | FL5: 0 | FN5: 42989 | FO5: 20170911
A6: 1046129072 | B6: 46129072 | C6: D | D6: LIBRETA ELECTORAL O DNI | E6: LIRA CANDIA | F6: LAURA CAROLINA | G6: PF | H6: PLAZO FIJO | I6: 401768 | J6: 42765 | K6: 42765 | L6: DP1 | M6: L5 | N6: SUELDO FIJO | O6: EMP | P6: EMPLEADO | Q6: TD | R6: TURNO DIURNO | S6: HD | T6: HORARIO DIURNO | U6: 46023 | V6: 3871 | W6: C | X6: Completa | Y6: 1 | Z6: 0 | AA6: 0 | AB6: 0 | AC6: 0 | AD6: 0 | AE6: 0 | AF6: 0 | AG6: 0 | AH6: 0 | AI6: 0 | AJ6: 0 | AO6: F | AP6: Soltero(a) | AQ6: 32891 | AR6: SND | AS6: 0 | AT6: PO001 | AU6: LIMA | AV6: JIRÓN ENRIQUE OPPENHEIMER 141 | AW6: 6000000 | BC6: 01 | BD6: LUNES-VIERNES | BE6: 11 | BF6: BBVA PERU | BG6: 11 | BH6: BBVA PERU | BI6: 01105700022883967270 | BJ6: A | BK6: Ahorro | BM6: NO | BN6: SIN RELACION SINDICAL | BO6: CM&CO | BP6: CLARKE, MODET & CO. PERU S.A.C. | BQ6: ME | BR6: 01 | BS6: CLARKE, MODET Y CO. PERÚ SAC | BT6: CMMX | BU6: COMISION MIXTA | BV6: GDBA | BW6: GRADO DE BACHILLER | BX6: IPS | BY6: IP PROSECUTION SPECIALIST | BZ6: 029 | CA6: CENTRAL SERVICES | CB6: 002 | CC6: CENTRAL SERVICES | CD6: CM&CO | CE6: CLARKE, MODET & CO. PERU S.A.C. | CF6: 1046129072 | CG6: 628890LLCAD9 | CH6: LINEA | CI6: LINEA | CJ6: 1046129072 | CK6: 9001180LACDL001 | CP6: 100 | CQ6: SAN ISIDRO | CR6: ST | CS6: SCTR | CT6: ES | CU6: ESSALUD | CV6: HA | CW6: HABITAT | CX6: ND | CY6: NO DEFINIDO | CZ6: NATHALIE | DA6: PE | DB6: PERUANO | DC6: 100 | DD6: SAN ISIDRO | DE6: OPE | DF6: OPERATIONS | DH6: Activo | DI6: 46100 | DO6: PO001 | DP6: LIMA | DQ6: 1 | DR6: TN | DS6: TRANSFERENCIA | DU6: PO001 | DV6: LIMA | DW6: LIMA | DX6: PO001 | DY6: LIMA | DZ6: 3871 | EA6: 16.129167 | EC6: Normal | ED6: N | EE6: 0 | EF6: 3871 | EG6: 31 | EH6: 0 | EM6: 0 | EN6: 0.522% | EO6: Ahorros | EP6: Propia | EQ6: CLARKE, MODET Y CO. PERÚ SAC | ER6: 01 | ES6: BANCO CENTRAL RESERVA DEL PERÚ | ET6: 0123456789 | EU6: S | EW6: PERU | FA6: 0 | FL6: 0 | FN6: 42765 | FO6: 20170130
A7: 1046722547 | B7: 46722547 | C7: D | D7: LIBRETA ELECTORAL O DNI | E7: KOO RIOJA | F7: FELIX ALEJANDRO | G7: PI | H7: PLAZO INDETERMINADO | J7: 44151 | K7: 44151 | L7: DP1 | M7: L5 | N7: SUELDO FIJO | O7: EMP | P7: EMPLEADO | Q7: TD | R7: TURNO DIURNO | S7: HD | T7: HORARIO DIURNO | U7: 46023 | V7: 5733 | W7: C | X7: Completa | Y7: 1 | Z7: 0 | AA7: 0 | AB7: 0 | AC7: 0 | AD7: 0 | AE7: 0 | AF7: 0 | AG7: 0 | AH7: 0 | AI7: 0 | AJ7: 0 | AO7: M | AP7: Soltero(a) | AQ7: 33233 | AR7: SND | AS7: 0 | AT7: PO001 | AU7: LIMA | AV7: AVENIDA LA MOLINA 1785, SOL DE LA MOLINA 0 | AW7: 6000000 | AX7: 924120490 | BC7: 01 | BD7: LUNES-VIERNES | BE7: 09 | BF7: SCOTIABANK | BG7: 09 | BH7: SCOTIABANK | BI7: 8330844338 | BJ7: A | BK7: Ahorro | BM7: NO | BN7: SIN RELACION SINDICAL | BO7: CM&CO | BP7: CLARKE, MODET & CO. PERU S.A.C. | BQ7: ME | BR7: 01 | BS7: CLARKE, MODET Y CO. PERÚ SAC | BT7: CMMX | BU7: COMISION MIXTA | BV7: UNCO | BW7: UNIVERSIDAD COMPLETA | BX7: FAS | BY7: FINANCE & ACCOUNTING SPECIALIST | BZ7: 007 | CA7: FINANCIERO | CB7: 005 | CC7: FINANZAS | CD7: CM&CO | CE7: CLARKE, MODET & CO. PERU S.A.C. | CF7: 1046722547 | CG7: 632311FKROJ0 | CH7: LINEA | CI7: LINEA | CJ7: 1046722547 | CK7: 9012261KORJF003 | CP7: 100 | CQ7: SAN ISIDRO | CR7: ST | CS7: SCTR | CT7: ES | CU7: ESSALUD | CV7: IN | CW7: INTEGRA | CX7: ND | CY7: NO DEFINIDO | CZ7: NATHALIE | DA7: PE | DB7: PERUANO | DC7: 100 | DD7: SAN ISIDRO | DE7: FAC | DF7: FACILITIES | DH7: Activo | DI7: 46101 | DO7: PO001 | DP7: LIMA | DQ7: 1 | DR7: TN | DS7: TRANSFERENCIA | DU7: PO001 | DV7: LIMA | DW7: LIMA | DX7: PO001 | DY7: LIMA | DZ7: 5733 | EA7: 23.8875 | EC7: Normal | ED7: N | EE7: 0 | EF7: 5733 | EG7: 34 | EH7: 0 | EM7: 0 | EN7: 0.522% | EO7: Ahorros | EP7: Propia | EQ7: CLARKE, MODET Y CO. PERÚ SAC | ER7: 01 | ES7: BANCO CENTRAL RESERVA DEL PERÚ | ET7: 0123456789 | EU7: S | EW7: PERU | FA7: 0 | FL7: 0 | FN7: 44151 | FO7: 20201116
A8: 1047924040 | B8: 47924040 | C8: D | D8: LIBRETA ELECTORAL O DNI | E8: NEYRA ELLIOT | F8: MARÍA DEL CARMEN | G8: PI | H8: PLAZO INDETERMINADO | J8: 42632 | K8: 42632 | L8: DP1 | M8: L5 | N8: SUELDO FIJO | O8: EMP | P8: EMPLEADO | Q8: TD | R8: TURNO DIURNO | S8: HD | T8: HORARIO DIURNO | U8: 46023 | V8: 6552 | W8: C | X8: Completa | Y8: 1 | Z8: 0 | AA8: 0 | AB8: 0 | AC8: 0 | AD8: 0 | AE8: 0 | AF8: 0 | AG8: 0 | AH8: 0 | AI8: 0 | AJ8: 0 | AO8: F | AP8: Soltero(a) | AQ8: 34166 | AR8: SND | AS8: 0 | AT8: PO001 | AU8: LIMA | AV8: URBANIZACIÓN JIRÓN AUSTRIA 1206 | AW8: 6010101 | AX8: 986345478 | BC8: 01 | BD8: LUNES-VIERNES | BE8: 11 | BF8: BBVA PERU | BG8: 11 | BH8: BBVA PERU | BI8: 01105700022619663471 | BJ8: A | BK8: Ahorro | BM8: NO | BN8: SIN RELACION SINDICAL | BO8: CM&CO | BP8: CLARKE, MODET & CO. PERU S.A.C. | BQ8: ME | BR8: 01 | BS8: CLARKE, MODET Y CO. PERÚ SAC | BT8: CMMX | BU8: COMISION MIXTA | BV8: UNCO | BW8: UNIVERSIDAD COMPLETA | BX8: QPM | BY8: QUALITY PROCESS MANAGER | BZ8: 026 | CA8: OPERATIONS | CB8: 010 | CC8: OPERATIONS | CD8: CM&CO | CE8: CLARKE, MODET & CO. PERU S.A.C. | CF8: 1047924040 | CG8: 641640MNERI3 | CH8: LINEA | CI8: LINEA | CJ8: 1047924040 | CK8: 9307160NREIM001 | CP8: 100 | CQ8: SAN ISIDRO | CR8: ST | CS8: SCTR | CT8: ES | CU8: ESSALUD | CV8: HA | CW8: HABITAT | CX8: ND | CY8: NO DEFINIDO | CZ8: NATHALIE | DA8: PE | DB8: PERUANO | DC8: 100 | DD8: SAN ISIDRO | DE8: OPE | DF8: OPERATIONS | DH8: Activo | DI8: 46100 | DO8: PO001 | DP8: LIMA | DQ8: 1 | DR8: TN | DS8: TRANSFERENCIA | DU8: PO001 | DV8: LIMA | DW8: LIMA | DX8: PO001 | DY8: LIMA | DZ8: 6552 | EA8: 27.3 | EC8: Normal | ED8: N | EE8: 0 | EF8: 6552 | EG8: 18 | EH8: 0 | EM8: 0 | EN8: 0.522% | EO8: Ahorros | EP8: Propia | EQ8: CLARKE, MODET Y CO. PERÚ SAC | ER8: 01 | ES8: BANCO CENTRAL RESERVA DEL PERÚ | ET8: 0123456789 | EU8: S | EW8: PERU | FA8: 0 | FL8: 0 | FN8: 42632 | FO8: 20160919
A9: 1070165336 | B9: 70165336 | C9: D | D9: LIBRETA ELECTORAL O DNI | E9: FERNANDEZ CASTILLO | F9: VICTOR DANIEL | G9: PI | H9: PLAZO INDETERMINADO | J9: 44623 | K9: 44623 | L9: DP1 | M9: L5 | N9: SUELDO FIJO | O9: EMP | P9: EMPLEADO | Q9: TD | R9: TURNO DIURNO | S9: HD | T9: HORARIO DIURNO | U9: 46023 | V9: 4099 | W9: C | X9: Completa | Y9: 1 | Z9: 0 | AA9: 0 | AB9: 0 | AC9: 0 | AD9: 0 | AE9: 0 | AF9: 0 | AG9: 0 | AH9: 0 | AI9: 0 | AJ9: 0 | AO9: M | AP9: Soltero(a) | AQ9: 34064 | AR9: SND | AS9: 0 | AT9: PO001 | AU9: LIMA | AV9: PARQUE RAIMONDI N° 234, DISTRITO DE BARRANCO, LIMA | AW9: 6020202 | BC9: 01 | BD9: LUNES-VIERNES | BE9: 02 | BF9: CREDITO | BG9: 02 | BH9: CREDITO | BI9: 19407201792036 | BJ9: A | BK9: Ahorro | BM9: NO | BN9: SIN RELACION SINDICAL | BO9: CM&CO | BP9: CLARKE, MODET & CO. PERU S.A.C. | BQ9: ME | BR9: 01 | BS9: CLARKE, MODET Y CO. PERÚ SAC | BT9: CMMX | BU9: COMISION MIXTA | BV9: SEFO | BW9: SIN EDUCACIÓN FORMAL | BX9: PSP | BY9: PATENT SPECIALIST | BZ9: 028 | CA9: OPERATIONS INVENTIONS | CB9: 011 | CC9: INVENTIONS | CD9: CM&CO | CE9: CLARKE, MODET & CO. PERU S.A.C. | CF9: 1070165336 | CG9: 640621VFCNT9 | CH9: STAFF | CI9: STAFF | CJ9: 1070165336 | CK9: N/A | CP9: 100 | CQ9: SAN ISIDRO | CR9: ST | CS9: SCTR | CT9: ES | CU9: ESSALUD | CV9: HA | CW9: HABITAT | CX9: ND | CY9: NO DEFINIDO | CZ9: NATHALIE | DA9: PE | DB9: PERUANO | DC9: 100 | DD9: SAN ISIDRO | DE9: OPV | DF9: OPERATIVA | DH9: Activo | DI9: 46100 | DO9: PO001 | DP9: LIMA | DQ9: 1 | DR9: TN | DS9: TRANSFERENCIA | DU9: PO001 | DV9: LIMA | DW9: LIMA | DX9: PO001 | DY9: LIMA | DZ9: 4099 | EA9: 17.079167 | EC9: Normal | ED9: N | EE9: 0 | EF9: 4099 | EG9: 2 | EH9: 0 | EM9: 0 | EN9: 0.522% | EO9: Ahorros | EP9: Propia | EQ9: CLARKE, MODET Y CO. PERÚ SAC | ER9: 01 | ES9: BANCO CENTRAL RESERVA DEL PERÚ | ET9: 0123456789 | EU9: S | EW9: PERU | FA9: 0 | FL9: 0 | FN9: 44623 | FO9: 20220303
A10: 1070680748 | B10: 70680748 | C10: D | D10: LIBRETA ELECTORAL O DNI | E10: SOLANO CARRILLO | F10: LIZ VALERIA | G10: PI | H10: PLAZO INDETERMINADO | J10: 44879 | K10: 44879 | L10: DP1 | M10: L5 | N10: SUELDO FIJO | O10: EMP | P10: EMPLEADO | U10: 46023 | V10: 6125 | W10: C | X10: Completa | Y10: 1 | Z10: 0 | AA10: 0 | AB10: 0 | AC10: 0 | AD10: 0 | AE10: 0 | AF10: 0 | AG10: 0 | AH10: 0 | AI10: 0 | AJ10: 0 | AO10: F | AP10: Soltero(a) | AQ10: 33055 | AR10: SND | AS10: 0 | AT10: 00000 | AU10: NO DEFINIDO | AW10: 12347568 | AX10: 1234567 | BA10: VSolano@clarkemodet.com | BC10: 01 | BD10: LUNES-VIERNES | BE10: 03 | BF10: INTERBANK | BG10: 03 | BH10: INTERBANK | BI10: 00326901316365802789 | BJ10: A | BK10: Ahorro | BM10: NO | BN10: SIN RELACION SINDICAL | BO10: CM&CO | BP10: CLARKE, MODET & CO. PERU S.A.C. | BQ10: ME | BR10: 01 | BS10: CLARKE, MODET Y CO. PERÚ SAC | BT10: PONP | BU10: PENSION ONP | BV10: UNCO | BW10: UNIVERSIDAD COMPLETA | BX10: P019 | BY10: IP SPECIALIST | BZ10: 027 | CA10: TRADEMARK | CB10: 003 | CC10: TRADEMARKS | CD10: CM&CO | CE10: CLARKE, MODET & CO. PERU S.A.C. | CH10: APOYO | CI10: APOYO | CP10: 100 | CQ10: SAN ISIDRO | CR10: ST | CS10: SCTR | CT10: ES | CU10: ESSALUD | CV10: ON | CW10: ONP | CZ10: NATHALIE | DA10: PE | DB10: PERUANO | DC10: 100 | DD10: SAN ISIDRO | DE10: ADM | DF10: ADMINISTRACION | DH10: Activo | DI10: 46100 | DO10: PO001 | DP10: LIMA | DQ10: 1 | DR10: TN | DS10: TRANSFERENCIA | DU10: PO001 | DV10: LIMA | DW10: LIMA | DX10: PO001 | DY10: LIMA | DZ10: 6125 | EA10: 25.520833 | EC10: Normal | ED10: N | EE10: 0 | EF10: 6125 | EG10: 8 | EH10: 0 | EM10: 0 | EN10: 0.522% | EO10: Ahorros | EP10: Propia | EQ10: CLARKE, MODET Y CO. PERÚ SAC | ER10: 01 | ES10: BANCO CENTRAL RESERVA DEL PERÚ | ET10: 0123456789 | EU10: S | EW10: COLOMBIA | FA10: 0 | FL10: 0 | FN10: 44879 | FO10: 20221114
A11: 1072251509 | B11: 72251509 | C11: D | D11: LIBRETA ELECTORAL O DNI | E11: HUAMAN TORRES | F11: CYNTHIA FIORELLA | G11: PI | H11: PLAZO INDETERMINADO | J11: 43241 | K11: 43241 | L11: DP1 | M11: L5 | N11: SUELDO FIJO | O11: EMP | P11: EMPLEADO | Q11: TD | R11: TURNO DIURNO | S11: HD | T11: HORARIO DIURNO | U11: 46023 | V11: 4631 | W11: C | X11: Completa | Y11: 1 | Z11: 0 | AA11: 0 | AB11: 0 | AC11: 0 | AD11: 0 | AE11: 0 | AF11: 0 | AG11: 0 | AH11: 0 | AI11: 0 | AJ11: 0 | AO11: F | AP11: Soltero(a) | AQ11: 33141 | AR11: SND | AS11: 0 | AT11: PO001 | AU11: LIMA | AV11: URBANIZACIÓN AVENIDA ANDRES RAZURI 344 | AW11: 6702020 | BC11: 01 | BD11: LUNES-VIERNES | BE11: 11 | BF11: BBVA PERU | BG11: 11 | BH11: BBVA PERU | BI11: 01115600020057152474 | BJ11: A | BK11: Ahorro | BM11: NO | BN11: SIN RELACION SINDICAL | BO11: CM&CO | BP11: CLARKE, MODET & CO. PERU S.A.C. | BQ11: ME | BR11: 01 | BS11: CLARKE, MODET Y CO. PERÚ SAC | BT11: CMMX | BU11: COMISION MIXTA | BV11: ESCO | BW11: EDUCACIÓN SECUNDARIA COMPLETA | BX11: PSP | BY11: PATENT SPECIALIST | BZ11: 028 | CA11: OPERATIONS INVENTIONS | CB11: 011 | CC11: INVENTIONS | CD11: CM&CO | CE11: CLARKE, MODET & CO. PERU S.A.C. | CF11: 1072251509 | CG11: 631390CHTMR2 | CH11: LINEA | CI11: LINEA | CJ11: 1072251509 | CK11: 9009250HMTRC002 | CP11: 100 | CQ11: SAN ISIDRO | CR11: ST | CS11: SCTR | CT11: ES | CU11: ESSALUD | CV11: HA | CW11: HABITAT | CX11: ND | CY11: NO DEFINIDO | CZ11: NATHALIE | DA11: PE | DB11: PERUANO | DC11: 100 | DD11: SAN ISIDRO | DE11: OPI | DF11: OPERATIONS INVENTIONS | DH11: Activo | DI11: 46100 | DO11: PO001 | DP11: LIMA | DQ11: 1 | DR11: TN | DS11: TRANSFERENCIA | DU11: PO001 | DV11: LIMA | DW11: LIMA | DX11: PO001 | DY11: LIMA | DZ11: 4631 | EA11: 19.295833 | EC11: Normal | ED11: N | EE11: 0 | EF11: 4631 | EG11: 10 | EH11: 0 | EM11: 0 | EN11: 0.522% | EO11: Ahorros | EP11: Propia | EQ11: CLARKE, MODET Y CO. PERÚ SAC | ER11: 01 | ES11: BANCO CENTRAL RESERVA DEL PERÚ | ET11: 0123456789 | EU11: S | EW11: PERU | FA11: 0 | FL11: 0 | FN11: 43241 | FO11: 20180521
A12: 1077485287 | B12: 77485287 | C12: D | D12: LIBRETA ELECTORAL O DNI | E12: CADILLO BRITO | F12: ZULEMA BELINDA | G12: PI | H12: PLAZO INDETERMINADO | J12: 45323 | K12: 45323 | L12: DP1 | M12: L5 | N12: SUELDO FIJO | O12: EMP | P12: EMPLEADO | Q12: TD | R12: TURNO DIURNO | S12: HD | T12: HORARIO DIURNO | U12: 46023 | V12: 2142 | W12: C | X12: Completa | Y12: 1 | Z12: 0 | AA12: 0 | AB12: 0 | AC12: 0 | AD12: 0 | AE12: 0 | AF12: 0 | AG12: 0 | AH12: 0 | AI12: 0 | AJ12: 0 | AO12: F | AP12: No definido | AQ12: 35563 | AR12: SND | AS12: 0 | AT12: PO001 | AU12: LIMA | AW12: 123456789101 | AX12: 123456789101 | BC12: 01 | BD12: LUNES-VIERNES | BE12: 02 | BF12: CREDITO | BG12: 02 | BH12: CREDITO | BI12: 19471432597036 | BJ12: A | BK12: Ahorro | BM12: NO | BN12: SIN RELACION SINDICAL | BO12: CM&CO | BP12: CLARKE, MODET & CO. PERU S.A.C. | BQ12: ME | BR12: 01 | BS12: CLARKE, MODET Y CO. PERÚ SAC | BT12: CM&CO | BU12: CLARKE, MODET & CO. PERU S.A.C. | BV12: UNCO | BW12: UNIVERSIDAD COMPLETA | BX12: IPS | BY12: IP PROSECUTION SPECIALIST | BZ12: 029 | CA12: CENTRAL SERVICES | CB12: 002 | CC12: CENTRAL SERVICES | CD12: CM&CO | CE12: CLARKE, MODET & CO. PERU S.A.C. | CF12: 1077485287 | CG12: 655610ZCBIT4 | CH12: LINEA | CI12: LINEA | CJ12: CM&CO | CK12: CLARKE, MODET & CO. PERU S.A.C. | CP12: 100 | CQ12: SAN ISIDRO | CR12: ST | CS12: SCTR | CT12: ES | CU12: ESSALUD | CV12: PR | CW12: PRIMA | CX12: ND | CY12: NO DEFINIDO | CZ12: NATHALIE | DA12: PE | DB12: PERUANO | DC12: 100 | DD12: SAN ISIDRO | DE12: FAC | DF12: FACILITIES | DH12: Activo | DI12: 46100 | DO12: PO001 | DP12: LIMA | DQ12: 1 | DR12: TN | DS12: TRANSFERENCIA | DU12: PO001 | DV12: LIMA | DW12: LIMA | DX12: PO001 | DY12: LIMA | DZ12: 2142 | EA12: 8.925 | EC12: Normal | ED12: N | EE12: 0 | EF12: 2142 | EG12: 14 | EH12: 0 | EM12: 0 | EN12: 0.522% | EO12: Ahorros | EP12: Propia | EQ12: CLARKE, MODET Y CO. PERÚ SAC | ER12: 02 | ES12: CREDITO | ET12: 00219300213983600318 | EU12: D | EW12: PERU | FA12: 0 | FL12: 0 | FN12: 45323 | FO12: 20240201
A13: 2001252358 | B13: 001252358 | C13: E | D13: CARNET DE EXTRANJERIA | E13: MARQUIS XXX | F13: JOSE NORBERT | G13: PI | H13: PLAZO INDETERMINADO | J13: 42438 | K13: 42438 | L13: DP1 | M13: L5 | N13: SUELDO FIJO | O13: EMP | P13: EMPLEADO | Q13: TD | R13: TURNO DIURNO | S13: HD | T13: HORARIO DIURNO | U13: 46023 | V13: 6644 | W13: C | X13: Completa | Y13: 1 | Z13: 0 | AA13: 0 | AB13: 0 | AC13: 0 | AD13: 0 | AE13: 0 | AF13: 0 | AG13: 0 | AH13: 0 | AI13: 0 | AJ13: 0 | AO13: M | AP13: Soltero(a) | AQ13: 32801 | AR13: SND | AS13: 0 | AT13: FA001 | AU13: PARIS | AV13: ZONA INDUSTRIAL CALLE PEDRO DENEGRI 130 INT 304 | AW13: 111111111111 | AX13: 989559279 | BC13: 01 | BD13: LUNES-VIERNES | BE13: 09 | BF13: SCOTIABANK | BG13: 09 | BH13: SCOTIABANK | BI13: 00972420831167877863 | BJ13: A | BK13: Ahorro | BM13: NO | BN13: SIN RELACION SINDICAL | BO13: CM&CO | BP13: CLARKE, MODET & CO. PERU S.A.C. | BQ13: ME | BR13: 01 | BS13: CLARKE, MODET Y CO. PERÚ SAC | BT13: CMMX | BU13: COMISION MIXTA | BV13: UNCO | BW13: UNIVERSIDAD COMPLETA | BX13: P019 | BY13: IP SPECIALIST | BZ13: 027 | CA13: TRADEMARK | CB13: 011 | CC13: INVENTIONS | CD13: CM&CO | CE13: CLARKE, MODET & CO. PERU S.A.C. | CF13: 2001252358 | CG13: 627991JMXQX0 | CH13: LINEA | CI13: LINEA | CJ13: 2001252358 | CK13: 8910201MQXXJ002 | CP13: 100 | CQ13: SAN ISIDRO | CR13: ST | CS13: SCTR | CT13: ES | CU13: ESSALUD | CV13: HA | CW13: HABITAT | CX13: ND | CY13: NO DEFINIDO | CZ13: NATHALIE | DA13: PE | DB13: PERUANO | DC13: 100 | DD13: SAN ISIDRO | DE13: OPE | DF13: OPERATIONS | DH13: Activo | DI13: 46100 | DO13: PO001 | DP13: LIMA | DQ13: 1 | DR13: TN | DS13: TRANSFERENCIA | DU13: PO001 | DV13: LIMA | DW13: LIMA | DX13: PO001 | DY13: LIMA | DZ13: 6644 | EA13: 27.683333 | EC13: Normal | ED13: N | EE13: 0 | EF13: 6644 | EG13: 12 | EH13: 0 | EM13: 0 | EN13: 0.522% | EO13: Ahorros | EP13: Propia | EQ13: CLARKE, MODET Y CO. PERÚ SAC | ER13: 01 | ES13: BANCO CENTRAL RESERVA DEL PERÚ | ET13: 0123456789 | EU13: S | EW13: FRANCIA | FA13: 0 | FL13: 0 | FN13: 42438 | FO13: 20160309
A14: 42115329 | B14: 42115329 | C14: D | D14: LIBRETA ELECTORAL O DNI | E14: SOTO LLOCLLA | F14: SARA MILAGROS | G14: PI | H14: PLAZO INDETERMINADO | J14: 45740 | K14: 45740 | L14: DP1 | M14: L5 | N14: SUELDO FIJO | O14: EMP | P14: EMPLEADO | Q14: TD | R14: TURNO DIURNO | S14: HD | T14: HORARIO DIURNO | U14: 46023 | V14: 3090 | W14: C | X14: Completa | Y14: 1 | Z14: 0 | AA14: 0 | AB14: 0 | AC14: 0 | AD14: 0 | AE14: 0 | AF14: 0 | AG14: 0 | AH14: 0 | AI14: 0 | AJ14: 0 | AO14: F | AP14: Soltero(a) | AQ14: 30617 | AR14: SND | AS14: 0 | AT14: PO001 | AU14: LIMA | AV14: OTRA NOMENCLATURA JR LA OROYA MZ 2 LOTE COOP LA | AW14: 000000000000 | AX14: 0000000 | AY14: 0000000 | BC14: 01 | BD14: LUNES-VIERNES | BE14: 02 | BF14: CREDITO | BG14: 02 | BH14: CREDITO | BI14: 19101190765092 | BJ14: A | BK14: Ahorro | BM14: NO | BN14: SIN RELACION SINDICAL | BO14: CM&CO | BP14: CLARKE, MODET & CO. PERU S.A.C. | BQ14: ME | BR14: 01 | BS14: CLARKE, MODET Y CO. PERÚ SAC | BT14: CFIN | BU14: COMISION FLUJO INTEGRA | BV14: UNCO | BW14: UNIVERSIDAD COMPLETA | BX14: IPS | BY14: IP PROSECUTION SPECIALIST | BZ14: 029 | CA14: CENTRAL SERVICES | CB14: 002 | CC14: CENTRAL SERVICES | CD14: CM&CO | CE14: CLARKE, MODET & CO. PERU S.A.C. | CF14: FAC | CG14: FACILITIES | CH14: LINEA | CI14: LINEA | CJ14: CM&CO | CK14: CLARKE, MODET & CO. PERU S.A.C. | CP14: 100 | CQ14: SAN ISIDRO | CR14: ST | CS14: SCTR | CT14: ES | CU14: ESSALUD | CV14: IN | CW14: INTEGRA | CZ14: NATHALIE | DA14: PE | DB14: PERUANO | DC14: 100 | DD14: SAN ISIDRO | DE14: FAC | DF14: FACILITIES | DH14: Activo | DI14: 46100 | DO14: PO001 | DP14: LIMA | DQ14: 1 | DR14: TN | DS14: TRANSFERENCIA | DU14: PO001 | DV14: LIMA | DW14: LIMA | DX14: PO001 | DY14: LIMA | DZ14: 3090 | EA14: 12.875 | EC14: Normal | ED14: N | EE14: 0 | EF14: 3090 | EG14: 0 | EH14: 0 | EL14: Av. Conquistadores 1136 Int 304 | EM14: 0 | EN14: 0.522% | EO14: Ahorros | EP14: Propia | EQ14: CLARKE, MODET Y CO. PERÚ SAC | ER14: 01 | ES14: BANCO CENTRAL RESERVA DEL PERÚ | ET14: 0123456789 | EU14: S | EW14: PERU | FA14: 0 | FL14: 0 | FN14: 45740 | FO14: 20250324
A15: 42683912 | B15: 42683912 | C15: D | D15: LIBRETA ELECTORAL O DNI | E15: HIRAOKA MARINA | F15: GUILLERMO HENRY | G15: PI | H15: PLAZO INDETERMINADO | J15: 45637 | K15: 45637 | L15: DP1 | M15: L5 | N15: SUELDO FIJO | O15: EMP | P15: EMPLEADO | Q15: TD | R15: TURNO DIURNO | S15: HD | T15: HORARIO DIURNO | U15: 46023 | V15: 5768 | W15: C | X15: Completa | Y15: 1 | Z15: 0 | AA15: 0 | AB15: 0 | AC15: 0 | AD15: 0 | AE15: 0 | AF15: 0 | AG15: 0 | AH15: 0 | AI15: 0 | AJ15: 0 | AO15: M | AP15: Soltero(a) | AQ15: 30965 | AR15: SND | AS15: 0 | AT15: PO001 | AU15: LIMA | AV15: CALLE 54 154 URB CORPAC LIMA-LIMA-SAN ISIDRO | AW15: 00000000000 | AX15: 000000000000 | BC15: 01 | BD15: LUNES-VIERNES | BE15: 04 | BF15: BANBIF | BG15: 04 | BH15: BANBIF | BI15: 03810010803075125745 | BJ15: A | BK15: Ahorro | BM15: NO | BN15: SIN RELACION SINDICAL | BO15: CM&CO | BP15: CLARKE, MODET & CO. PERU S.A.C. | BQ15: ME | BR15: 01 | BS15: CLARKE, MODET Y CO. PERÚ SAC | BT15: CMMX | BU15: COMISION MIXTA | BV15: UNCO | BW15: UNIVERSIDAD COMPLETA | BX15: P019 | BY15: IP SPECIALIST | BZ15: 027 | CA15: TRADEMARK | CB15: 003 | CC15: TRADEMARKS | CD15: CM&CO | CE15: CLARKE, MODET & CO. PERU S.A.C. | CF15: 42683912 | CG15: 309631GHMAI4 | CH15: LINEA | CI15: LINEA | CP15: 100 | CQ15: SAN ISIDRO | CR15: ST | CS15: SCTR | CT15: ES | CU15: ESSALUD | CV15: HA | CW15: HABITAT | CZ15: NATHALIE | DA15: PE | DB15: PERUANO | DC15: 100 | DD15: SAN ISIDRO | DH15: Activo | DI15: 46100 | DO15: PO001 | DP15: LIMA | DQ15: 1 | DR15: TN | DS15: TRANSFERENCIA | DU15: PO001 | DV15: LIMA | DW15: LIMA | DX15: PO001 | DY15: LIMA | DZ15: 5768 | EA15: 24.033333 | EC15: Normal | ED15: N | EE15: 0 | EF15: 5768 | EG15: 29 | EH15: 0 | EM15: 0 | EN15: 0.522% | EO15: Ahorros | EP15: Propia | EQ15: CLARKE, MODET Y CO. PERÚ SAC | ER15: 02 | ES15: CREDITO | ET15: 00219300213983600318 | EU15: D | EW15: PERU | FA15: 0 | FL15: 0 | FN15: 45637 | FO15: 20241211
A16: 72836862 | B16: 72836862 | C16: D | D16: LIBRETA ELECTORAL O DNI | E16: MEJIA DOLORES | F16: JACKELINE NANCY | G16: PI | H16: PLAZO INDETERMINADO | J16: 45208 | K16: 45208 | L16: DP1 | M16: L5 | N16: SUELDO FIJO | O16: EMP | P16: EMPLEADO | Q16: TD | R16: TURNO DIURNO | U16: 46023 | V16: 2652 | W16: C | X16: Completa | Y16: 1 | Z16: 0 | AA16: 0 | AB16: 0 | AC16: 0 | AD16: 0 | AE16: 0 | AF16: 0 | AG16: 0 | AH16: 0 | AI16: 0 | AJ16: 0 | AO16: F | AP16: Soltero(a) | AQ16: 36368 | AR16: SND | AS16: 0 | AT16: PO001 | AU16: LIMA | AV16: BARRIO MZ. EL MIRADOR SHANCAYAN MZ.G INT. LT.11 URB. EL MIRADOR | AW16: 00000000000 | BA16: jackymejia1129@gmail.com | BC16: 01 | BD16: LUNES-VIERNES | BE16: 03 | BF16: INTERBANK | BG16: 03 | BH16: INTERBANK | BI16: 8983386275167 | BJ16: A | BK16: Ahorro | BM16: NO | BN16: SIN RELACION SINDICAL | BO16: CM&CO | BP16: CLARKE, MODET & CO. PERU S.A.C. | BQ16: ME | BR16: 01 | BS16: CLARKE, MODET Y CO. PERÚ SAC | BT16: CMMX | BU16: COMISION MIXTA | BV16: UNCO | BW16: UNIVERSIDAD COMPLETA | BX16: IPP | BY16: IP PROCUREMENT SPECIALIST | BZ16: 027 | CA16: TRADEMARK | CB16: 003 | CC16: TRADEMARKS | CD16: CM&CO | CE16: CLARKE, MODET & CO. PERU S.A.C. | CF16: 72836862 | CG16: 663680JMDIO1 | CH16: LINEA | CI16: LINEA | CJ16: CM&CO | CK16: CLARKE, MODET & CO. PERU S.A.C. | CL16: CCEPS | CM16: CON CREDITO EPS | CP16: 100 | CQ16: SAN ISIDRO | CR16: ST | CS16: SCTR | CT16: ES | CU16: ESSALUD | CV16: IN | CW16: INTEGRA | CZ16: NATHALIE | DA16: PE | DB16: PERUANO | DC16: 100 | DD16: SAN ISIDRO | DE16: OPE | DF16: OPERATIONS | DH16: Activo | DI16: 46100 | DO16: PO001 | DP16: LIMA | DQ16: 1 | DR16: TN | DS16: TRANSFERENCIA | DU16: PO001 | DV16: LIMA | DW16: LIMA | DX16: PO001 | DY16: LIMA | DZ16: 2652 | EA16: 11.05 | EC16: Normal | ED16: N | EE16: 0 | EF16: 2652 | EG16: 8 | EH16: 0 | EM16: 0 | EN16: 0.522% | EO16: Ahorros | EP16: Propia | EQ16: CLARKE, MODET Y CO. PERÚ SAC | ER16: 01 | ES16: BANCO CENTRAL RESERVA DEL PERÚ | ET16: 0123456789 | EU16: S | EW16: PERU | FA16: 0 | FL16: 0 | FN16: 45208 | FO16: 20231009
A17: 76607245 | B17: 76607245 | C17: D | D17: LIBRETA ELECTORAL O DNI | E17: CAICEDO ROSADO | F17: STEFFANY FELICIA | G17: PP | H17: PRACTICANTE PROFESIONAL | I17: 51136 | J17: 45740 | K17: 45740 | L17: AS2 | M17: SU | N17: SUBVENCION | O17: PRA | P17: PRACTICANTE | S17: HD | T17: HORARIO DIURNO | U17: 45740 | V17: 1130 | W17: C | X17: Completa | Y17: 1 | Z17: 0 | AA17: 0 | AB17: 0 | AC17: 0 | AD17: 0 | AE17: 0 | AF17: 0 | AG17: 0 | AH17: 0 | AI17: 0 | AJ17: 0 | AO17: F | AP17: Soltero(a) | AQ17: 38104 | AR17: SND | AS17: 0 | AT17: PO001 | AU17: LIMA | AW17: 00000 | AX17: 00000000 | AY17: 00000 | BC17: 01 | BD17: LUNES-VIERNES | BE17: 02 | BF17: CREDITO | BG17: 02 | BH17: CREDITO | BI17: 19406467626054 | BJ17: A | BK17: Ahorro | BM17: NO | BN17: SIN RELACION SINDICAL | BO17: CM&CO | BP17: CLARKE, MODET & CO. PERU S.A.C. | BQ17: ME | BR17: 01 | BS17: CLARKE, MODET Y CO. PERÚ SAC | BT17: CM&CO | BU17: CLARKE, MODET & CO. PERU S.A.C. | BV17: UNCO | BW17: UNIVERSIDAD COMPLETA | BX17: P030 | BY17: BECARIA | BZ17: 015 | CA17: FACILITIES | CB17: 008 | CC17: FACILITES | CD17: CM&CO | CE17: CLARKE, MODET & CO. PERU S.A.C. | CF17: FAC | CG17: FACILITIES | CH17: LINEA | CI17: LINEA | CJ17: CM&CO | CK17: CLARKE, MODET & CO. PERU S.A.C. | CP17: 100 | CQ17: SAN ISIDRO | CR17: ST | CS17: SCTR | CT17: ES | CU17: ESSALUD | CZ17: NATHALIE | DA17: PE | DB17: PERUANO | DC17: 100 | DD17: SAN ISIDRO | DE17: FAC | DF17: FACILITIES | DH17: Activo | DI17: 45772 | DO17: PO001 | DP17: LIMA | DQ17: 1 | DR17: TN | DS17: TRANSFERENCIA | DU17: PO001 | DV17: LIMA | DW17: LIMA | DX17: PO001 | DY17: LIMA | DZ17: 1130 | EA17: 4.7083333 | EC17: Normal | ED17: N | EE17: 0 | EF17: 1130 | EG17: 0 | EH17: 0 | EL17: Av. Conquistadores 1136 | EM17: 0 | EN17: 0.522% | EO17: Ahorros | EP17: Propia | EQ17: CLARKE, MODET Y CO. PERÚ SAC | ER17: 02 | ES17: CREDITO | ET17: 00219300213983600318 | EU17: D | EW17: PERU | FA17: 0 | FL17: 0 | FO17: 20250324
A18: 74026184 | B18: 74026184 | C18: D | D18: LIBRETA ELECTORAL O DNI | E18: FAJARDO APOLAYA | F18: JACKELINE TAMARA | G18: PR | H18: PRACTICANTE PRE-PROFESIONAL | I18: 46518 | J18: 46153 | K18: 46153 | L18: AS2 | M18: SU | N18: SUBVENCION | O18: PRA | P18: PRACTICANTE | Q18: TD | R18: TURNO DIURNO | S18: HD | T18: HORARIO DIURNO | U18: 46153 | V18: 1130 | W18: C | X18: Completa | Y18: 1 | Z18: 0 | AA18: 0 | AB18: 0 | AC18: 0 | AD18: 0 | AE18: 0 | AF18: 0 | AG18: 0 | AH18: 0 | AI18: 0 | AJ18: 0 | AO18: F | AP18: Soltero(a) | AQ18: 37410 | AR18: SND | AS18: 0 | AT18: PO001 | AU18: LIMA | AV18: OTRA NOMENCLATURA CALLE 4 LUIS SANCHEZ CERRO MZ A LT 16 | AW18: 00000000 | AX18: 000000000 | BC18: 01 | BD18: LUNES-VIERNES | BE18: 02 | BF18: CREDITO | BG18: 02 | BH18: CREDITO | BI18: 19406809861045 | BJ18: A | BK18: Ahorro | BM18: NO | BN18: SIN RELACION SINDICAL | BO18: CM&CO | BP18: CLARKE, MODET & CO. PERU S.A.C. | BQ18: ME | BR18: 01 | BS18: CLARKE, MODET Y CO. PERÚ SAC | BT18: CM&CO | BU18: CLARKE, MODET & CO. PERU S.A.C. | BV18: UNCO | BW18: UNIVERSIDAD COMPLETA | BX18: P030 | BY18: BECARIA | BZ18: 015 | CA18: FACILITIES | CB18: 008 | CC18: FACILITES | CD18: CM&CO | CE18: CLARKE, MODET & CO. PERU S.A.C. | CF18: FAC | CG18: FACILITIES | CH18: LINEA | CI18: LINEA | CJ18: CM&CO | CK18: CLARKE, MODET & CO. PERU S.A.C. | CL18: SCEPS | CM18: SIN CREDITO EPS | CP18: 100 | CQ18: SAN ISIDRO | CR18: ST | CS18: SCTR | CT18: ES | CU18: ESSALUD | CZ18: NATHALIE | DA18: PE | DB18: PERUANO | DC18: 100 | DD18: SAN ISIDRO | DE18: FAC | DF18: FACILITIES | DH18: Activo | DI18: 46164 | DO18: PO001 | DP18: LIMA | DR18: TN | DS18: TRANSFERENCIA | DU18: 11001 | DV18: BOGOTA D.C. | DW18: LIMA | DX18: PO001 | DY18: LIMA | DZ18: 1130 | EA18: 4.7083333 | EC18: Normal | ED18: N | EE18: 0 | EF18: 1130 | EG18: 0 | EH18: 0 | EM18: 0 | EN18: 0.522% | EO18: Ahorros | EP18: Propia | EQ18: CLARKE, MODET Y CO. PERÚ SAC | ER18: 01 | ES18: BANCO CENTRAL RESERVA DEL PERÚ | ET18: 0123456789 | EU18: S | EW18: PERU | FA18: 0 | FO18: 20260511
